Workbook
Name G872_: '攤位整理表 請在此填寫資訊'!$G$866

Sheet FF47 攤位整理表單操作手冊
B2: FF47 攤位整理表單 使用說明 | I2: 攤位名稱 | J2: 徵求寄攤 | K2: 第一天攤位編號 | L2: 第二天攤位編號 | M2: 第三天攤位編號 | N2: 筆名 | O2: 創作者類型 | P2: 商品年齡分類 (一般、R15 (明顯性暗示)、R18) | Q2: 作品類型 (原創、二創) | R2: 二創參考作品 (原創免填) | S2: 販售資訊 | T2: 商品備註 (特殊標籤) | U2: 場前印調 | V2: FB (1) | W2: FB (2) | X2: Bluesky(1) | Y2: Bluesky(2) | Z2: TWITTER (1) | AA2: TWITTER (2) | AB2: PLURK | AC2: Pixiv | AD2: Fanbox | AE2: Fantia | AF2: 可洛斯 | AG2: 其他贊助平台 | AH2: IG | AI2: YOUTUBE | AJ2: TWITCH | AK2: LINE | AL2: DISCORD | AM2: 巴哈姆特 | AN2: 官方網站 | AO2: Linktree等連結整合網頁 | AP2: 其他連結 | AQ2: 預告 | AR2: 品書 | AS2: 預購/通販 | AT2: 賣場 | AU2: 縮圖 | AV2: 有無縮圖 | AW2: 試閱
B4: 前言 | C4: 大家好! 這裡是加帕利天藍怪預警中心小編，也是場次攤位整理人員，在此歡迎各位攤主們使用攤位整理表單! 以下表格將跟各位講解有關如何使用此整理表單。如果沒有問題，可直接至「攤位整理表單 請在此填寫資料」試算表中填寫喔! 我們並非開拓官方，請注意。 | K4: 攤位位置 (我們已幫您填寫，若有誤請跟我們連繫) | N4: 攤主基本資訊 | P4: 販售詳細資訊 | W4: 網頁/社群網站SNS | AQ4: 本次販售資訊連結及賣場 | AU4: 呈現在攤位查詢網上的縮圖 | AW4: 本次販售資訊連結及賣場
B7: 表單結構 | C7: 攤位位置 | D7: 包含攤位編號、分區等，我們已經幫您導入了
I8: 表1, 攤位整理表單格式
C9: 攤主基本資訊 | D9: 包含您的筆名、創作者類型，創作者類型請見右表2，可自訂
C10: 販售詳細資訊 | D10: 年齡分級 (一般，R15，R18)，可複選 | I10: 表2. 創作者類型
D11: 作品類型 (原創? 二創?)。如果是二創，那麼二創的參考作品? (如蔚藍檔案等) | I11: 繪師 | J11: Coser | K11: Vtuber | L11: 寫手/作家 | M11: 音聲作品
I12: 模型製作 | J12: 代理社團 | K12: 手工藝品 | L12: 攝影相關 | M12: 遊戲作品
D13: 販售資訊，請列出你想要賣甚麼? 如同人誌、立牌、飯友等，可於商品後面標示價格。 | I13: 學生社團 | J13: Vtype
D14: 特殊標籤，如有特殊癖好如扶他、獸人、性轉，或是要標註男性女性向等，可列出 | I14: 整理進度說明
D15: 場前印調，場前印調部分就跟SNS的方式一樣，備註表單連結即可
C16: 社群網站連結 | D16: 您的社團、個人、品牌社群網站連結，詳細請見表1。填寫時，請填寫有效之網址，如果為多網址，請空一格後，將網址貼進來，不可在網址欄中加入非網址之文字，不然系統會無法識別而沒有更新。 | I16: 本次攤位整理新增區域 以下區域權限全面開放，不需使用加註功能
C17: 本次販售資訊連結 | D17: 請貼上您的預告、品書連結、預購通販、賣場、試閱連結 | I17: 集中宣傳區 | J17: 如果攤主要宣傳自家的周邊，可至此處進行宣傳喔
C18: 縮圖 | D18: 請貼上您打算在我們攤位查詢網中呈現的縮圖 Google 雲端連結 | I18: 印量調查區 | J18: 如果攤主要針對產品的印製數量進行調查，可至此處進行印調，印調的網址將會同步在攤位整理表中
D19: 格式: 橫式、尺寸 2:1，解析度至少 800x400px，檔案需使用Google雲端連結提供，並且需開共享。縮圖不可以瑟瑟! | I19: 交流區 | J19: 無論參加者還是攤主，都可以聊天交流之處
B21: 加 註 功 能 詳 細 使 用 教 學 | I21: 因徵求寄攤區可能會被開拓方監控，為避免起爭議，本屆暫停提供徵求寄攤區
B23: 一、如何使用註解/加註功能 | I23: 攤位整理不容易，歡迎贊助支持我們! :D
B24: 如何打開加註功能? 電腦版教學
I25: 其他場次的簡易攤位整理
I26: 贊助合作宣傳，讓加帕利幫你宣傳你的攤位資訊
I29: 距離開場 | J29: 46255.438 | M29: 剩下 | N29: =INT(J29 - J30) & " 日 " & HOUR(J29 - J30) & " 時 " & MINUTE(J29 - J30) & " 分 " & SECOND(J29 - J30) & " 秒 " -> 9 日 18 時 54 分 23 秒
I30: 現在時間 | J30: =NOW() -> 46245.65
C34: 第一步: 先選擇你想要填寫的格子，點選它 | F34: 點選左上角的「插入註解」也可達成相同效果喔
C35: 第二步: 按滑鼠右鍵，把選單叫出來
C36: 第三步: 點選「註解」
C37: 第四步: 此時便可填寫您的資料
B38: 如何打開加註功能? 手機版教學
J53: 你的測試地點 | K53: 上圖1. 成功叫出註解框的樣子
I54: 測試方格-->
I55: 您可以在上面方塊測試註解
C58: 第一步: 點選您要填寫的格子 | K58: 上圖2. 註解成功輸出的畫面
C59: 第二步: 點選右下角的「對話框」
C60: 第三步: 輸入註解
C61: 各位可至右上邊的測試欄位試試看喔!
B62: 二、資料填寫
B63: 假設今天有一個攤主要填寫資料，其資料如下表所示 (然後想在周日寄攤) | F63: 填寫步驟
F64: 第一步: 使用「CTRL+F」功能，尋找您的攤位 (手機請使用「尋找並取代」功能)
F67: 第二步: 進入到我們的攤位整理表單中
F69: 第三步: 使用「註解/加註」功能，將資料註解上去，填寫方式如右表4示範所示
F72: 第四步: 等待攤位整理人員將您的註解資料填寫上去
F74: 最終呈現
F75: 最後呈現在攤位查詢系統上面的資料如右圖3所示
F76: 若有不理解想詢問的，或是發現資料有誤，還請至下方連結處聯絡我們! | I76: 如對於本使用手冊還沒了解，可參考上面影片喔! (點此進去) | N76: 或是參考本投影片喔! (點此進去)
B79: 相 關 連 結
B80: 聯絡我們 | C80: 加帕利天藍怪預警中心 | E80: https://www.facebook.com/JapariWeatherBureau
C81: 品書機器人 | E81: https://www.facebook.com/profile.php?id=100005806961929 | I81: 表4. 模擬填寫表單的樣子
C82: 場次資訊中心噗浪 | E82: https://www.plurk.com/JWB_DoujinInfo | I82: 攤位名稱 | J82: 徵求寄攤 | K82: D1攤位編號 | L82: D2攤位編號 | M82: D3攤位編號 | N82: 筆名 | O82: 創作者類型 | P82: 商品年齡分類 (一般、R15 (明顯性暗示)、R18) | Q82: 作品類型 (原創、二創) | R82: 二創參考作品 (原創免填) | S82: 販售資訊 | T82: 商品備註 (特殊標籤) | U82: 場前印調 | V82: FB (1) | W82: FB (2) | X82: Bluesky(1) | Y82: Bluesky(2) | Z82: TWITTER (1) | AA82: TWITTER (2) | AB82: PLURK | AC82: Pixiv | AD82: Fanbox | AE82: Fantia | AF82: 可洛斯 | AG82: 其他贊助平台 | AH82: IG | AI82: YOUTUBE | AJ82: TWITCH | AK82: LINE | AL82: DISCORD | AM82: 巴哈姆特 | AN82: 官方網站 | AO82: Linktree等連結整合網頁 | AP82: 其他連結 | AR82: 品書 | AS82: 預購/通販 | AT82: 賣場 | AU82: 縮圖 | AV82: 有無縮圖 | AW82: 試閱
B83: 教學影片 | C83: https://www.facebook.com/share/v/12A3tfFQiyQ/ | I83: Sean的無重力實驗室 | J83: 禮拜天 | K83: A01 | L83: B01 | N83: Seanminecraft18 | O83: 繪師 | P83: R15,R18 | Q83: 二創 | R83: 點兔 | S83: 同人誌，立牌，吊飾 | T83: 飄浮戀物癖 | X83: https://bsky.app/profile/seanminecraft18.bsky.social | Z83: https://x.com/seanminecraft2 | AC83: https://www.pixiv.net/users/18206795 | AO83: https://linktr.ee/Seanminecraft | AR83: [品書連結] | AU83: [縮圖連結] | AV83: 有縮圖
B84: 投影片 | C84: https://drive.google.com/file/d/17wVJrLaJixwwdj-LHLeydoEY2MOL9AcL/view?usp=sharing
B85: 官網 | C85: https://sites.google.com/view/tw-doujin-event/%E5%90%8C%E4%BA%BA%E5%B1%95%E6%94%A4%E4%BD%8D%E6%9F%A5%E8%A9%A2%E7%B3%BB%E7%B5%B1?authuser=0
B86: 攤位查詢網 | C86: https://tw-doujin.info/
B87: 攤主問卷調查 | C87: https://forms.gle/ScKJpanKT1dp9DBU6

Sheet 攤位整理表 請在此填寫資訊
A1: 攤位名稱 | B1: 筆名 | C1: 第一天 | D1: 第二天 | E1: 第三天 | G1: 創作者類型 | H1: 商品年齡分類 | I1: 作品類型 (原創、二創) | J1: 二創參考作品 (原創免填) | K1: 販售資訊 | L1: 特殊標籤或備註 | M1: {={ "有無資料"; BYROW(S2:AM1337, LAMBDA(currRow, COUNTA(currRow)>0)) }} -> 有無資料 | N1: {={ "有無販售資訊"; BYROW(H2:L1337, LAMBDA(currRow,COUNTA(currRow)>0)) }} -> 有無販售資訊 | O1: {={"有無預告";MAP(AN2:AN1337, LAMBDA(cell, ISTEXT(cell)))}} -> 有無預告 | P1: {={"有無品書";MAP(AO2:AO1337, LAMBDA(cell, ISTEXT(cell)))}} -> 有無品書 | Q1: 資料信心度 | R1: 印量調查 請至印調區填寫 | S1: FB (1) | T1: FB (2) | U1: Bluesky (1) | V1: Bluesky (2) | W1: TWITTER (1) | X1: TWITTER (2) | Y1: PLURK | Z1: Pixiv | AA1: Fanbox | AB1: Fantia | AC1: 可洛斯 | AD1: 其他贊助平台 | AE1: IG | AF1: YOUTUBE | AG1: TWITCH | AH1: LINE | AI1: DISCORD | AJ1: 巴哈姆特 | AK1: 官方網站 | AL1: Linktree等連結整合網頁 | AM1: 其他連結 | AN1: 預告 | AO1: 品書 | AP1: 預購/通販 | AQ1: 縮圖[請備註] | AR1: 是否有縮圖 | AS1: 試閱
A2: 2.5 | E2: U43 | M2: FALSE | N2: FALSE | O2: FALSE | P2: FALSE | R2: {=IFERROR(INDEX('印量調查區'!G:G, MATCH(A2, '印量調查區'!A:A, 0)), "")} | AR2: =IFERROR(__xludf.DUMMYFUNCTION("IF(IFERROR(VLOOKUP(A2, IMPORTRANGE(""https://docs.google.com/spreadsheets/d/1f7uHQQgxgff8nh6aFDrh_cqkeFpcVPsvJILesm778_0"", ""工作表1!A:B""), 2, FALSE), """") <> """", ""有縮圖"", ""無縮圖"")"),"無縮圖") -> 無縮圖
A3: 825 | D3: T08 | G3: Coser | M3: FALSE | N3: FALSE | O3: FALSE | P3: FALSE | R3: {=IFERROR(INDEX('印量調查區'!G:G, MATCH(A3, '印量調查區'!A:A, 0)), "")} | AR3: =IFERROR(__xludf.DUMMYFUNCTION("IF(IFERROR(VLOOKUP(A3, IMPORTRANGE(""https://docs.google.com/spreadsheets/d/1f7uHQQgxgff8nh6aFDrh_cqkeFpcVPsvJILesm778_0"", ""工作表1!A:B""), 2, FALSE), """") <> """", ""有縮圖"", ""無縮圖"")"),"無縮圖") -> 無縮圖
A4: ‘-Sakimiya- | B4: 校工 | D4: N03 | G4: 繪師 | I4: 二創 | J4: 蔚藍檔案 / Blue Archive / ブルーアーカイブ | M4: TRUE | N4: TRUE | O4: FALSE | P4: FALSE | R4: {=IFERROR(INDEX('印量調查區'!G:G, MATCH(A4, '印量調查區'!A:A, 0)), "")} | W4: https://x.com/sakimiya_Hsu?t=jSZ9U8yrx9KsiNHAgOo6Iw&s=09 | Y4: https://www.plurk.com/sakimiya | Z4: https://www.pixiv.net/users/3029076 | AJ4: https://home.gamer.com.tw/profile/index.php?owner=p30000909120 | AL4: https://lit.link/zh-tw/sakimiyaHsu | AM4: https://skeb.jp/@sakimiya_Hsu | AR4: =IFERROR(__xludf.DUMMYFUNCTION("IF(IFERROR(VLOOKUP(A4, IMPORTRANGE(""https://docs.google.com/spreadsheets/d/1f7uHQQgxgff8nh6aFDrh_cqkeFpcVPsvJILesm778_0"", ""工作表1!A:B""), 2, FALSE), """") <> """", ""有縮圖"", ""無縮圖"")"),"無縮圖") -> 無縮圖
A5: [CHOCOLATE SHOP] | B5: CHOCO | C5: E19,E20 | D5: E19,E20 | G5: 繪師 | M5: TRUE | N5: FALSE | O5: FALSE | P5: FALSE | R5: {=IFERROR(INDEX('印量調查區'!G:G, MATCH(A5, '印量調查區'!A:A, 0)), "")} | W5: https://x.com/chocolateshop_i | Z5: https://www.pixiv.net/users/4768145 | AR5: =IFERROR(__xludf.DUMMYFUNCTION("IF(IFERROR(VLOOKUP(A5, IMPORTRANGE(""https://docs.google.com/spreadsheets/d/1f7uHQQgxgff8nh6aFDrh_cqkeFpcVPsvJILesm778_0"", ""工作表1!A:B""), 2, FALSE), """") <> """", ""有縮圖"", ""無縮圖"")"),"無縮圖") -> 無縮圖
A6: 【ZENTENG】 | E6: F02 | G6: 繪師 | M6: TRUE | N6: FALSE | O6: FALSE | P6: FALSE | R6: {=IFERROR(INDEX('印量調查區'!G:G, MATCH(A6, '印量調查區'!A:A, 0)), "")} | S6: https://www.facebook.com/Zen-Teng-214385615977145/ | AR6: =IFERROR(__xludf.DUMMYFUNCTION("IF(IFERROR(VLOOKUP(A6, IMPORTRANGE(""https://docs.google.com/spreadsheets/d/1f7uHQQgxgff8nh6aFDrh_cqkeFpcVPsvJILesm778_0"", ""工作表1!A:B""), 2, FALSE), """") <> """", ""有縮圖"", ""無縮圖"")"),"無縮圖") -> 無縮圖
A7: #DREAMProject [JooA Cosplay] | D7: Q23,Q24 | E7: Q23,Q24 | G7: Coser | M7: TRUE | N7: FALSE | O7: FALSE | P7: FALSE | R7: {=IFERROR(INDEX('印量調查區'!G:G, MATCH(A7, '印量調查區'!A:A, 0)), "")} | S7: https://www.facebook.com/dreamproject0079/?locale=zh_TW | AR7: =IFERROR(__xludf.DUMMYFUNCTION("IF(IFERROR(VLOOKUP(A7, IMPORTRANGE(""https://docs.google.com/spreadsheets/d/1f7uHQQgxgff8nh6aFDrh_cqkeFpcVPsvJILesm778_0"", ""工作表1!A:B""), 2, FALSE), """") <> """", ""有縮圖"", ""無縮圖"")"),"無縮圖") -> 無縮圖
A8: #DREAMProject Momo | B8: 毛毛 | D8: R39 | E8: R39 | G8: Coser | M8: TRUE | N8: FALSE | O8: FALSE | P8: FALSE | R8: {=IFERROR(INDEX('印量調查區'!G:G, MATCH(A8, '印量調查區'!A:A, 0)), "")} | S8: https://www.facebook.com/lovemolove | W8: https://twitter.com/lovemomosweet | AB8: https://fantia.jp/fanclubs/52892?locale=zh-tw | AE8: https://www.instagram.com/momo180_cos/ | AG8: https://www.twitch.tv/lovemomosweet | AL8: https://linktr.ee/lovemomosweet?utm_source=linktree_profile_share&ltsid=db415409-4786-4a29-a547-9cfc4302406b | AR8: =IFERROR(__xludf.DUMMYFUNCTION("IF(IFERROR(VLOOKUP(A8, IMPORTRANGE(""https://docs.google.com/spreadsheets/d/1f7uHQQgxgff8nh6aFDrh_cqkeFpcVPsvJILesm778_0"", ""工作表1!A:B""), 2, FALSE), """") <> """", ""有縮圖"", ""無縮圖"")"),"無縮圖") -> 無縮圖
A9: #DREAMProject Neneko | B9: 肉肉 | D9: R43,R44 | E9: R43,R44 | G9: Coser | M9: TRUE | N9: FALSE | O9: FALSE | P9: FALSE | R9: {=IFERROR(INDEX('印量調查區'!G:G, MATCH(A9, '印量調查區'!A:A, 0)), "")} | S9: https://www.facebook.com/neneko.page?locale=zh_TW | AR9: =IFERROR(__xludf.DUMMYFUNCTION("IF(IFERROR(VLOOKUP(A9, IMPORTRANGE(""https://docs.google.com/spreadsheets/d/1f7uHQQgxgff8nh6aFDrh_cqkeFpcVPsvJILesm778_0"", ""工作表1!A:B""), 2, FALSE), """") <> """", ""有縮圖"", ""無縮圖"")"),"無縮圖") -> 無縮圖
A10: #DREAMProject Shimo | B10: 霜月 | D10: R40,R41 | E10: R40,R41 | G10: Coser | K10: 寫真集 一番賞 現場拍立得 | M10: TRUE | N10: TRUE | O10: FALSE | P10: FALSE | R10: {=IFERROR(INDEX('印量調查區'!G:G, MATCH(A10, '印量調查區'!A:A, 0)), "")} | S10: https://www.facebook.com/shimotsuki18 | AR10: =IFERROR(__xludf.DUMMYFUNCTION("IF(IFERROR(VLOOKUP(A10, IMPORTRANGE(""https://docs.google.com/spreadsheets/d/1f7uHQQgxgff8nh6aFDrh_cqkeFpcVPsvJILesm778_0"", ""工作表1!A:B""), 2, FALSE), """") <> """", ""有縮圖"", ""無縮圖"")"),"無縮圖") -> 無縮圖
A11: #DREAMProject Usagi羽咲 | B11: 羽咲 | C11: Q02 [寄] | D11: R42 | E11: R42 | G11: Coser | H11: 一般 | I11: 二創 | J11: 蔚藍檔案 / Blue Archive / ブルーアーカイブ，百合園聖亞，紫羅蘭永恆花園 | K11: 聖亞套組 1-6 1500元 💠1、聖亞寫真集 600元 💠2、坐姿立牌 💠3、折疊圓鏡 💠4、貼紙組 100元 💠5、寫真照 200元 💠6、應援扇 200元 | M11: TRUE | N11: TRUE | O11: TRUE | P11: TRUE | R11: {=IFERROR(INDEX('印量調查區'!G:G, MATCH(A11, '印量調查區'!A:A, 0)), "")} | S11: https://www.facebook.com/UsagiTW | W11: https://twitter.com/Usagi__tw?t=ixuelpbn0R8uq7N9PL3bNg&s=09 | AE11: https://www.instagram.com/usagi_tw?utm_source=ig_web_button_share_sheet&igsh=ZDNlZDc0MzIxNw== | AN11: https://www.facebook.com/UsagiTW/posts/pfbid027P1pNzny93BpfJkRchjWgugGtUMV4JvQWj7vtkXJQyJ8AphQzBDdP3zwHhKtCD6rl https://www.facebook.com/100063575087204/posts/pfbid02ipi5ygnReXxwLB1yycyottdqReWTaFeKN8zYGWxxME3YynUdHsy8aXCH8NVWY3K4l/? https://www.facebook.com/UsagiTW/posts/pfbid02VK8d1bsnWPE1dELMHov3o96cUDd1AYJQjdsruEgdVfuH9ZGctCaEYTb6r4prz88yl | AO11: https://www.facebook.com/photo.php?fbid=1680506590745161&set=p.1680506590745161&type=3 | AP11: https://reurl.cc/dOWj6g | AR11: =IFERROR(__xludf.DUMMYFUNCTION("IF(IFERROR(VLOOKUP(A11, IMPORTRANGE(""https://docs.google.com/spreadsheets/d/1f7uHQQgxgff8nh6aFDrh_cqkeFpcVPsvJILesm778_0"", ""工作表1!A:B""), 2, FALSE), """") <> """", ""有縮圖"", ""無縮圖"")"),"無縮圖") -> 無縮圖
A12: +喵耳園魔法道具屋+ | G12: 手工藝品 | M12: TRUE | N12: FALSE | O12: FALSE | P12: FALSE | R12: {=IFERROR(INDEX('印量調查區'!G:G, MATCH(A12, '印量調查區'!A:A, 0)), "")} | AE12: https://www.instagram.com/cat_ears2007/ | AR12: =IFERROR(__xludf.DUMMYFUNCTION("IF(IFERROR(VLOOKUP(A12, IMPORTRANGE(""https://docs.google.com/spreadsheets/d/1f7uHQQgxgff8nh6aFDrh_cqkeFpcVPsvJILesm778_0"", ""工作表1!A:B""), 2, FALSE), """") <> """", ""有縮圖"", ""無縮圖"")"),"無縮圖") -> 無縮圖
A13: +Ely Cosplay+ | B13: Ely | G13: Coser | M13: TRUE | N13: FALSE | O13: FALSE | P13: FALSE | R13: {=IFERROR(INDEX('印量調查區'!G:G, MATCH(A13, '印量調查區'!A:A, 0)), "")} | S13: https://www.facebook.com/eeelyeee/ | W13: https://twitter.com/Ely_eee | AE13: IG | AR13: =IFERROR(__xludf.DUMMYFUNCTION("IF(IFERROR(VLOOKUP(A13, IMPORTRANGE(""https://docs.google.com/spreadsheets/d/1f7uHQQgxgff8nh6aFDrh_cqkeFpcVPsvJILesm778_0"", ""工作表1!A:B""), 2, FALSE), """") <> """", ""有縮圖"", ""無縮圖"")"),"無縮圖") -> 無縮圖
A14: ＋そおの | D14: H18 | E14: H17,H18 | G14: 繪師 | M14: TRUE | N14: FALSE | O14: FALSE | P14: FALSE | R14: {=IFERROR(INDEX('印量調查區'!G:G, MATCH(A14, '印量調查區'!A:A, 0)), "")} | W14: https://x.com/soOno2020 | Z14: https://www.pixiv.net/users/540668 | AE14: https://www.instagram.com/soono_artist | AF14: https://www.youtube.com/channel/UCJ4lUmPIs4RhEihsSZ7Jl1Q | AM14: https://soono.weebly.com/?utm_source=ig&utm_medium=social&utm_content=link_in_bio | AR14: =IFERROR(__xludf.DUMMYFUNCTION("IF(IFERROR(VLOOKUP(A14, IMPORTRANGE(""https://docs.google.com/spreadsheets/d/1f7uHQQgxgff8nh6aFDrh_cqkeFpcVPsvJILesm778_0"", ""工作表1!A:B""), 2, FALSE), """") <> """", ""有縮圖"", ""無縮圖"")"),"無縮圖") -> 無縮圖
A15: ～黑色布丁～ | D15: C44 | E15: C44 | G15: 繪師 | M15: TRUE | N15: FALSE | O15: FALSE | P15: FALSE | R15: {=IFERROR(INDEX('印量調查區'!G:G, MATCH(A15, '印量調查區'!A:A, 0)), "")} | S15: https://www.facebook.com/melanianpurin | Y15: https://www.plurk.com/melanianpruin | AR15: =IFERROR(__xludf.DUMMYFUNCTION("IF(IFERROR(VLOOKUP(A15, IMPORTRANGE(""https://docs.google.com/spreadsheets/d/1f7uHQQgxgff8nh6aFDrh_cqkeFpcVPsvJILesm778_0"", ""工作表1!A:B""), 2, FALSE), """") <> """", ""有縮圖"", ""無縮圖"")"),"無縮圖") -> 無縮圖
A16: ～NEKONABE～ | E16: C43 | G16: 繪師 | I16: 二創 | J16: 精靈寶可夢 | M16: TRUE | N16: TRUE | O16: FALSE | P16: FALSE | R16: {=IFERROR(INDEX('印量調查區'!G:G, MATCH(A16, '印量調查區'!A:A, 0)), "")} | S16: https://www.facebook.com/profile.php?id=100066562821753 | AR16: =IFERROR(__xludf.DUMMYFUNCTION("IF(IFERROR(VLOOKUP(A16, IMPORTRANGE(""https://docs.google.com/spreadsheets/d/1f7uHQQgxgff8nh6aFDrh_cqkeFpcVPsvJILesm778_0"", ""工作表1!A:B""), 2, FALSE), """") <> """", ""有縮圖"", ""無縮圖"")"),"無縮圖") -> 無縮圖
A17: ♡可凡kofan0331 | B17: 可凡 | C17: R37,R38 | D17: R37,R38 | G17: Coser | M17: TRUE | N17: FALSE | O17: FALSE | P17: FALSE | R17: {=IFERROR(INDEX('印量調查區'!G:G, MATCH(A17, '印量調查區'!A:A, 0)), "")} | S17: https://m.facebook.com/kofan331/ | W17: https://twitter.com/kofan0331/status/1552294307767341058?s=46&t=BBl9xiG-s1NqApoWBm401g | AD17: https://www.patreon.com/kofan0331 https://streamlabs.com/kofan0331/tip | AE17: https://www.instagram.com/kofan_0331/?hl=zh-tw | AF17: https://youtube.com/c/kofan%E5%8F%AF%E5%87%A1 | AG17: https://m.twitch.tv/kofan0331 | AI17: https://discord.gg/f9ukYFb | AL17: https://taplink.cc/kofan_0331?fbclid=PAZXh0bgNhZW0CMTEAAactAAtQW-I09r3QO7QEZFi7BONssX6zyCvfLKDLBZMNczkOUmn6UlXnuB9-fQ_aem_0Yfbze5olK5vRZAtJUqXEw | AR17: =IFERROR(__xludf.DUMMYFUNCTION("IF(IFERROR(VLOOKUP(A17, IMPORTRANGE(""https://docs.google.com/spreadsheets/d/1f7uHQQgxgff8nh6aFDrh_cqkeFpcVPsvJILesm778_0"", ""工作表1!A:B""), 2, FALSE), """") <> """", ""有縮圖"", ""無縮圖"")"),"無縮圖") -> 無縮圖
A18: 0蛋黃女子由奈0 | D18: R07 | E18: R07 | G18: Coser | M18: TRUE | N18: FALSE | O18: FALSE | P18: FALSE | R18: {=IFERROR(INDEX('印量調查區'!G:G, MATCH(A18, '印量調查區'!A:A, 0)), "")} | S18: https://www.facebook.com/matsuokayune.2015/ | AE18: https://www.instagram.com/akai_yuna_1110/ | AL18: https://linktr.ee/matsuoka_yuna | AR18: =IFERROR(__xludf.DUMMYFUNCTION("IF(IFERROR(VLOOKUP(A18, IMPORTRANGE(""https://docs.google.com/spreadsheets/d/1f7uHQQgxgff8nh6aFDrh_cqkeFpcVPsvJILesm778_0"", ""工作表1!A:B""), 2, FALSE), """") <> """", ""有縮圖"", ""無縮圖"")"),"無縮圖") -> 無縮圖
A19: 1%小風 | B19: 小風 | C19: B10 | G19: 繪師 | I19: 二創 | J19: Hololive | M19: TRUE | N19: TRUE | O19: FALSE | P19: FALSE | R19: {=IFERROR(INDEX('印量調查區'!G:G, MATCH(A19, '印量調查區'!A:A, 0)), "")} | S19: https://www.facebook.com/FFFfengXX/?locale=zh_TW | AR19: =IFERROR(__xludf.DUMMYFUNCTION("IF(IFERROR(VLOOKUP(A19, IMPORTRANGE(""https://docs.google.com/spreadsheets/d/1f7uHQQgxgff8nh6aFDrh_cqkeFpcVPsvJILesm778_0"", ""工作表1!A:B""), 2, FALSE), """") <> """", ""有縮圖"", ""無縮圖"")"),"無縮圖") -> 無縮圖
A20: 23.4ド＆きのこのみ＆蜂蜜少女 | B20: イチリ, きのこのみ, 蜜桃まむ | D20: G34 | G20: 繪師，日本 | I20: 二創 | J20: 請問您今天要來點兔子嗎? / Is the order a rabbit? / ご注文はうさぎですか?? | M20: TRUE | N20: TRUE | O20: FALSE | P20: FALSE | R20: {=IFERROR(INDEX('印量調查區'!G:G, MATCH(A20, '印量調查區'!A:A, 0)), "")} | W20: https://x.com/234itiri | X20: https://x.com/mamgon | AA20: https://mamgon.fanbox.cc/ | AB20: https://itiri.fanbox.cc/ | AR20: =IFERROR(__xludf.DUMMYFUNCTION("IF(IFERROR(VLOOKUP(A20, IMPORTRANGE(""https://docs.google.com/spreadsheets/d/1f7uHQQgxgff8nh6aFDrh_cqkeFpcVPsvJILesm778_0"", ""工作表1!A:B""), 2, FALSE), """") <> """", ""有縮圖"", ""無縮圖"")"),"無縮圖") -> 無縮圖
A21: 33号部屋 | B21: 微雨 | C21: O25 | D21: O25 | G21: 繪師 | I21: 二創 | J21: 蔚藍檔案 / Blue Archive / ブルーアーカイブ | M21: TRUE | N21: TRUE | O21: TRUE | P21: FALSE | R21: {=IFERROR(INDEX('印量調查區'!G:G, MATCH(A21, '印量調查區'!A:A, 0)), "")} | S21: https://facebook.com/yu.yan.ting.974906/ | W21: https://twitter.com/Yen_Ting_Yu | Y21: https://www.plurk.com/rifrif686 | Z21: https://www.pixiv.net/users/3433634 | AN21: https://www.facebook.com/permalink.php?story_fbid=pfbid0Sjbto9HFM3mf1XkkoaT4DxFzDDT9d1Wu2dn5SoNYhJ6U7GKymBXdxBpFX6bYz5w3l&id=61583891031404 | AR21: =IFERROR(__xludf.DUMMYFUNCTION("IF(IFERROR(VLOOKUP(A21, IMPORTRANGE(""https://docs.google.com/spreadsheets/d/1f7uHQQgxgff8nh6aFDrh_cqkeFpcVPsvJILesm778_0"", ""工作表1!A:B""), 2, FALSE), """") <> """", ""有縮圖"", ""無縮圖"")"),"有縮圖") -> 有縮圖
A22: 404便利通販 | B22: 熊初末 | C22: C06 | E22: B33 | G22: 繪師 | H22: 一般 | I22: 二創 | J22: 米哈遊 | K22: 音擎鑰匙圈盲盒 (伸縮鑰匙圈) 壓克力立牌 簽繪板 掛軸 | M22: TRUE | N22: TRUE | O22: TRUE | P22: TRUE | R22: {=IFERROR(INDEX('印量調查區'!G:G, MATCH(A22, '印量調查區'!A:A, 0)), "")} | S22: https://www.facebook.com/404Armory/ | T22: https://www.facebook.com/xiongchumo | U22: https://bsky.app/profile/beardad85414.bsky.social | W22: https://x.com/beardad85414 | Z22: https://www.pixiv.net/users/11526704 | AE22: https://www.instagram.com/beardad850414 | AM22: https://portaly.cc/beardad85414 | AN22: https://www.facebook.com/reel/3367086716832008/ | AO22: https://drive.google.com/file/d/1msQmu0U2Wo6IC-leRgMdwigybkSJegHq/view?usp=sharing | AR22: =IFERROR(__xludf.DUMMYFUNCTION("IF(IFERROR(VLOOKUP(A22, IMPORTRANGE(""https://docs.google.com/spreadsheets/d/1f7uHQQgxgff8nh6aFDrh_cqkeFpcVPsvJILesm778_0"", ""工作表1!A:B""), 2, FALSE), """") <> """", ""有縮圖"", ""無縮圖"")"),"無縮圖") -> 無縮圖
A23: 44c_isaac | C23: D35 | E23: D23 | G23: 繪師 | M23: TRUE | N23: FALSE | O23: TRUE | P23: FALSE | R23: {=IFERROR(INDEX('印量調查區'!G:G, MATCH(A23, '印量調查區'!A:A, 0)), "")} | W23: https://x.com/44c_isaac?lang=zh-TW | Z23: https://www.pixiv.net/users/19063155 | AJ23: https://home.gamer.com.tw/profile/index_feed.php?owner=lowkey0820 | AM23: https://weibo.com/isaacyeh | AN23: https://www.facebook.com/ssd.ada.831152/posts/pfbid02m47QRGEYFp9u1eVe7tT2K7PU27X1BmoWALE3Z8m4rDeSDYrJwMnHrSiLTEoTMvYyl | AR23: =IFERROR(__xludf.DUMMYFUNCTION("IF(IFERROR(VLOOKUP(A23, IMPORTRANGE(""https://docs.google.com/spreadsheets/d/1f7uHQQgxgff8nh6aFDrh_cqkeFpcVPsvJILesm778_0"", ""工作表1!A:B""), 2, FALSE), """") <> """", ""有縮圖"", ""無縮圖"")"),"無縮圖") -> 無縮圖
A24: 5年目の放課後 | D24: F26 | G24: 繪師 | M24: TRUE | N24: FALSE | O24: FALSE | P24: FALSE | R24: {=IFERROR(INDEX('印量調查區'!G:G, MATCH(A24, '印量調查區'!A:A, 0)), "")} | W24: https://twitter.com/kantoku_5th | Z24: https://www.pixiv.net/users/1565632 | AK24: http://5-y.2-d.jp/ | AR24: =IFERROR(__xludf.DUMMYFUNCTION("IF(IFERROR(VLOOKUP(A24, IMPORTRANGE(""https://docs.google.com/spreadsheets/d/1f7uHQQgxgff8nh6aFDrh_cqkeFpcVPsvJILesm778_0"", ""工作表1!A:B""), 2, FALSE), """") <> """", ""有縮圖"", ""無縮圖"")"),"無縮圖") -> 無縮圖
A25: 74 Production | D25: L06 | G25: 繪師 | M25: TRUE | N25: FALSE | O25: TRUE | P25: FALSE | R25: {=IFERROR(INDEX('印量調查區'!G:G, MATCH(A25, '印量調查區'!A:A, 0)), "")} | S25: https://www.facebook.com/IdolProduction74 | T25: https://www.facebook.com/profile.php?id=100000297013388 | W25: https://x.com/mikoair | Y25: https://www.plurk.com/summerair | Z25: https://www.pixiv.net/users/495657 | AN25: https://www.facebook.com/IdolProduction74/posts/pfbid02FhecfsRJSxCTJWm5cuYZaj6jmKad9c5WTMshwCS5rAKfcqBX6xWn8oB6KdbUvirql | AR25: =IFERROR(__xludf.DUMMYFUNCTION("IF(IFERROR(VLOOKUP(A25, IMPORTRANGE(""https://docs.google.com/spreadsheets/d/1f7uHQQgxgff8nh6aFDrh_cqkeFpcVPsvJILesm778_0"", ""工作表1!A:B""), 2, FALSE), """") <> """", ""有縮圖"", ""無縮圖"")"),"有縮圖") -> 有縮圖
A26: 7B鉛筆 | E26: A14 | M26: FALSE | N26: FALSE | O26: FALSE | P26: FALSE | R26: {=IFERROR(INDEX('印量調查區'!G:G, MATCH(A26, '印量調查區'!A:A, 0)), "")} | AR26: =IFERROR(__xludf.DUMMYFUNCTION("IF(IFERROR(VLOOKUP(A26, IMPORTRANGE(""https://docs.google.com/spreadsheets/d/1f7uHQQgxgff8nh6aFDrh_cqkeFpcVPsvJILesm778_0"", ""工作表1!A:B""), 2, FALSE), """") <> """", ""有縮圖"", ""無縮圖"")"),"無縮圖") -> 無縮圖
A27: 8七兔 | B27: 8七兔 | C27: D26 | G27: 繪師 | H27: 一般 | I27: 二創, 原創 | J27: Hololive，Ina，Vtuber，Saba，Gura | K27: 新刊套組 500元 💠1、同人誌新刊【Kaleidoscope】200元 💠2、壓克力立繪板 💠3、Ina奶飲料杯套 💠4、透明貼紙2張 150元 其他品項 💠Ina、Saba 壓克力飯友 200元 💠明信片 50元 既品 💠同人誌既刊 150元 💠胸章 150元/組 💠眼鏡布 100元 💠2026便當月曆 100元 💠Saba立牌 250元 💠吊飾 100元/個 250元/3個 💠滑鼠墊 150元 💠立繪板 200元 | M27: TRUE | N27: TRUE | O27: FALSE | P27: TRUE | R27: {=IFERROR(INDEX('印量調查區'!G:G, MATCH(A27, '印量調查區'!A:A, 0)), "")} | S27: https://www.facebook.com/profile.php?id=100094134949022 | W27: https://twitter.com/8nana_usa | Z27: https://www.pixiv.net/users/13614957 | AE27: https://www.instagram.com/illustration_aku007/?fbclid=IwAR30XW9AaLfNNg3gSXARaZv2zi_41q_XhrjNEtM7bCinFjthZ0Skr1h9TUQ | AO27: https://www.facebook.com/wu.zhu.ying.361685/posts/pfbid02bPyqHFMPbjeXnvqjJeFPfTWrwayuZQDeGcKcxWwRchKZhUkUxvyqnm6Ck5LEWMW6l | AP27: https://reurl.cc/vG52kA | AR27: =IFERROR(__xludf.DUMMYFUNCTION("IF(IFERROR(VLOOKUP(A27, IMPORTRANGE(""https://docs.google.com/spreadsheets/d/1f7uHQQgxgff8nh6aFDrh_cqkeFpcVPsvJILesm778_0"", ""工作表1!A:B""), 2, FALSE), """") <> """", ""有縮圖"", ""無縮圖"")"),"無縮圖") -> 無縮圖
A28: 一心三惑 | B28: とうち,桃李タロ | C28: L07,L08 | E28: L03,L04 | G28: 繪師 | M28: TRUE | N28: FALSE | O28: TRUE | P28: FALSE | R28: {=IFERROR(INDEX('印量調查區'!G:G, MATCH(A28, '印量調查區'!A:A, 0)), "")} | S28: https://www.facebook.com/misconception2014/ | W28: https://twitter.com/tori_mcct | Y28: PLURK | Z28: https://www.pixiv.net/users/14368479 | AN28: https://www.facebook.com/tc.chan.675349/posts/pfbid0oYUxjbDYvHQSZaauX7XmztPxDVUqGpZLfrpYknX1QqZyigU4yAaARQT6xKt7deG5l | AR28: =IFERROR(__xludf.DUMMYFUNCTION("IF(IFERROR(VLOOKUP(A28, IMPORTRANGE(""https://docs.google.com/spreadsheets/d/1f7uHQQgxgff8nh6aFDrh_cqkeFpcVPsvJILesm778_0"", ""工作表1!A:B""), 2, FALSE), """") <> """", ""有縮圖"", ""無縮圖"")"),"無縮圖") -> 無縮圖
A29: 一米七雪貓 | B29: 雪貓 | C29: B15,B16 | D29: B15,B16 | G29: 繪師，Coser | M29: TRUE | N29: FALSE | O29: FALSE | P29: FALSE | R29: {=IFERROR(INDEX('印量調查區'!G:G, MATCH(A29, '印量調查區'!A:A, 0)), "")} | S29: https://www.facebook.com/yukineko170 | T29: https://www.facebook.com/seaoceanumi | U29: https://bsky.app/profile/yukineko0975.bsky.social | W29: https://x.com/yukineko0975 | X29: https://x.com/yukineko097 | Z29: https://www.pixiv.net/users/25447095 | AA29: https://yukineko0975.fanbox.cc/ | AE29: https://www.instagram.com/yukineko170/ | AF29: https://www.youtube.com/@yukineko097 | AG29: https://www.twitch.tv/yukineko0975 | AI29: https://discord.com/invite/G5DUnS2Qcz | AJ29: https://m.gamer.com.tw/home/home.php?owner=yukineko1018 | AL29: https://linktr.ee/yukineko0975 | AR29: =IFERROR(__xludf.DUMMYFUNCTION("IF(IFERROR(VLOOKUP(A29, IMPORTRANGE(""https://docs.google.com/spreadsheets/d/1f7uHQQgxgff8nh6aFDrh_cqkeFpcVPsvJILesm778_0"", ""工作表1!A:B""), 2, FALSE), """") <> """", ""有縮圖"", ""無縮圖"")"),"無縮圖") -> 無縮圖
A30: 一虎虎虎 | C30: L44 | E30: L06 | G30: 繪師 | M30: TRUE | N30: FALSE | O30: FALSE | P30: FALSE | Q30: 高 | R30: {=IFERROR(INDEX('印量調查區'!G:G, MATCH(A30, '印量調查區'!A:A, 0)), "")} | S30: https://www.facebook.com/yihu15/ | W30: https://x.com/yihu_15 | AE30: https://www.instagram.com/yihu_15/ | AG30: https://www.twitch.tv/yihu15 | AL30: https://portaly.cc/yihu_15?utm_source=ig&utm_medium=social&utm_content=link_in_bio&fbclid=PAZXh0bgNhZW0CMTEAc3J0YwZhcHBfaWQPOTM2NjE5NzQzMzkyNDU5AAGnG7bfuIo7zfH0Y5o0j7ENjzeAkuDEqEXrOn1K4z25oTbXqMJVy8iq4-__SbQ_aem_3Dvr6XFLaV_4N_6KASU7MQ&utm_id=97760_v0_s00_e0_tv3 | AR30: =IFERROR(__xludf.DUMMYFUNCTION("IF(IFERROR(VLOOKUP(A30, IMPORTRANGE(""https://docs.google.com/spreadsheets/d/1f7uHQQgxgff8nh6aFDrh_cqkeFpcVPsvJILesm778_0"", ""工作表1!A:B""), 2, FALSE), """") <> """", ""有縮圖"", ""無縮圖"")"),"無縮圖") -> 無縮圖
A31: 一個小路人 | B31: 路人 | C31: J30 | G31: 繪師 | M31: TRUE | N31: FALSE | O31: FALSE | P31: FALSE | R31: {=IFERROR(INDEX('印量調查區'!G:G, MATCH(A31, '印量調查區'!A:A, 0)), "")} | S31: https://www.facebook.com/p/%E5%B0%8F%E8%B7%AF%E4%BA%BA%E7%9A%84%E8%85%A6%E6%B4%9E%E5%A1%97%E9%B4%89%E7%89%86-100077894957363/ | W31: https://x.com/Miga_Chen | Y31: https://www.plurk.com/s/u/susan1980735?offset= | AR31: =IFERROR(__xludf.DUMMYFUNCTION("IF(IFERROR(VLOOKUP(A31, IMPORTRANGE(""https://docs.google.com/spreadsheets/d/1f7uHQQgxgff8nh6aFDrh_cqkeFpcVPsvJILesm778_0"", ""工作表1!A:B""), 2, FALSE), """") <> """", ""有縮圖"", ""無縮圖"")"),"無縮圖") -> 無縮圖
A32: 一個簡單的黛黛 | E32: R13,R14 | G32: Coser | M32: FALSE | N32: FALSE | O32: FALSE | P32: FALSE | R32: {=IFERROR(INDEX('印量調查區'!G:G, MATCH(A32, '印量調查區'!A:A, 0)), "")} | AR32: =IFERROR(__xludf.DUMMYFUNCTION("IF(IFERROR(VLOOKUP(A32, IMPORTRANGE(""https://docs.google.com/spreadsheets/d/1f7uHQQgxgff8nh6aFDrh_cqkeFpcVPsvJILesm778_0"", ""工作表1!A:B""), 2, FALSE), """") <> """", ""有縮圖"", ""無縮圖"")"),"無縮圖") -> 無縮圖
A33: 一隻呆呆魚 | E33: D43,D44 | M33: FALSE | N33: FALSE | O33: FALSE | P33: FALSE | R33: {=IFERROR(INDEX('印量調查區'!G:G, MATCH(A33, '印量調查區'!A:A, 0)), "")} | AR33: =IFERROR(__xludf.DUMMYFUNCTION("IF(IFERROR(VLOOKUP(A33, IMPORTRANGE(""https://docs.google.com/spreadsheets/d/1f7uHQQgxgff8nh6aFDrh_cqkeFpcVPsvJILesm778_0"", ""工作表1!A:B""), 2, FALSE), """") <> """", ""有縮圖"", ""無縮圖"")"),"無縮圖") -> 無縮圖
A34: 一輩子少女樂團 | D34: U15 [寄] | E34: U13,U14 | G34: 繪師 | H34: 一般 | I34: 二創 | J34: Bang Dream，MyGO!!!!!，Ave Mujica，少女樂團吶喊吧 (女團哭 GBC)，孤獨搖滾 | K34: 壓克力雙面吊飾 100元 | M34: TRUE | N34: TRUE | O34: FALSE | P34: TRUE | R34: {=IFERROR(INDEX('印量調查區'!G:G, MATCH(A34, '印量調查區'!A:A, 0)), "")} | AM34: https://www.threads.com/@ry_rouyu | AO34: https://www.threads.com/@ry_rouyu/post/DbkhvDoidRn | AR34: =IFERROR(__xludf.DUMMYFUNCTION("IF(IFERROR(VLOOKUP(A34, IMPORTRANGE(""https://docs.google.com/spreadsheets/d/1f7uHQQgxgff8nh6aFDrh_cqkeFpcVPsvJILesm778_0"", ""工作表1!A:B""), 2, FALSE), """") <> """", ""有縮圖"", ""無縮圖"")"),"無縮圖") -> 無縮圖
A35: 一顆馬鈴薯-燦 | E35: G35 | G35: 繪師 | H35: 一般 | I35: 原創 | K35: 同人誌【馬鈴薯與他的快樂男人】 | M35: TRUE | N35: TRUE | O35: TRUE | P35: FALSE | R35: {=IFERROR(INDEX('印量調查區'!G:G, MATCH(A35, '印量調查區'!A:A, 0)), "")} | S35: https://www.facebook.com/lin.heng.166900/ | U35: https://bsky.app/profile/potato80501.bsky.social | Y35: https://www.plurk.com/potato80501 | AE35: https://www.instagram.com/potato80501in309/ | AM35: https://www.plurk.com/p/3izjsj05sc | AN35: https://www.plurk.com/p/3iy4ufnwxi | AR35: =IFERROR(__xludf.DUMMYFUNCTION("IF(IFERROR(VLOOKUP(A35, IMPORTRANGE(""https://docs.google.com/spreadsheets/d/1f7uHQQgxgff8nh6aFDrh_cqkeFpcVPsvJILesm778_0"", ""工作表1!A:B""), 2, FALSE), """") <> """", ""有縮圖"", ""無縮圖"")"),"無縮圖") -> 無縮圖
A36: 丁丁烤魚魚 | C36: J35,J36 | E36: L13,L14 | G36: 繪師 | M36: TRUE | N36: FALSE | O36: TRUE | P36: FALSE | R36: {=IFERROR(INDEX('印量調查區'!G:G, MATCH(A36, '印量調查區'!A:A, 0)), "")} | S36: https://www.facebook.com/shiyasakana/ | W36: https://twitter.com/shiyasakana | Y36: https://www.plurk.com/shiyasakana | AN36: https://x.com/shiyasakana/status/2060325475663405131 | AR36: =IFERROR(__xludf.DUMMYFUNCTION("IF(IFERROR(VLOOKUP(A36, IMPORTRANGE(""https://docs.google.com/spreadsheets/d/1f7uHQQgxgff8nh6aFDrh_cqkeFpcVPsvJILesm778_0"", ""工作表1!A:B""), 2, FALSE), """") <> """", ""有縮圖"", ""無縮圖"")"),"有縮圖") -> 有縮圖
A37: 丁丁dingding | C37: R14 | D37: R14 | G37: Coser | M37: TRUE | N37: FALSE | O37: FALSE | P37: FALSE | R37: {=IFERROR(INDEX('印量調查區'!G:G, MATCH(A37, '印量調查區'!A:A, 0)), "")} | S37: https://www.facebook.com/p/%E4%B8%81%E4%B8%81DingDing-100084623769863/ | W37: https://x.com/dingding_0106?fbclid=IwY2xjawSIzWRleHRuA2FlbQIxMABicmlkETFSS0NySzhvbnpSVWZQM0NRc3J0YwZhcHBfaWQQMjIyMDM5MTc4ODIwMDg5MgABHsE_h2zMx7jQCsr_SWDoCRiJHZI3DWVu9wLwaHb200PfdGDolf_g0koMHH3N_aem_D0LY30W7_lJBJStuHJ_qyA | AR37: =IFERROR(__xludf.DUMMYFUNCTION("IF(IFERROR(VLOOKUP(A37, IMPORTRANGE(""https://docs.google.com/spreadsheets/d/1f7uHQQgxgff8nh6aFDrh_cqkeFpcVPsvJILesm778_0"", ""工作表1!A:B""), 2, FALSE), """") <> """", ""有縮圖"", ""無縮圖"")"),"無縮圖") -> 無縮圖
A38: 七七小姐_Miss Seven | C38: R33,R34 | D38: R33,R34 | G38: Coser | M38: TRUE | N38: FALSE | O38: FALSE | P38: FALSE | R38: {=IFERROR(INDEX('印量調查區'!G:G, MATCH(A38, '印量調查區'!A:A, 0)), "")} | S38: https://www.facebook.com/Miss.double.seven/?locale=zh_TW | W38: https://x.com/coser_seven_tw | AE38: https://www.instagram.com/miss.seven.77/ | AF38: https://www.youtube.com/@seven5277 | AL38: https://linktr.ee/sevencosplay | AR38: =IFERROR(__xludf.DUMMYFUNCTION("IF(IFERROR(VLOOKUP(A38, IMPORTRANGE(""https://docs.google.com/spreadsheets/d/1f7uHQQgxgff8nh6aFDrh_cqkeFpcVPsvJILesm778_0"", ""工作表1!A:B""), 2, FALSE), """") <> """", ""有縮圖"", ""無縮圖"")"),"無縮圖") -> 無縮圖
A39: 七兔不好吃 | B39: 七兔 | D39: L33 | E39: M23,M24 | G39: Vtuber | H39: 一般 | M39: TRUE | N39: TRUE | O39: TRUE | P39: FALSE | R39: {=IFERROR(INDEX('印量調查區'!G:G, MATCH(A39, '印量調查區'!A:A, 0)), "")} | W39: https://x.com/Nayomi0204?ref_src=twsrc%5Egoogle%7Ctwcamp%5Eserp%7Ctwgr%5Eauthor | AG39: https://www.twitch.tv/nayomi0204 | AN39: https://x.com/nayomi0204/status/2081299581749575938?s=61&t=J9-H8xDVimG-T97w1or4FA https://www.instagram.com/p/DbbmvfJE6Jx/ | AR39: =IFERROR(__xludf.DUMMYFUNCTION("IF(IFERROR(VLOOKUP(A39, IMPORTRANGE(""https://docs.google.com/spreadsheets/d/1f7uHQQgxgff8nh6aFDrh_cqkeFpcVPsvJILesm778_0"", ""工作表1!A:B""), 2, FALSE), """") <> """", ""有縮圖"", ""無縮圖"")"),"無縮圖") -> 無縮圖
A40: 七叔神社 | B40: 七叔 | C40: B43 | G40: 繪師 | H40: 一般 | I40: 二創 | J40: 艦隊收藏 / Kantai Collection / 艦コレ | K40: 💠7公分壓克力立牌 120元，💠明信片 20元 | M40: TRUE | N40: TRUE | O40: FALSE | P40: TRUE | R40: {=IFERROR(INDEX('印量調查區'!G:G, MATCH(A40, '印量調查區'!A:A, 0)), "")} | S40: https://www.facebook.com/Uncle7Fansite/ | W40: https://x.com/nanaojisan | AF40: https://youtube.com/@nanaoji?si=zBfHFe1mH-wZFQHa | AO40: https://www.facebook.com/share/1Gs2pSrC11/?mibextid=wwXIfr | AR40: =IFERROR(__xludf.DUMMYFUNCTION("IF(IFERROR(VLOOKUP(A40, IMPORTRANGE(""https://docs.google.com/spreadsheets/d/1f7uHQQgxgff8nh6aFDrh_cqkeFpcVPsvJILesm778_0"", ""工作表1!A:B""), 2, FALSE), """") <> """", ""有縮圖"", ""無縮圖"")"),"有縮圖") -> 有縮圖
A41: 乃木乃木出版 | C41: S16 | D41: S16 | G41: Coser | M41: FALSE | N41: FALSE | O41: FALSE | P41: FALSE | R41: {=IFERROR(INDEX('印量調查區'!G:G, MATCH(A41, '印量調查區'!A:A, 0)), "")} | AR41: =IFERROR(__xludf.DUMMYFUNCTION("IF(IFERROR(VLOOKUP(A41, IMPORTRANGE(""https://docs.google.com/spreadsheets/d/1f7uHQQgxgff8nh6aFDrh_cqkeFpcVPsvJILesm778_0"", ""工作表1!A:B""), 2, FALSE), """") <> """", ""有縮圖"", ""無縮圖"")"),"無縮圖") -> 無縮圖
A42: 九尾貓desu | B42: 九尾ねこ | E42: N27,N28 | G42: 繪師 | H42: 一般 | I42: 二創 | J42: 魔法少女的魔女審判、學園偶像大師、蔚藍檔案、賽馬娘 | K42: ☘︎櫻羽艾瑪／二階堂希羅 陶瓷杯墊 ---> NT$200／個 ☘︎櫻羽艾瑪／二階堂希羅 徽章(58mm) ---> NT$60／個 ☘︎二階堂希羅 壓克力打卡棒(7x7cm+10cm) ---> NT$200／個 ☘︎蓮見蕾雅 開合壓克力吊飾 ---> NT$250／個 一些學園偶像大師吊飾 一些蔚藍檔案立牌 一些馬娘相關周邊 | M42: TRUE | N42: TRUE | O42: FALSE | P42: TRUE | R42: {=IFERROR(INDEX('印量調查區'!G:G, MATCH(A42, '印量調查區'!A:A, 0)), "")} | S42: https://www.facebook.com/kyukonneko/ | W42: https://x.com/NtcMuffet | AA42: https://www.pixiv.net/users/19583491 | AL42: https://linktr.ee/kyukon | AO42: https://www.threads.com/@muffet_nyanko/post/DbqRK5rmjwS | AR42: =IFERROR(__xludf.DUMMYFUNCTION("IF(IFERROR(VLOOKUP(A42, IMPORTRANGE(""https://docs.google.com/spreadsheets/d/1f7uHQQgxgff8nh6aFDrh_cqkeFpcVPsvJILesm778_0"", ""工作表1!A:B""), 2, FALSE), """") <> """", ""有縮圖"", ""無縮圖"")"),"無縮圖") -> 無縮圖
A43: 二色幽紫蝶 | C43: G11,G12 | E43: G07,G08 | G43: 繪師，中國 | M43: TRUE | N43: FALSE | O43: FALSE | P43: FALSE | R43: {=IFERROR(INDEX('印量調查區'!G:G, MATCH(A43, '印量調查區'!A:A, 0)), "")} | W43: https://x.com/youziKK | AM43: https://space.bilibili.com/86865890 | AR43: =IFERROR(__xludf.DUMMYFUNCTION("IF(IFERROR(VLOOKUP(A43, IMPORTRANGE(""https://docs.google.com/spreadsheets/d/1f7uHQQgxgff8nh6aFDrh_cqkeFpcVPsvJILesm778_0"", ""工作表1!A:B""), 2, FALSE), """") <> """", ""有縮圖"", ""無縮圖"")"),"有縮圖") -> 有縮圖
A44: 人工降雨 | D44: N30 | G44: 繪師 | H44: R15 | I44: 二創 | J44: 蔚藍檔案 / Blue Archive / ブルーアーカイブ | K44: 💠搖擺星陽組 500元 1、星野壓克力立牌 300元 2、陽奈壓克力立牌 300元 💠同人誌新刊 400元 💠壓克力腳踏車立牌 300元 💠新刊+特典+腳踏車立牌套組 600元 💠同人誌三部曲套組 800元 💠壓克力懸吊莉排 300元 💠壓克力色紙 300元 | M44: TRUE | N44: TRUE | O44: FALSE | P44: TRUE | R44: {=IFERROR(INDEX('印量調查區'!G:G, MATCH(A44, '印量調查區'!A:A, 0)), "")} | W44: https://x.com/manmaderain?s=21 | Z44: https://www.pixiv.net/users/3172150?_gl=1*1bb9yfm*_ga*MTg0OTgzODg1MC4xNzgwMjM0NjE0*_ga_D9TLP3EFER*czE3ODAyMzQ2MTQkbzEkZzAkdDE3ODAyMzQ2MTQkajYwJGwwJGgw | AA44: https://manmaderain.fanbox.cc/ | AO44: https://www.facebook.com/permalink.php?story_fbid=pfbid02ZofUsKmozEYQJNYYFnfhd1diUYrN5Jj3CscHocihqUULNDmq7HKtdtNFGDGwgfMl&id=61587605733163 | AR44: =IFERROR(__xludf.DUMMYFUNCTION("IF(IFERROR(VLOOKUP(A44, IMPORTRANGE(""https://docs.google.com/spreadsheets/d/1f7uHQQgxgff8nh6aFDrh_cqkeFpcVPsvJILesm778_0"", ""工作表1!A:B""), 2, FALSE), """") <> """", ""有縮圖"", ""無縮圖"")"),"有縮圖") -> 有縮圖
A45: 人見巫拉拉 | D45: L32 | E45: M20 | G45: vtuber | M45: TRUE | N45: FALSE | O45: FALSE | P45: FALSE | R45: {=IFERROR(INDEX('印量調查區'!G:G, MATCH(A45, '印量調查區'!A:A, 0)), "")} | S45: https://x.com/HitomiOhlala | AR45: =IFERROR(__xludf.DUMMYFUNCTION("IF(IFERROR(VLOOKUP(A45, IMPORTRANGE(""https://docs.google.com/spreadsheets/d/1f7uHQQgxgff8nh6aFDrh_cqkeFpcVPsvJILesm778_0"", ""工作表1!A:B""), 2, FALSE), """") <> """", ""有縮圖"", ""無縮圖"")"),"無縮圖") -> 無縮圖
A46: 十塔星飛船總部 | C46: M40 | M46: FALSE | N46: FALSE | O46: FALSE | P46: FALSE | R46: {=IFERROR(INDEX('印量調查區'!G:G, MATCH(A46, '印量調查區'!A:A, 0)), "")} | AR46: =IFERROR(__xludf.DUMMYFUNCTION("IF(IFERROR(VLOOKUP(A46, IMPORTRANGE(""https://docs.google.com/spreadsheets/d/1f7uHQQgxgff8nh6aFDrh_cqkeFpcVPsvJILesm778_0"", ""工作表1!A:B""), 2, FALSE), """") <> """", ""有縮圖"", ""無縮圖"")"),"無縮圖") -> 無縮圖
A47: 三三殿下駕到 | D47: Q21,Q22 | E47: R21,R22 | G47: Coser | M47: TRUE | N47: FALSE | O47: FALSE | P47: FALSE | R47: {=IFERROR(INDEX('印量調查區'!G:G, MATCH(A47, '印量調查區'!A:A, 0)), "")} | S47: https://www.facebook.com/Princess33TW | AR47: =IFERROR(__xludf.DUMMYFUNCTION("IF(IFERROR(VLOOKUP(A47, IMPORTRANGE(""https://docs.google.com/spreadsheets/d/1f7uHQQgxgff8nh6aFDrh_cqkeFpcVPsvJILesm778_0"", ""工作表1!A:B""), 2, FALSE), """") <> """", ""有縮圖"", ""無縮圖"")"),"無縮圖") -> 無縮圖
A48: 三分糖手作中 | C48: J11 | D48: J11 | G48: 手作娃娃 | M48: TRUE | N48: FALSE | O48: FALSE | P48: FALSE | R48: {=IFERROR(INDEX('印量調查區'!G:G, MATCH(A48, '印量調查區'!A:A, 0)), "")} | S48: https://www.facebook.com/BJDhappy.candy/ | T48: https://www.facebook.com/profile.php?id=100072289940546&mibextid=ZbWKwL | AE48: https://www.instagram.com/dollworld1204/ | AF48: https://www.youtube.com/@Erenehsu | AK48: https://blog.erenehsu.com/archives/3017#more-3017 | AM48: https://www.google.com/maps/place/Happy+candy+%E4%B8%89%E5%88%86%E7%B3%96%E6%89%8B%E4%BD%9C%E9%A3%9F%E7%8E%A9%E5%B0%8F%E7%89%A9+(%E9%9D%9E%E5%BA%97%E9%9D%A2+%E6%8E%A1%E9%9B%BB%E8%A9%B1%E9%A0%90%E7%B4%84%E5%88%B6)/@25.1905713,121.4378092,15z/data=!4m6!3m5!1s0x3468038ec152b963:0xd4f6f822f6d2d969!8m2!3d25.1905713!4d121.4378092!16s%2Fg%2F11h06_73lr?sa=X&ved=1t:2428&ictx=111&coh=210790&entry=tts | AR48: =IFERROR(__xludf.DUMMYFUNCTION("IF(IFERROR(VLOOKUP(A48, IMPORTRANGE(""https://docs.google.com/spreadsheets/d/1f7uHQQgxgff8nh6aFDrh_cqkeFpcVPsvJILesm778_0"", ""工作表1!A:B""), 2, FALSE), """") <> """", ""有縮圖"", ""無縮圖"")"),"無縮圖") -> 無縮圖
A49: 三色坊 | C49: A10,A11 | D49: A10,A11 | G49: 繪師 | M49: TRUE | N49: FALSE | O49: TRUE | P49: FALSE | R49: {=IFERROR(INDEX('印量調查區'!G:G, MATCH(A49, '印量調查區'!A:A, 0)), "")} | S49: https://www.facebook.com/san.se.fang/ | W49: https://x.com/PaiHaku | Y49: https://www.plurk.com/PAIZERO | Z49: https://www.pixiv.net/users/882490 | AD49: https://www.patreon.com/paizero | AN49: https://www.plurk.com/p/3iu0nazaam | AR49: =IFERROR(__xludf.DUMMYFUNCTION("IF(IFERROR(VLOOKUP(A49, IMPORTRANGE(""https://docs.google.com/spreadsheets/d/1f7uHQQgxgff8nh6aFDrh_cqkeFpcVPsvJILesm778_0"", ""工作表1!A:B""), 2, FALSE), """") <> """", ""有縮圖"", ""無縮圖"")"),"有縮圖") -> 有縮圖
A50: 三食納豆飯 | B50: 美和野らぐ | D50: H19,H20 | E50: H19,H20 | G50: 繪師，日本 | M50: TRUE | N50: FALSE | O50: FALSE | P50: FALSE | R50: {=IFERROR(INDEX('印量調查區'!G:G, MATCH(A50, '印量調查區'!A:A, 0)), "")} | W50: https://x.com/rag_ragko | Z50: https://www.pixiv.net/users/7324626 | AE50: https://www.instagram.com/miwano_rag/ | AL50: https://potofu.me/miwanorag | AR50: =IFERROR(__xludf.DUMMYFUNCTION("IF(IFERROR(VLOOKUP(A50, IMPORTRANGE(""https://docs.google.com/spreadsheets/d/1f7uHQQgxgff8nh6aFDrh_cqkeFpcVPsvJILesm778_0"", ""工作表1!A:B""), 2, FALSE), """") <> """", ""有縮圖"", ""無縮圖"")"),"無縮圖") -> 無縮圖
A51: 三喬主公 | C51: Q20 | E51: Q30 | G51: Coser | M51: TRUE | N51: FALSE | O51: FALSE | P51: FALSE | R51: {=IFERROR(INDEX('印量調查區'!G:G, MATCH(A51, '印量調查區'!A:A, 0)), "")} | W51: https://x.com/3kiumaster | AE51: https://www.instagram.com/made.in.3kiu/ | AL51: https://lit.link/zh-tw/madein3kiu?utm_source=ig&utm_medium=social&utm_content=link_in_bio | AR51: =IFERROR(__xludf.DUMMYFUNCTION("IF(IFERROR(VLOOKUP(A51, IMPORTRANGE(""https://docs.google.com/spreadsheets/d/1f7uHQQgxgff8nh6aFDrh_cqkeFpcVPsvJILesm778_0"", ""工作表1!A:B""), 2, FALSE), """") <> """", ""有縮圖"", ""無縮圖"")"),"無縮圖") -> 無縮圖
A52: 三酸化炭素 | B52: Jack | C52: B38,B39 | D52: B38 | G52: 繪師 | H52: R18 | I52: 二創 | J52: 絕區零、蔚藍檔案、米哈遊 | K52: 💠大套組 (新刊+3個立牌) 1100元 💠中套組 ( 新刊+2個立牌) 800元 💠小套組 (新刊+1個立牌) 500元 💠同人誌新刊 200元 💠壓克力立牌 350元 💠陽奈抱枕 2500元 💠Kei滑鼠墊 600元 | M52: TRUE | N52: TRUE | O52: FALSE | P52: TRUE | R52: {=IFERROR(INDEX('印量調查區'!G:G, MATCH(A52, '印量調查區'!A:A, 0)), "")} | S52: https://www.facebook.com/k2illust/ | W52: https://x.com/k2_illust | Z52: https://www.pixiv.net/users/35352009 | AA52: https://jack0418.fanbox.cc/ | AO52: https://www.facebook.com/k2illust/posts/pfbid0zQRyzDdSSymUVhmkwuf4CmF9nBREC5FwDosCkwq4PXHKzjt3u4a2CTeAvXHV6ZDal | AR52: =IFERROR(__xludf.DUMMYFUNCTION("IF(IFERROR(VLOOKUP(A52, IMPORTRANGE(""https://docs.google.com/spreadsheets/d/1f7uHQQgxgff8nh6aFDrh_cqkeFpcVPsvJILesm778_0"", ""工作表1!A:B""), 2, FALSE), """") <> """", ""有縮圖"", ""無縮圖"")"),"有縮圖") -> 有縮圖
A53: 下空少女 | B53: 雁冰、夏久 | C53: U39,U40 | G53: 繪師 | H53: R18 | I53: 原創 | K53: 💠同人誌【祕密的少女圖鑑 】250元 💠同人誌【無人公園的小彼女】250元 | M53: TRUE | N53: TRUE | O53: FALSE | P53: FALSE | R53: {=IFERROR(INDEX('印量調查區'!G:G, MATCH(A53, '印量調查區'!A:A, 0)), "")} | S53: https://www.facebook.com/nicknikg863/ | W53: https://twitter.com/nicknikg86 | Y53: https://www.plurk.com/nicknikg | Z53: https://www.pixiv.net/users/577076 | AP53: https://www.myacg.com.tw/seller_market.php?seller=590573 | AR53: =IFERROR(__xludf.DUMMYFUNCTION("IF(IFERROR(VLOOKUP(A53, IMPORTRANGE(""https://docs.google.com/spreadsheets/d/1f7uHQQgxgff8nh6aFDrh_cqkeFpcVPsvJILesm778_0"", ""工作表1!A:B""), 2, FALSE), """") <> """", ""有縮圖"", ""無縮圖"")"),"有縮圖") -> 有縮圖
A54: 下空社 | C54: F09,F10 | E54: G05,G06 | G54: 繪師 | M54: TRUE | N54: FALSE | O54: TRUE | P54: FALSE | R54: {=IFERROR(INDEX('印量調查區'!G:G, MATCH(A54, '印量調查區'!A:A, 0)), "")} | S54: https://www.facebook.com/TUITDC | AE54: https://www.instagram.com/tuitdc1112/ | AJ54: https://home.gamer.com.tw/profile/index.php?owner=shaconsir | AL54: https://portaly.cc/TUITDC | AN54: https://www.facebook.com/TUITDC/posts/pfbid04xGpSCyaq9gZfikNr6YBiTMHAPrqsGRYEUYgAKnEpgeEEQRPcXiVWj1cZGM41Bwwl https://www.threads.com/share/BAW7WoqKPc/ | AR54: =IFERROR(__xludf.DUMMYFUNCTION("IF(IFERROR(VLOOKUP(A54, IMPORTRANGE(""https://docs.google.com/spreadsheets/d/1f7uHQQgxgff8nh6aFDrh_cqkeFpcVPsvJILesm778_0"", ""工作表1!A:B""), 2, FALSE), """") <> """", ""有縮圖"", ""無縮圖"")"),"無縮圖") -> 無縮圖
A55: 丫鴨 | B55: 丫鴨 | E55: K20 | G55: スバ友 | H55: 一般 | I55: 二創 | M55: TRUE | N55: TRUE | O55: FALSE | P55: FALSE | R55: {=IFERROR(INDEX('印量調查區'!G:G, MATCH(A55, '印量調查區'!A:A, 0)), "")} | W55: https://x.com/Master_ya1122 | X55: https://x.com/whale30504 | AR55: =IFERROR(__xludf.DUMMYFUNCTION("IF(IFERROR(VLOOKUP(A55, IMPORTRANGE(""https://docs.google.com/spreadsheets/d/1f7uHQQgxgff8nh6aFDrh_cqkeFpcVPsvJILesm778_0"", ""工作表1!A:B""), 2, FALSE), """") <> """", ""有縮圖"", ""無縮圖"")"),"無縮圖") -> 無縮圖
A56: 丸杏亭 | D56: C08 | E56: C08 | G56: 繪師，日本 | M56: TRUE | N56: FALSE | O56: FALSE | P56: FALSE | R56: {=IFERROR(INDEX('印量調查區'!G:G, MATCH(A56, '印量調查區'!A:A, 0)), "")} | W56: https://x.com/anzu0130 | X56: https://x.com/marrrr_co | AE56: https://www.instagram.com/anzu_maruco/ | AF56: https://www.youtube.com/@anzu_maruco | AL56: https://piku.page/@maruco | AR56: =IFERROR(__xludf.DUMMYFUNCTION("IF(IFERROR(VLOOKUP(A56, IMPORTRANGE(""https://docs.google.com/spreadsheets/d/1f7uHQQgxgff8nh6aFDrh_cqkeFpcVPsvJILesm778_0"", ""工作表1!A:B""), 2, FALSE), """") <> """", ""有縮圖"", ""無縮圖"")"),"無縮圖") -> 無縮圖
A57: 兀幾斗wugedou | B57: 兀幾斗 | D57: K11 | E57: K11 | G57: 繪師,vtuber | H57: 一般 | I57: 二創 | J57: Hololive，Ina | K57: 💠古神入教福袋 1500元 1、帆布袋 2、滑鼠墊 3、飯友包 4、大吊飾 | M57: TRUE | N57: TRUE | O57: FALSE | P57: TRUE | R57: {=IFERROR(INDEX('印量調查區'!G:G, MATCH(A57, '印量調查區'!A:A, 0)), "")} | S57: https://www.facebook.com/wugdouGG/?locale=zh_TW | W57: https://twitter.com/wugedou579 | Y57: https://www.plurk.com/wugedou | AF57: YOUTUBE | AI57: DISCORD | AO57: https://www.facebook.com/wugdouGG/posts/pfbid0S913bFB7zYiEmHL3koqFCuqCsVpKwNDX9gPfh3w3yUv1PaUUV2qH3PPr1rRpuwrDl | AR57: =IFERROR(__xludf.DUMMYFUNCTION("IF(IFERROR(VLOOKUP(A57, IMPORTRANGE(""https://docs.google.com/spreadsheets/d/1f7uHQQgxgff8nh6aFDrh_cqkeFpcVPsvJILesm778_0"", ""工作表1!A:B""), 2, FALSE), """") <> """", ""有縮圖"", ""無縮圖"")"),"無縮圖") -> 無縮圖
A58: 千煂+BS | B58: 塗鴉 | D58: V06 | E58: V05,V06 | G58: 繪師 | H58: 一般 | I58: 二創 | J58: #新世界狂歡 #戀與深空 #戀與製作人 #無職轉生 #咒術迴戰 薩爾達傳說 崩壞星穹鐵道 鳴潮 | K58: 💠同人誌 💠卡貼 💠明信片 💠扇子 💠透明壓克力 💠吊飾 💠袋子 💠貼紙 | M58: TRUE | N58: TRUE | O58: FALSE | P58: TRUE | R58: {=IFERROR(INDEX('印量調查區'!G:G, MATCH(A58, '印量調查區'!A:A, 0)), "")} | S58: https://www.facebook.com/profile.php?id=100063490909635# | W58: https://x.com/hagarener | Y58: https://www.plurk.com/blackstrange | Z58: https://www.pixiv.net/users/36214643 | AO58: https://www.instagram.com/p/Dbp-qFBCV3Z/ | AR58: =IFERROR(__xludf.DUMMYFUNCTION("IF(IFERROR(VLOOKUP(A58, IMPORTRANGE(""https://docs.google.com/spreadsheets/d/1f7uHQQgxgff8nh6aFDrh_cqkeFpcVPsvJILesm778_0"", ""工作表1!A:B""), 2, FALSE), """") <> """", ""有縮圖"", ""無縮圖"")"),"無縮圖") -> 無縮圖
A59: 士雷 | B59: 士雷 | C59: K23,K24 | D59: K23,K24 | E59: K23,K24 | G59: 繪師 | M59: TRUE | N59: FALSE | O59: FALSE | P59: FALSE | R59: {=IFERROR(INDEX('印量調查區'!G:G, MATCH(A59, '印量調查區'!A:A, 0)), "")} | S59: https://www.facebook.com/profile.php?id=100072024726705 | W59: https://x.com/uanuan_93 | Z59: https://www.pixiv.net/users/2145683 | AR59: =IFERROR(__xludf.DUMMYFUNCTION("IF(IFERROR(VLOOKUP(A59, IMPORTRANGE(""https://docs.google.com/spreadsheets/d/1f7uHQQgxgff8nh6aFDrh_cqkeFpcVPsvJILesm778_0"", ""工作表1!A:B""), 2, FALSE), """") <> """", ""有縮圖"", ""無縮圖"")"),"有縮圖") -> 有縮圖
A60: 大幼蟲 | D60: V01,V02 | E60: V01,V02 | G60: 繪師 | M60: TRUE | N60: FALSE | O60: FALSE | P60: FALSE | R60: {=IFERROR(INDEX('印量調查區'!G:G, MATCH(A60, '印量調查區'!A:A, 0)), "")} | S60: https://www.facebook.com/you.chong.403989/ | W60: https://x.com/lianbiglian | Z60: https://www.pixiv.net/users/10278825 | AD60: https://clibo.tw/users/fvMEBW | AE60: https://www.instagram.com/lianbiglian | AF60: https://www.youtube.com/channel/UCN8fq5W9Qnc3f0mFu3DYjJA | AL60: https://linktr.ee/lianbiglian | AR60: =IFERROR(__xludf.DUMMYFUNCTION("IF(IFERROR(VLOOKUP(A60, IMPORTRANGE(""https://docs.google.com/spreadsheets/d/1f7uHQQgxgff8nh6aFDrh_cqkeFpcVPsvJILesm778_0"", ""工作表1!A:B""), 2, FALSE), """") <> """", ""有縮圖"", ""無縮圖"")"),"有縮圖") -> 有縮圖
A61: 大同大學ACG繪畫暨藝術研習社 | C61: F06 | E61: E03 | G61: 繪師, 大學社團 | M61: TRUE | N61: FALSE | O61: FALSE | P61: FALSE | R61: {=IFERROR(INDEX('印量調查區'!G:G, MATCH(A61, '印量調查區'!A:A, 0)), "")} | S61: https://www.facebook.com/TTUACG/?locale=zh_TW | AR61: =IFERROR(__xludf.DUMMYFUNCTION("IF(IFERROR(VLOOKUP(A61, IMPORTRANGE(""https://docs.google.com/spreadsheets/d/1f7uHQQgxgff8nh6aFDrh_cqkeFpcVPsvJILesm778_0"", ""工作表1!A:B""), 2, FALSE), """") <> """", ""有縮圖"", ""無縮圖"")"),"無縮圖") -> 無縮圖
A62: 大江戶外萌 | D62: C11,C12 | E62: C11,C12 | G62: 繪師 | M62: TRUE | N62: FALSE | O62: FALSE | P62: FALSE | R62: {=IFERROR(INDEX('印量調查區'!G:G, MATCH(A62, '印量調查區'!A:A, 0)), "")} | S62: https://www.facebook.com/p/%E5%A4%A7%E6%B1%9F%E6%88%B6%E5%A4%96%E8%90%8C-100063894948544/?paipv=0&eav=AfZPECPFmKMUbi0PFVullQ6fwZ2PfphJLzCSlW0B74H2KVR_bYTuPdTG9uunGcYu-F0&_rdr | AR62: =IFERROR(__xludf.DUMMYFUNCTION("IF(IFERROR(VLOOKUP(A62, IMPORTRANGE(""https://docs.google.com/spreadsheets/d/1f7uHQQgxgff8nh6aFDrh_cqkeFpcVPsvJILesm778_0"", ""工作表1!A:B""), 2, FALSE), """") <> """", ""有縮圖"", ""無縮圖"")"),"無縮圖") -> 無縮圖
A63: 大阪風男 | B63: 大阪風男 | C63: U04 | D63: M15 | G63: 繪師 | M63: TRUE | N63: FALSE | O63: FALSE | P63: FALSE | R63: {=IFERROR(INDEX('印量調查區'!G:G, MATCH(A63, '印量調查區'!A:A, 0)), "")} | S63: https://www.facebook.com/profile.php?id=100095148571755 | W63: https://x.com/Oosaka212 | Y63: https://www.plurk.com/ayumu3659 | Z63: https://www.pixiv.net/users/5650892 | AA63: https://oosaka212.fanbox.cc/ | AJ63: https://home.gamer.com.tw/homeindex.php?owner=ayumu3659 | AR63: =IFERROR(__xludf.DUMMYFUNCTION("IF(IFERROR(VLOOKUP(A63, IMPORTRANGE(""https://docs.google.com/spreadsheets/d/1f7uHQQgxgff8nh6aFDrh_cqkeFpcVPsvJILesm778_0"", ""工作表1!A:B""), 2, FALSE), """") <> """", ""有縮圖"", ""無縮圖"")"),"有縮圖") -> 有縮圖
A64: 大波斯菊花園 | C64: K17 | D64: K17 | G64: 繪師 | M64: TRUE | N64: FALSE | O64: FALSE | P64: FALSE | R64: {=IFERROR(INDEX('印量調查區'!G:G, MATCH(A64, '印量調查區'!A:A, 0)), "")} | S64: https://www.facebook.com/cosmosmumu | W64: https://x.com/cosmos0204 | Y64: https://www.plurk.com/cosmos24 | Z64: https://www.pixiv.net/users/1293378 | AM64: https://www.doujin.com.tw/groups/info/195 | AR64: =IFERROR(__xludf.DUMMYFUNCTION("IF(IFERROR(VLOOKUP(A64, IMPORTRANGE(""https://docs.google.com/spreadsheets/d/1f7uHQQgxgff8nh6aFDrh_cqkeFpcVPsvJILesm778_0"", ""工作表1!A:B""), 2, FALSE), """") <> """", ""有縮圖"", ""無縮圖"")"),"無縮圖") -> 無縮圖
A65: 大御哦哦哦 | B65: 大御 | E65: G42 | G65: 繪師 | H65: R15 | I65: 二創 | J65: 米哈遊，絕區零 / ZenlessZoneZero / ゼンレスゾーンゼロ | K65: 套組 1100元 💠同人誌【夏日妄想】200元 💠單面立牌 💠雙面雷射票卡 💠壓克力色紙 (含支架) 💠明信片套組 (一組4張) 💠飯友 | M65: TRUE | N65: TRUE | O65: FALSE | P65: TRUE | R65: {=IFERROR(INDEX('印量調查區'!G:G, MATCH(A65, '印量調查區'!A:A, 0)), "")} | S65: https://www.facebook.com/dayuh.kawa/ | W65: https://x.com/Dayuh_820 | AE65: https://www.instagram.com/dayuh820/ | AF65: https://www.youtube.com/@dayuh820 | AG65: https://www.twitch.tv/dayuh820 | AI65: https://discord.com/invite/394WrEagyY | AL65: https://lit.link/zh-tw/dayuh | AO65: https://x.com/Dayuh_820/status/2078389825242358024 | AP65: https://myship.7-11.com.tw/general/detail/GM2512180397715 | AR65: =IFERROR(__xludf.DUMMYFUNCTION("IF(IFERROR(VLOOKUP(A65, IMPORTRANGE(""https://docs.google.com/spreadsheets/d/1f7uHQQgxgff8nh6aFDrh_cqkeFpcVPsvJILesm778_0"", ""工作表1!A:B""), 2, FALSE), """") <> """", ""有縮圖"", ""無縮圖"")"),"有縮圖") -> 有縮圖
A66: 大概是…夭謬? | C66: K18 | D66: K18 | G66: COSER | M66: TRUE | N66: FALSE | O66: FALSE | P66: FALSE | R66: {=IFERROR(INDEX('印量調查區'!G:G, MATCH(A66, '印量調查區'!A:A, 0)), "")} | S66: https://www.doujin.com.tw/authors/info/ilove446 | AR66: =IFERROR(__xludf.DUMMYFUNCTION("IF(IFERROR(VLOOKUP(A66, IMPORTRANGE(""https://docs.google.com/spreadsheets/d/1f7uHQQgxgff8nh6aFDrh_cqkeFpcVPsvJILesm778_0"", ""工作表1!A:B""), 2, FALSE), """") <> """", ""有縮圖"", ""無縮圖"")"),"無縮圖") -> 無縮圖
A67: 大福喵喵 | B67: 喵大福 | E67: V28 | G67: 繪師 | M67: TRUE | N67: FALSE | O67: FALSE | P67: FALSE | S67: https://www.facebook.com/daifuku.nyanya/ | U67: https://bsky.app/profile/did:plc:ytwxpofm2caozjzhwy7fywme | W67: https://x.com/cat_tsuki29 | Y67: https://www.plurk.com/cat_tsuki29 | Z67: https://www.pixiv.net/users/4671005 | AE67: https://www.instagram.com/cat_atsuki | AG67: https://www.twitch.tv/cat_tsuki | AI67: https://discord.gg/KdwZtXZNsJ | AR67: =IFERROR(__xludf.DUMMYFUNCTION("IF(IFERROR(VLOOKUP(A67, IMPORTRANGE(""https://docs.google.com/spreadsheets/d/1f7uHQQgxgff8nh6aFDrh_cqkeFpcVPsvJILesm778_0"", ""工作表1!A:B""), 2, FALSE), """") <> """", ""有縮圖"", ""無縮圖"")"),"無縮圖") -> 無縮圖
A68: 女孩日常 | B68: 雪之饗 | C68: I05 | G68: 繪師 | M68: TRUE | N68: FALSE | O68: FALSE | P68: FALSE | R68: {=IFERROR(INDEX('印量調查區'!G:G, MATCH(A68, '印量調查區'!A:A, 0)), "")} | S68: https://www.facebook.com/ekis2018/ | AR68: =IFERROR(__xludf.DUMMYFUNCTION("IF(IFERROR(VLOOKUP(A68, IMPORTRANGE(""https://docs.google.com/spreadsheets/d/1f7uHQQgxgff8nh6aFDrh_cqkeFpcVPsvJILesm778_0"", ""工作表1!A:B""), 2, FALSE), """") <> """", ""有縮圖"", ""無縮圖"")"),"無縮圖") -> 無縮圖
A69: 小文西畫廊 | B69: Davinci | E69: J31,J32 | G69: 繪師 | M69: TRUE | N69: FALSE | O69: FALSE | P69: FALSE | R69: {=IFERROR(INDEX('印量調查區'!G:G, MATCH(A69, '印量調查區'!A:A, 0)), "")} | S69: https://www.facebook.com/profile.php?id=61557752053454 | W69: https://x.com/Dasketchci | Z69: https://www.pixiv.net/users/3838279 | AA69: https://g7lhn17v.fanbox.cc/ | AI69: https://discord.com/invite/DpXgNnyAEr | AR69: =IFERROR(__xludf.DUMMYFUNCTION("IF(IFERROR(VLOOKUP(A69, IMPORTRANGE(""https://docs.google.com/spreadsheets/d/1f7uHQQgxgff8nh6aFDrh_cqkeFpcVPsvJILesm778_0"", ""工作表1!A:B""), 2, FALSE), """") <> """", ""有縮圖"", ""無縮圖"")"),"有縮圖") -> 有縮圖
A70: 小白鹿 WHITE DEER | E70: V12 | G70: 繪師 | M70: TRUE | N70: FALSE | O70: FALSE | P70: FALSE | R70: {=IFERROR(INDEX('印量調查區'!G:G, MATCH(A70, '印量調查區'!A:A, 0)), "")} | S70: https://www.facebook.com/naigua.liu.3# | W70: https://x.com/umiru___?s=21&t=4BupqqlUHOnQ83DJ2W0aqA | Z70: https://www.pixiv.net/users/114628589 | AE70: https://www.instagram.com/umiru___/ | AR70: =IFERROR(__xludf.DUMMYFUNCTION("IF(IFERROR(VLOOKUP(A70, IMPORTRANGE(""https://docs.google.com/spreadsheets/d/1f7uHQQgxgff8nh6aFDrh_cqkeFpcVPsvJILesm778_0"", ""工作表1!A:B""), 2, FALSE), """") <> """", ""有縮圖"", ""無縮圖"")"),"無縮圖") -> 無縮圖
A71: 小白熊 | B71: bbibinbing | C71: U32 | D71: U34 | G71: 繪師 | H71: 一般 | I71: 二創 | J71: 初音未來 / Hatsune Miku，vocaloid | K71: 同人誌 200元 壓克力吊飾 100元 明信片 30元 | M71: TRUE | N71: TRUE | O71: FALSE | P71: TRUE | R71: {=IFERROR(INDEX('印量調查區'!G:G, MATCH(A71, '印量調查區'!A:A, 0)), "")} | S71: https://www.facebook.com/whitericebear | W71: https://twitter.com/WhiteRiceBear | X71: https://x.com/TilliLing0130 | Y71: https://www.plurk.com/WRB | Z71: https://www.pixiv.net/users/308870 | AE71: https://www.instagram.com/whitericebear/ | AJ71: https://home.gamer.com.tw/creation.php?owner=galvestxy | AO71: https://x.com/WhiteRiceBear/status/2084614988304650500 | AR71: =IFERROR(__xludf.DUMMYFUNCTION("IF(IFERROR(VLOOKUP(A71, IMPORTRANGE(""https://docs.google.com/spreadsheets/d/1f7uHQQgxgff8nh6aFDrh_cqkeFpcVPsvJILesm778_0"", ""工作表1!A:B""), 2, FALSE), """") <> """", ""有縮圖"", ""無縮圖"")"),"無縮圖") -> 無縮圖
A72: 小朵time | C72: T38 | E72: T42 | G72: Coser | I72: 二創 | J72: 絕區零 | M72: TRUE | N72: TRUE | O72: TRUE | P72: FALSE | R72: {=IFERROR(INDEX('印量調查區'!G:G, MATCH(A72, '印量調查區'!A:A, 0)), "")} | S72: https://www.facebook.com/dodolovecat/ | W72: https://x.com/1111dodotime | AE72: https://www.instagram.com/1111dodotime | AL72: https://linktr.ee/1111dodotime | AN72: https://www.facebook.com/share/1EiDtAAZdh/?mibextid=wwXIfr https://www.facebook.com/dodolovecat/posts/pfbid0tJ8Sw8Ai81oyftwiTH3kBuAyDhCUrRyXU6vtrcU2goedvYbSSWwX42F9expKHKicl https://www.facebook.com/dodolovecat/posts/pfbid0sgL2FwKTv74RCLzARtuaFtdqhwbyV45BKuTKMT1rkNCR577UU8Xs5jZsypXRGxAhl | AR72: =IFERROR(__xludf.DUMMYFUNCTION("IF(IFERROR(VLOOKUP(A72, IMPORTRANGE(""https://docs.google.com/spreadsheets/d/1f7uHQQgxgff8nh6aFDrh_cqkeFpcVPsvJILesm778_0"", ""工作表1!A:B""), 2, FALSE), """") <> """", ""有縮圖"", ""無縮圖"")"),"無縮圖") -> 無縮圖
A73: 小羊/풍신 Kohitsuji_Pungsin | B73: 小羊/풍신 | C73: Q14 | D73: Q34 | G73: Coser | M73: TRUE | N73: FALSE | O73: FALSE | P73: FALSE | R73: {=IFERROR(INDEX('印量調查區'!G:G, MATCH(A73, '印量調查區'!A:A, 0)), "")} | S73: https://www.facebook.com/kohitsuji.pungsin.cosplay | U73: https://bsky.app/profile/kohitsujipungsin.bsky.social | W73: https://twitter.com/hitsuji_pungsin?fbclid=PAZXh0bgNhZW0CMTEAAabCTq9BipDwp_awArdK9BS8Pvg-U4kgpSErWtEtCC4HBCmMaeTcixx-gts_aem_gwx1IH6Q-J-pici3Zyt1XQ | AE73: https://www.instagram.com/kohitsuji_pungsin/ | AM73: https://www.threads.net/@kohitsuji_pungsin?xmt=AQGzkesOeJ38udeHDEqWhG62v9uyR9vkg7yHu3v79lWzsoQ | AR73: =IFERROR(__xludf.DUMMYFUNCTION("IF(IFERROR(VLOOKUP(A73, IMPORTRANGE(""https://docs.google.com/spreadsheets/d/1f7uHQQgxgff8nh6aFDrh_cqkeFpcVPsvJILesm778_0"", ""工作表1!A:B""), 2, FALSE), """") <> """", ""有縮圖"", ""無縮圖"")"),"無縮圖") -> 無縮圖
A74: 小羽feather | E74: T13,T14 | G74: Coser | M74: TRUE | N74: FALSE | O74: FALSE | P74: FALSE | R74: {=IFERROR(INDEX('印量調查區'!G:G, MATCH(A74, '印量調查區'!A:A, 0)), "")} | S74: https://www.facebook.com/zzfeather/ | W74: https://x.com/ink_night04 | AE74: https://www.instagram.com/z_inkstar?fbclid=IwY2xjawHAo1hleHRuA2FlbQIxMAABHZ0IzqHr71x_OkOx8H3J3iftJ_IpQ5T0gMPgo5YYRBX6xFOxdqaPmIgZ_g_aem_abXuwfPmrEqpWwI6W8jCMA | AF74: https://youtube.com/@user-tl1lf2mi1e?si=8i_5VhxvN0W-28tC | AH74: https://line.me/ti/g2/kFTqYlc9u0-_eyDeyTuzCWPL3p5Hh3aNakAqKQ?utm_source=invitation&utm_medium=link_copy&utm_campaign=default | AJ74: https://wall.gamer.com.tw/redir.php?userId=r0429ydy | AL74: https://linktr.ee/z_inkstar | AM74: https://www.furuke.com/880429851020 | AR74: =IFERROR(__xludf.DUMMYFUNCTION("IF(IFERROR(VLOOKUP(A74, IMPORTRANGE(""https://docs.google.com/spreadsheets/d/1f7uHQQgxgff8nh6aFDrh_cqkeFpcVPsvJILesm778_0"", ""工作表1!A:B""), 2, FALSE), """") <> """", ""有縮圖"", ""無縮圖"")"),"無縮圖") -> 無縮圖
A75: 小艾 | C75: Q17,Q18 | G75: vtuber | M75: TRUE | N75: FALSE | O75: FALSE | P75: FALSE | R75: {=IFERROR(INDEX('印量調查區'!G:G, MATCH(A75, '印量調查區'!A:A, 0)), "")} | S75: https://www.facebook.com/profile.php?id=61551905133307 | W75: https://x.com/alfadaimon | AE75: https://www.instagram.com/alfadaimon_01/ | AF75: https://www.youtube.com/@AlfaDaimon | AG75: https://www.twitch.tv/alfa_daimon | AI75: https://discord.com/invite/nvCF6vnZ47 | AL75: https://lit.link/zh-tw/alfadaimon | AR75: =IFERROR(__xludf.DUMMYFUNCTION("IF(IFERROR(VLOOKUP(A75, IMPORTRANGE(""https://docs.google.com/spreadsheets/d/1f7uHQQgxgff8nh6aFDrh_cqkeFpcVPsvJILesm778_0"", ""工作表1!A:B""), 2, FALSE), """") <> """", ""有縮圖"", ""無縮圖"")"),"無縮圖") -> 無縮圖
A76: 小町牧場 | E76: S14 | G76: Coser，日本 | M76: TRUE | N76: FALSE | O76: FALSE | P76: FALSE | R76: {=IFERROR(INDEX('印量調查區'!G:G, MATCH(A76, '印量調查區'!A:A, 0)), "")} | W76: https://x.com/nmc008es?s=21 | AE76: https://www.instagram.com/comacomachi3/ | AF76: https://www.youtube.com/@nenecomachi | AL76: https://pont.co/u/nenecomachi?utm_source=ig&utm_medium=social&utm_content=link_in_bio | AR76: =IFERROR(__xludf.DUMMYFUNCTION("IF(IFERROR(VLOOKUP(A76, IMPORTRANGE(""https://docs.google.com/spreadsheets/d/1f7uHQQgxgff8nh6aFDrh_cqkeFpcVPsvJILesm778_0"", ""工作表1!A:B""), 2, FALSE), """") <> """", ""有縮圖"", ""無縮圖"")"),"無縮圖") -> 無縮圖
A77: 小波波利那可可 | B77: 個波那 | C77: B06 | E77: B35 [寄] | G77: 繪師 | M77: TRUE | N77: FALSE | O77: TRUE | P77: FALSE | R77: {=IFERROR(INDEX('印量調查區'!G:G, MATCH(A77, '印量調查區'!A:A, 0)), "")} | S77: https://www.facebook.com/na.ge.bo.coffee89298929?__cft__[0]=AZV8AeqPcON9AKeWI9NCyQa_WtoX2Iu01eRpz75xJI_QbjRoOVJMn2V2L7IRRLoqIDRdIo7fKDx8ho_-vToDEMc80bmM68kxfZiOT5bUTd1UwtIyOlVerWpSmBcdaVJlOPk4xhiKpVdKnjP0QiER8REOf_2DQr5gwYjtqdtasXKAVQ&__tn__=-UC*F | U77: https://bsky.app/profile/thenami8929.bsky.social | W77: https://x.com/coffee89298929 | Z77: https://www.pixiv.net/users/6460806 | AL77: https://linktr.ee/thenami | AN77: https://www.facebook.com/permalink.php?story_fbid=pfbid0qUdHDGJU8VjVTpqdB11cDgnz6Mq3vQDA7qrNaczSjNxwKkr1R3SwbLHs41KhQaUAl&id=100073147566142 https://www.facebook.com/permalink.php?story_fbid=pfbid0sM61zynJE2TPjDJn6gt7c63oM8Gwo2fvZZUpLLnJsnWa14S3Wdm9ggCFwzqsxAuyl&id=100073147566142 | AR77: =IFERROR(__xludf.DUMMYFUNCTION("IF(IFERROR(VLOOKUP(A77, IMPORTRANGE(""https://docs.google.com/spreadsheets/d/1f7uHQQgxgff8nh6aFDrh_cqkeFpcVPsvJILesm778_0"", ""工作表1!A:B""), 2, FALSE), """") <> """", ""有縮圖"", ""無縮圖"")"),"無縮圖") -> 無縮圖
A78: 小狗咪出沒注意 (阿不思1號) | B78: 阿不思、荷月晴 | C78: K21 | E78: L09 | G78: 繪師 | H78: R18 | I78: 二創 | J78: Hololive | K78: 畫冊、立牌、掛軸 | L78: 男性向 | M78: TRUE | N78: TRUE | O78: FALSE | P78: FALSE | R78: {=IFERROR(INDEX('印量調查區'!G:G, MATCH(A78, '印量調查區'!A:A, 0)), "")} | S78: https://www.facebook.com/share/14irLqsoDPA/ | T78: https://www.facebook.com/share/18zsghmMao/ | W78: https://x.com/0_albusart | X78: https://x.com/Nitsuki_Hare | AR78: =IFERROR(__xludf.DUMMYFUNCTION("IF(IFERROR(VLOOKUP(A78, IMPORTRANGE(""https://docs.google.com/spreadsheets/d/1f7uHQQgxgff8nh6aFDrh_cqkeFpcVPsvJILesm778_0"", ""工作表1!A:B""), 2, FALSE), """") <> """", ""有縮圖"", ""無縮圖"")"),"無縮圖") -> 無縮圖
A79: 小咩 | D79: Q06 | E79: Q06 | G79: Coser，香港 | M79: TRUE | N79: FALSE | O79: FALSE | P79: FALSE | R79: {=IFERROR(INDEX('印量調查區'!G:G, MATCH(A79, '印量調查區'!A:A, 0)), "")} | S79: https://www.facebook.com/Mei.0107/?ref=NONE_xav_ig_profile_page_web# | W79: https://x.com/siumei_0107 | AE79: https://www.instagram.com/siumei_0107/ | AR79: =IFERROR(__xludf.DUMMYFUNCTION("IF(IFERROR(VLOOKUP(A79, IMPORTRANGE(""https://docs.google.com/spreadsheets/d/1f7uHQQgxgff8nh6aFDrh_cqkeFpcVPsvJILesm778_0"", ""工作表1!A:B""), 2, FALSE), """") <> """", ""有縮圖"", ""無縮圖"")"),"無縮圖") -> 無縮圖
A80: 小律 Ritsu | C80: Q37,Q38 | E80: Q41,Q42 | G80: Coser | M80: TRUE | N80: FALSE | O80: FALSE | P80: FALSE | R80: {=IFERROR(INDEX('印量調查區'!G:G, MATCH(A80, '印量調查區'!A:A, 0)), "")} | S80: https://www.facebook.com/share/1Ckc6VKWNx/?mibextid=wwXIfr | AE80: https://www.instagram.com/ritsuoxo?igsh=ZGZheTIwZGxmOGh0 | AR80: =IFERROR(__xludf.DUMMYFUNCTION("IF(IFERROR(VLOOKUP(A80, IMPORTRANGE(""https://docs.google.com/spreadsheets/d/1f7uHQQgxgff8nh6aFDrh_cqkeFpcVPsvJILesm778_0"", ""工作表1!A:B""), 2, FALSE), """") <> """", ""有縮圖"", ""無縮圖"")"),"無縮圖") -> 無縮圖
A81: 小馬麗’Mary | C81: R42 | G81: Coser | M81: TRUE | N81: FALSE | O81: FALSE | P81: FALSE | R81: {=IFERROR(INDEX('印量調查區'!G:G, MATCH(A81, '印量調查區'!A:A, 0)), "")} | S81: https://www.facebook.com/littlemaryJ/?locale=zh_TW | AE81: https://www.instagram.com/__mari__j_/ | AG81: https://www.twitch.tv/lamento821229 | AL81: https://linktr.ee/littlemarieJ | AM81: https://linkpota.to/mari_j | AR81: =IFERROR(__xludf.DUMMYFUNCTION("IF(IFERROR(VLOOKUP(A81, IMPORTRANGE(""https://docs.google.com/spreadsheets/d/1f7uHQQgxgff8nh6aFDrh_cqkeFpcVPsvJILesm778_0"", ""工作表1!A:B""), 2, FALSE), """") <> """", ""有縮圖"", ""無縮圖"")"),"無縮圖") -> 無縮圖
A82: 小雪Yukichan | B82: 小雪/阿鼠 | C82: M30 | D82: M30 | G82: vtuber | H82: R15 | I82: 原創 | K82: 💠同人誌 插畫本 350元 💠魔法少女套組 10套 1500元 壓克力立牌 徽章 壓克力鑰匙圈 明信片 | M82: TRUE | N82: TRUE | O82: FALSE | P82: TRUE | R82: {=IFERROR(INDEX('印量調查區'!G:G, MATCH(A82, '印量調查區'!A:A, 0)), "")} | S82: https://www.google.com/url?sa=t&source=web&rct=j&opi=89978449&url=https://www.facebook.com/%40yasetsu1314520/&ved=2ahUKEwi5ku-O6ZqKAxW7n68BHTzXAMUQFnoECCgQAQ&usg=AOvVaw0KxfrGnn6QGQikkSKqttMw | W82: https://www.google.com/url?sa=t&source=web&rct=j&opi=89978449&url=https://twitter.com/Yukichan1102%3Fref_src%3Dtwsrc%255Egoogle%257Ctwcamp%255Eserp%257Ctwgr%255Eauthor&ved=2ahUKEwi5ku-O6ZqKAxW7n68BHTzXAMUQ6F56BAhBEAE&usg=AOvVaw1xa9UEFSu3EujAX7uVVokM | AF82: https://www.google.com/url?sa=t&source=web&rct=j&opi=89978449&url=https://www.youtube.com/channel/UCQymE4njJ-t9oahwX9-iC8w&ved=2ahUKEwi5ku-O6ZqKAxW7n68BHTzXAMUQFnoECBoQAQ&usg=AOvVaw0AZkRRD-Q5btlVcPMcso10 | AG82: https://www.google.com/url?sa=t&source=web&rct=j&opi=89978449&url=https://www.twitch.tv/hosinoyasetsu%3Flang%3Dzh-tw&ved=2ahUKEwi5ku-O6ZqKAxW7n68BHTzXAMUQFnoECBsQAQ&usg=AOvVaw0vOpddAijLPnz6BehVhX5Z | AI82: DISCORD | AJ82: 巴哈姆特 | AO82: https://x.com/Yukichan1102/status/2086101771420881106 | AR82: =IFERROR(__xludf.DUMMYFUNCTION("IF(IFERROR(VLOOKUP(A82, IMPORTRANGE(""https://docs.google.com/spreadsheets/d/1f7uHQQgxgff8nh6aFDrh_cqkeFpcVPsvJILesm778_0"", ""工作表1!A:B""), 2, FALSE), """") <> """", ""有縮圖"", ""無縮圖"")"),"無縮圖") -> 無縮圖
A83: 小喵喵不講舞德 | B83: Mai喵 | C83: S37,S38 | D83: S37 | G83: Coser | M83: TRUE | N83: FALSE | O83: FALSE | P83: FALSE | Q83: 高 | R83: {=IFERROR(INDEX('印量調查區'!G:G, MATCH(A83, '印量調查區'!A:A, 0)), "")} | S83: https://www.facebook.com/share/16WCrUvAao/?mibextid=wwXIfr | W83: https://twitter.com/maiqqcatbb | AE83: https://www.instagram.com/maimeow0?igsh=MTg3bmR0cDU5ZzFjdg== | AF83: https://youtube.com/@maiqqcatbb | AR83: =IFERROR(__xludf.DUMMYFUNCTION("IF(IFERROR(VLOOKUP(A83, IMPORTRANGE(""https://docs.google.com/spreadsheets/d/1f7uHQQgxgff8nh6aFDrh_cqkeFpcVPsvJILesm778_0"", ""工作表1!A:B""), 2, FALSE), """") <> """", ""有縮圖"", ""無縮圖"")"),"無縮圖") -> 無縮圖
A84: 小琪 Aki Cosplayer | D84: R28 | E84: R28 | G84: Coser | M84: TRUE | N84: FALSE | O84: FALSE | P84: FALSE | R84: {=IFERROR(INDEX('印量調查區'!G:G, MATCH(A84, '印量調查區'!A:A, 0)), "")} | S84: https://www.facebook.com/aki.coser/ | AE84: https://www.instagram.com/ringoaki/ | AR84: =IFERROR(__xludf.DUMMYFUNCTION("IF(IFERROR(VLOOKUP(A84, IMPORTRANGE(""https://docs.google.com/spreadsheets/d/1f7uHQQgxgff8nh6aFDrh_cqkeFpcVPsvJILesm778_0"", ""工作表1!A:B""), 2, FALSE), """") <> """", ""有縮圖"", ""無縮圖"")"),"無縮圖") -> 無縮圖
A85: 小菊小花園 | C85: U42 | E85: U44 | G85: 繪師 | M85: TRUE | N85: FALSE | O85: FALSE | P85: FALSE | R85: {=IFERROR(INDEX('印量調查區'!G:G, MATCH(A85, '印量調查區'!A:A, 0)), "")} | S85: https://www.facebook.com/hua.xiao.hua.859628/ | W85: https://x.com/0_71_Rain | Y85: https://www.plurk.com/kikukiku599 | Z85: https://www.pixiv.net/users/13155227 | AR85: =IFERROR(__xludf.DUMMYFUNCTION("IF(IFERROR(VLOOKUP(A85, IMPORTRANGE(""https://docs.google.com/spreadsheets/d/1f7uHQQgxgff8nh6aFDrh_cqkeFpcVPsvJILesm778_0"", ""工作表1!A:B""), 2, FALSE), """") <> """", ""有縮圖"", ""無縮圖"")"),"無縮圖") -> 無縮圖
A86: 小壽司的快樂板板 | B86: 莊鎔維 | D86: J29,J30 | E86: J19,J20 | G86: 繪師 | M86: TRUE | N86: FALSE | O86: FALSE | P86: FALSE | R86: {=IFERROR(INDEX('印量調查區'!G:G, MATCH(A86, '印量調查區'!A:A, 0)), "")} | S86: https://www.facebook.com/zhuang.rong.wei.449636/ | W86: https://x.com/Luneceygs | Z86: https://www.pixiv.net/users/9998207 | AK86: https://potofu.me/luneceygs | AR86: =IFERROR(__xludf.DUMMYFUNCTION("IF(IFERROR(VLOOKUP(A86, IMPORTRANGE(""https://docs.google.com/spreadsheets/d/1f7uHQQgxgff8nh6aFDrh_cqkeFpcVPsvJILesm778_0"", ""工作表1!A:B""), 2, FALSE), """") <> """", ""有縮圖"", ""無縮圖"")"),"有縮圖") -> 有縮圖
A87: 小漾樣x樣樣子 | B87: 漾樣子 | C87: T03,T04 | D87: T04 | G87: vtuber，Coser | M87: TRUE | N87: FALSE | O87: FALSE | P87: FALSE | R87: {=IFERROR(INDEX('印量調查區'!G:G, MATCH(A87, '印量調查區'!A:A, 0)), "")} | S87: https://www.facebook.com/TwoyunCosplay | W87: https://x.com/7woyun | X87: https://x.com/twoyun25 | AD87: https://www.patreon.com/Twoyuncosplay | AE87: https://www.instagram.com/7woyun/ | AF87: https://www.youtube.com/@Twoyun25 | AJ87: https://home.gamer.com.tw/profile/index.php?owner=darksteel | AL87: https://lit.link/zh-tw/twoyuncosplay https://linktr.ee/Twoyuncosplay | AM87: https://twoyuncosplay.gumroad.com/ | AR87: =IFERROR(__xludf.DUMMYFUNCTION("IF(IFERROR(VLOOKUP(A87, IMPORTRANGE(""https://docs.google.com/spreadsheets/d/1f7uHQQgxgff8nh6aFDrh_cqkeFpcVPsvJILesm778_0"", ""工作表1!A:B""), 2, FALSE), """") <> """", ""有縮圖"", ""無縮圖"")"),"無縮圖") -> 無縮圖
A88: 小熊貓工作室 | C88: T17 | D88: T17 | G88: Coser | M88: TRUE | N88: FALSE | O88: FALSE | P88: FALSE | R88: {=IFERROR(INDEX('印量調查區'!G:G, MATCH(A88, '印量調查區'!A:A, 0)), "")} | AE88: https://www.instagram.com/fox_together_with_rabbit/ | AK88: https://foxtogetherwithrabbit.mystrikingly.com/ | AR88: =IFERROR(__xludf.DUMMYFUNCTION("IF(IFERROR(VLOOKUP(A88, IMPORTRANGE(""https://docs.google.com/spreadsheets/d/1f7uHQQgxgff8nh6aFDrh_cqkeFpcVPsvJILesm778_0"", ""工作表1!A:B""), 2, FALSE), """") <> """", ""有縮圖"", ""無縮圖"")"),"無縮圖") -> 無縮圖
A89: 小撿存檔點 | B89: Xiao Jen | D89: O16 | E89: O16 | G89: 繪師 | I89: 二創 | J89: 蔚藍檔案 / Blue Archive / ブルーアーカイブ | M89: TRUE | N89: TRUE | O89: FALSE | P89: FALSE | R89: {=IFERROR(INDEX('印量調查區'!G:G, MATCH(A89, '印量調查區'!A:A, 0)), "")} | S89: https://www.facebook.com/xiao.jen.3304 | W89: https://x.com/yeeeeeeejen | Z89: https://www.pixiv.net/users/3109265 | AR89: =IFERROR(__xludf.DUMMYFUNCTION("IF(IFERROR(VLOOKUP(A89, IMPORTRANGE(""https://docs.google.com/spreadsheets/d/1f7uHQQgxgff8nh6aFDrh_cqkeFpcVPsvJILesm778_0"", ""工作表1!A:B""), 2, FALSE), """") <> """", ""有縮圖"", ""無縮圖"")"),"有縮圖") -> 有縮圖
A90: 小翼小光180 | E90: S43,S44 | G90: Coser | M90: TRUE | N90: FALSE | O90: FALSE | P90: FALSE | R90: {=IFERROR(INDEX('印量調查區'!G:G, MATCH(A90, '印量調查區'!A:A, 0)), "")} | S90: https://www.facebook.com/TSUBASA.OwO/ | AR90: =IFERROR(__xludf.DUMMYFUNCTION("IF(IFERROR(VLOOKUP(A90, IMPORTRANGE(""https://docs.google.com/spreadsheets/d/1f7uHQQgxgff8nh6aFDrh_cqkeFpcVPsvJILesm778_0"", ""工作表1!A:B""), 2, FALSE), """") <> """", ""有縮圖"", ""無縮圖"")"),"無縮圖") -> 無縮圖
A91: 小顆子 | C91: C15 | D91: C07 | G91: 繪師 | M91: TRUE | N91: FALSE | O91: FALSE | P91: FALSE | R91: {=IFERROR(INDEX('印量調查區'!G:G, MATCH(A91, '印量調查區'!A:A, 0)), "")} | W91: https://x.com/TheLittleThingy | AE91: https://www.instagram.com/The_Little_Thingy/ | AG91: https://www.twitch.tv/TheLittleThingy | AL91: https://linktr.ee/TheLittleThingy?utm_source=ig&utm_medium=social&utm_content=link_in_bio | AR91: =IFERROR(__xludf.DUMMYFUNCTION("IF(IFERROR(VLOOKUP(A91, IMPORTRANGE(""https://docs.google.com/spreadsheets/d/1f7uHQQgxgff8nh6aFDrh_cqkeFpcVPsvJILesm778_0"", ""工作表1!A:B""), 2, FALSE), """") <> """", ""有縮圖"", ""無縮圖"")"),"無縮圖") -> 無縮圖
A92: 小薰的百變魔法衣櫥 | D92: R11 | E92: Q05 | G92: Coser | M92: TRUE | N92: FALSE | O92: FALSE | P92: FALSE | R92: {=IFERROR(INDEX('印量調查區'!G:G, MATCH(A92, '印量調查區'!A:A, 0)), "")} | S92: https://www.facebook.com/hui.ju.chang.54693 | AR92: =IFERROR(__xludf.DUMMYFUNCTION("IF(IFERROR(VLOOKUP(A92, IMPORTRANGE(""https://docs.google.com/spreadsheets/d/1f7uHQQgxgff8nh6aFDrh_cqkeFpcVPsvJILesm778_0"", ""工作表1!A:B""), 2, FALSE), """") <> """", ""有縮圖"", ""無縮圖"")"),"無縮圖") -> 無縮圖
A93: 小雞塊嗶嗶 | B93: 口畢雞 | D93: D29 | E93: D29 | G93: 繪師 | H93: 一般 | I93: 二創 | J93: 明日方舟終末地、明日方舟 | K93: 套組1 600元 💠掛軸 500元 💠吊飾 100元 套組2 450元 💠立牌 350元 💠厚飯友 100元 掛軸 450元 鈴蘭搖搖壓克力 100元 | M93: TRUE | N93: TRUE | O93: TRUE | P93: TRUE | R93: {=IFERROR(INDEX('印量調查區'!G:G, MATCH(A93, '印量調查區'!A:A, 0)), "")} | S93: https://www.facebook.com/share/1Hdu3wfWi6/?mibextid=wwXIfr | W93: https://x.com/shinas_13?s=21 | AL93: https://portaly.cc/ShinaS13 | AN93: https://www.facebook.com/xiao.ji.kuai.shang.gong/posts/pfbid02zNSVpwgbT9VBbDdqZwzhQyrK73U8BscS6RRG2WyZ5MrLeJS7yo1VSj187UYHHErrl https://www.facebook.com/xiao.ji.kuai.shang.gong/posts/pfbid0r6NVKszdC4x6c92fuEd5N6wXsveD8gsiUb5xKfcbZgKjJY24wXTaxt3drS8mKq8Ul | AO93: https://www.facebook.com/xiao.ji.kuai.shang.gong/posts/pfbid038MjFhUhCDNi9fFXLzwFJ2rq2AFU6rw2YVLBhDtUvV4ga6pUka5p7sekvFtVrX172l | AP93: https://myship.7-11.com.tw/general/detail/GM2312258759908 | AR93: =IFERROR(__xludf.DUMMYFUNCTION("IF(IFERROR(VLOOKUP(A93, IMPORTRANGE(""https://docs.google.com/spreadsheets/d/1f7uHQQgxgff8nh6aFDrh_cqkeFpcVPsvJILesm778_0"", ""工作表1!A:B""), 2, FALSE), """") <> """", ""有縮圖"", ""無縮圖"")"),"有縮圖") -> 有縮圖
A94: 川崎重工 | C94: L32 | D94: L13 | G94: 繪師 | M94: TRUE | N94: FALSE | O94: TRUE | P94: FALSE | R94: {=IFERROR(INDEX('印量調查區'!G:G, MATCH(A94, '印量調查區'!A:A, 0)), "")} | S94: https://www.facebook.com/profile.php?id=100086439973776&__cft__[0]=AZVAOb6VbmkfbXX6Qhgs__LzgRk-eIRjN-w2cszmSspTazf8xQN4Xa24xeGZNPFoSnZ9tRfmc6OaXq9c5ZPQeOR0xQptqjEEUPQ6AREw6Ti1BH-cS2w43GAYTf7nkaPtQiLVvlb4O-k28RH4wWbNQpJ_88itMdWI1YkA8UPllIlWOUSCl95RHSyFRuQjaBJjtu0&__tn__=-UC%2CP-R-R | AN94: https://www.facebook.com/shan.yan.266094/posts/pfbid02DdiZmkwEKKeGzpMXodAnQT5hZa67FTeV3xxnSMSD99p55dJuXri7d2rtwb1E9XeQl | AR94: =IFERROR(__xludf.DUMMYFUNCTION("IF(IFERROR(VLOOKUP(A94, IMPORTRANGE(""https://docs.google.com/spreadsheets/d/1f7uHQQgxgff8nh6aFDrh_cqkeFpcVPsvJILesm778_0"", ""工作表1!A:B""), 2, FALSE), """") <> """", ""有縮圖"", ""無縮圖"")"),"無縮圖") -> 無縮圖
A95: 工口中毒ガールM10 | D95: Q32 | E95: Q32 | G95: Coser | M95: FALSE | N95: FALSE | O95: FALSE | P95: FALSE | R95: {=IFERROR(INDEX('印量調查區'!G:G, MATCH(A95, '印量調查區'!A:A, 0)), "")} | AR95: =IFERROR(__xludf.DUMMYFUNCTION("IF(IFERROR(VLOOKUP(A95, IMPORTRANGE(""https://docs.google.com/spreadsheets/d/1f7uHQQgxgff8nh6aFDrh_cqkeFpcVPsvJILesm778_0"", ""工作表1!A:B""), 2, FALSE), """") <> """", ""有縮圖"", ""無縮圖"")"),"無縮圖") -> 無縮圖
A96: 工坊夏至千里 | D96: K35 | G96: 繪師 | M96: TRUE | N96: FALSE | O96: FALSE | P96: FALSE | R96: {=IFERROR(INDEX('印量調查區'!G:G, MATCH(A96, '印量調查區'!A:A, 0)), "")} | S96: https://www.facebook.com/km1000km1000/ | AJ96: https://home.gamer.com.tw/profile/index.php?owner=summerkmth | AR96: =IFERROR(__xludf.DUMMYFUNCTION("IF(IFERROR(VLOOKUP(A96, IMPORTRANGE(""https://docs.google.com/spreadsheets/d/1f7uHQQgxgff8nh6aFDrh_cqkeFpcVPsvJILesm778_0"", ""工作表1!A:B""), 2, FALSE), """") <> """", ""有縮圖"", ""無縮圖"")"),"無縮圖") -> 無縮圖
A97: 不要那麼吉 | D97: B09 | M97: FALSE | N97: FALSE | O97: FALSE | P97: FALSE | R97: {=IFERROR(INDEX('印量調查區'!G:G, MATCH(A97, '印量調查區'!A:A, 0)), "")} | AR97: =IFERROR(__xludf.DUMMYFUNCTION("IF(IFERROR(VLOOKUP(A97, IMPORTRANGE(""https://docs.google.com/spreadsheets/d/1f7uHQQgxgff8nh6aFDrh_cqkeFpcVPsvJILesm778_0"", ""工作表1!A:B""), 2, FALSE), """") <> """", ""有縮圖"", ""無縮圖"")"),"無縮圖") -> 無縮圖
A98: 不要碰我的狗 | B98: tsumi | E98: D27 | G98: 繪師 | I98: 二創 | J98: 明日方舟 | M98: TRUE | N98: TRUE | O98: FALSE | P98: FALSE | R98: {=IFERROR(INDEX('印量調查區'!G:G, MATCH(A98, '印量調查區'!A:A, 0)), "")} | S98: https://www.facebook.com/profile.php?id=100064811495948 | W98: https://x.com/AmakuraHaruka | Z98: https://www.pixiv.net/users/18325314 | AR98: =IFERROR(__xludf.DUMMYFUNCTION("IF(IFERROR(VLOOKUP(A98, IMPORTRANGE(""https://docs.google.com/spreadsheets/d/1f7uHQQgxgff8nh6aFDrh_cqkeFpcVPsvJILesm778_0"", ""工作表1!A:B""), 2, FALSE), """") <> """", ""有縮圖"", ""無縮圖"")"),"無縮圖") -> 無縮圖
A99: 中央動畫社 | C99: O28 | D99: O28 | G99: 學生社團 | I99: 二創 | J99: 蔚藍檔案 / Blue Archive / ブルーアーカイブ | M99: TRUE | N99: TRUE | O99: FALSE | P99: FALSE | R99: {=IFERROR(INDEX('印量調查區'!G:G, MATCH(A99, '印量調查區'!A:A, 0)), "")} | S99: https://www.facebook.com/ncuanimeclub | Y99: https://www.plurk.com/NCUACG | AC99: https://clusters.tw/profile/47AFE9E2-0664-4F7B-92CC-B7CE1220A981/plans | AF99: https://www.youtube.com/channel/UCiqgchrGAe72bDcMyCy8Wwg | AK99: https://ncuacg.pixnet.net/blog | AR99: =IFERROR(__xludf.DUMMYFUNCTION("IF(IFERROR(VLOOKUP(A99, IMPORTRANGE(""https://docs.google.com/spreadsheets/d/1f7uHQQgxgff8nh6aFDrh_cqkeFpcVPsvJILesm778_0"", ""工作表1!A:B""), 2, FALSE), """") <> """", ""有縮圖"", ""無縮圖"")"),"無縮圖") -> 無縮圖
A100: 中原大學漫畫研習社 | D100: H05 | E100: H05 | G100: 學生社團 | M100: TRUE | N100: FALSE | O100: FALSE | P100: FALSE | R100: {=IFERROR(INDEX('印量調查區'!G:G, MATCH(A100, '印量調查區'!A:A, 0)), "")} | S100: https://www.facebook.com/cyccacglab/?locale=zh_TW | AR100: =IFERROR(__xludf.DUMMYFUNCTION("IF(IFERROR(VLOOKUP(A100, IMPORTRANGE(""https://docs.google.com/spreadsheets/d/1f7uHQQgxgff8nh6aFDrh_cqkeFpcVPsvJILesm778_0"", ""工作表1!A:B""), 2, FALSE), """") <> """", ""有縮圖"", ""無縮圖"")"),"無縮圖") -> 無縮圖
...

Sheet 集中宣傳區
A1: FF47 攤位集中宣傳區 (吃土單/宣傳串/廣告區)，歡迎攤主自行利用 [完成表單後，請協助在您的攤位欄位最底下拉底線，感謝]
A2: 攤位名稱 | B2: 天數 | C2: 攤位編號 | D2: 販售主題 | E2: 販售品項 | F2: 角色 / CP等 | G2: 售價 | H2: 品書/預告連結 | I2: 年齡分級 | J2: 特殊備註
A3: 加帕利天藍怪預警中心 [範例] | B3: 第二天 | C3: F22, F23 | D3: 點兔、蔚藍檔案、原創 [範例] | E3: 同人誌【xxxxxxxxx】 | F3: 心愛、智乃 | G3: 200 | H3: 預告 | I3: R18 | J3: 泡泡戀物癖
B4: 第三天 | C4: F23 | E4: 壓克力立牌 | F4: 智乃、冬優 | G4: 250 | H4: 品書 | I4: R15 | J4: [此為範例]
B5: 第二天 | C5: x | E5: 壓克力吊飾 | F5: 伊吹、原創 | G5: 150 | H5: [請在此放入連結] | I5: 一般
A6: 背骨貓屋 | B6: 第一天 | C6: W31、W32 | D6: 原創 鄰座的同學(們)怎麼有點奇怪 | E6: となおか新刊 | G6: NTD200 | H6: 通販 https://www.myacg.com.tw/seller_market.php?seller=551830 | I6: 一般
B7: 第二天 | C7: W31、W32 | E7: となおか新刊套組(插畫集『せぼあーと2』、雙面壓克力PP夾(4入)、 花奈醬姆指扇、不織布袋、明信片組三入) | F7: 花奈、貓山、砂糖 | G7: NTD600 | H7: 品書 https://www.facebook.com/share/p/1BkbZZrLDq// | I7: 一般
B8: 第三天 | C8: W31、W32 | E8: B2泳裝掛軸 (有三種款式) | F8: 花奈、貓山、砂糖 | G8: NTD600 | I8: 一般
A9: ACGN創作權益推動協會 | B9: 第一天 | C9: H34 | D9: 原創 | E9: ACGNMaker創刊號 | G9: 200 | H9: 預告：https://www.facebook.com/share/p/17t7488g78/ | I9: 一般
B10: 第二天 | C10: H34 | E10: 協會看板娘立牌 | G10: 150 | I10: 一般 | J10: 套組：300
A11: 秋森萬玩具店 | B11: 第一天 | C11: E08 | D11: 二創 | E11: 戰錘40k 獅王性轉同人本《別當哥哥了！但是在40k》(小黃雞老師) | F11: 戰錘40K 基因原體 獅王 萊恩 攝政王 基里曼 | G11: 350 | I11: 一般 | J11: 代理販售 全球限量 售完為止
E12: 戰錘40K 蘿伯特‧姬里蔓 金属書籤 (蟹仁飯老師) | G12: 400 | I12: 一般

Sheet 印量調查區
A1: 印量調查區，歡迎貼上貴攤位的印調資訊喔
A2: 您的攤位名稱 (需跟資料庫相同) | B2: 預計販售刊物/商品 | C2: 販售主題 | D2: 年齡分級 | E2: 刊物/商品簡介 | F2: 試閱連結 | G2: 印調連結
A3: 加帕利天藍怪預警中心 [範例] | B3: 同人誌【xxxx】、壓克力立牌 | C3: 點兔、蔚藍檔案 | D3: 一般, R18 | E3: xxxooooxxxx | F3: https://www.facebook.com/JapariWeatherBureau/posts/pfbid0sBU7c7iMXzyNrWzgnG4fgce7oo8JVx3N2oRjbi4cYrqscnTpbFHNGN3mREvfp89Ll | G3: https://www.facebook.com/JapariWeatherBureau/
A4: 星球蛋糕捲☆ | B4: T-Shirt | C4: Maimai | D4: 一般 | F4: https://www.facebook.com/share/p/18gS9cDbLt/?mibextid=wwXIfr | G4: https://forms.gle/ma1VC5NsLceRWKHeA
A5: 萬象澄澈 | B5: 同人誌【全年齡向原神本】 | C5: 原神 | D5: 一般 | E5: cp：洛恩x熒x葉洛亞/all熒（可嗑可代） | F5: https://www.plurk.com/p/3iwzaz0o46 | G5: https://forms.gle/PXowBJWWJhYe42Ud6
A6: SyuanIshen | B6: 同人誌、周邊 | C6: 九日 | D6: 一般, R18 | E6: CP：羿恆骨科 | F6: https://www.plurk.com/p/3iwjyyo30w | G6: https://docs.google.com/forms/d/e/1FAIpQLSd3MLMudawLu_L3bRP_1gD71TAsfvdbzGVRQ1t764WIv77Kzw/viewform
A7: 麥茶園 | B7: 飯友 | C7: 賽馬娘 | D7: 一般 | E7: 無聲鈴鹿 | F7: https://www.facebook.com/share/p/1D7BMk3e5M/ | G7: https://docs.google.com/forms/d/e/1FAIpQLScbxtqQ5_lSL1ytSo35TW5noX5KGbzJMVAyn_rZ6jkR-DNmfA/viewform?usp=dialog
A8: 邊緣小地方 | B8: 同人誌 | C8: 原創 | D8: R18 | E8: 雙頭龍X天使+惡魔的快樂瑟瑟3P | F8: https://www.doujin.com.tw/books/info/70374 | G8: https://forms.gle/Ktev8Lzxf36gfCHUA
A9: 茨城的繪圖小窩 | B9: 同人誌 | C9: 終末地,MyGO | D9: 一般 R18 | E9: 咕嘎騎士大戰爭 | F9: https://docs.google.com/forms/d/e/1FAIpQLScRQb-DXosWnqwpibAbgRtaCyCcOFP2QD4hPJa1-RP2_i0ueg/viewform?usp=dialog

Sheet 交流區
A1: 純粹的交流區，各位想留甚麼就留什麼吧 (或是有問題也可以詢問喔)
A2: 主編留 | B2: 主編7/3退伍，倒數中😌
A3: 粗線條工房AKN阿根 | B3: 我只是來說一下，你們整理這些資料的人都好帥😘
A4: 捲 | B4: 謝謝主編小編們，今年也全力支持！！
A5: 阿嵐章魚繪圖手作舖 | B5: 感謝各位每次整理的資訊QQ! 突然發現快登出國軍Online了! 最後衝刺!
A6: 阿嵐章魚繪圖手作舖 | B6: 註：我是社團【萬象澄澈】的友人/小精靈，有幫他先填一些資料，若造成不便的話，先在此說聲抱歉QQ
A7: 奇譚異書齋 | B7: 感謝主編小編們每次都這麼用心整理資訊，真的幫很大的忙~ 也在這預祝各位前輩完售，滿箱進場空箱回家
A8: DeityMark | B8: 謝謝你們每次都提前整理表單!真的幫了很多忙非常感謝主編及小編們!!!
A9: 雞塊 | B9: 感謝各位每次的整理!正要上來丟資料發現都被填好了神之效率QQQQ
A10: 主編留 | B10: 不會，這是我們應該要做的👍
A11: 蛙君 | B11: 感謝你們每年的資訊整理，今年異常炎熱，屆時請務必注意身體狀況QQ
A12: 秋森萬玩具店 | B12: 感謝【加帕利天藍怪預警中心】整理資訊與提供攤位宣傳，本店第一次參與擺攤，還請各位多指教

Sheet 0608更新名單
A1: 攤位名稱 | B1: 第一天 攤數 | C1: 第二天 攤位 | D1: 第三天 攤數
A2: 2.5 | B2: 0 | C2: 0 | D2: 1
A3: 825 | B3: 0 | C3: 1 | D3: 0
A4: #DREAMProject [JooA Cosplay] | B4: 0 | C4: 2 | D4: 2
A5: #DREAMProject Momo | B5: 0 | C5: 1 | D5: 1
A6: #DREAMProject Neneko | B6: 0 | C6: 2 | D6: 2
A7: #DREAMProject Shimo | B7: 0 | C7: 2 | D7: 2
A8: #DREAMProject Usagi羽咲 | B8: 0 | C8: 1 | D8: 1
A9: [CHOCOLATE SHOP] | B9: 2 | C9: 2 | D9: 0
A10: ～NEKONABE～ | B10: 0 | C10: 0 | D10: 1
A11: ～黑色布丁～ | B11: 0 | C11: 1 | D11: 1
A12: 【ZENTENG】 | B12: 0 | C12: 0 | D12: 1
A13: ‘+Ely Cosplay+ | B13: 0 | C13: 2 | D13: 2
A14: ＋そおの | B14: 0 | C14: 1 | D14: 2
A15: =+喵耳園魔法道具屋+ -> #ERROR! | B15: 2 | C15: 2 | D15: 0
A16: ♡可凡kofan0331 | B16: 2 | C16: 2 | D16: 0
A17: 0蛋黃女子由奈0 | B17: 0 | C17: 1 | D17: 1
A18: 1%小風 | B18: 1 | C18: 0 | D18: 0
A19: 23.4ド＆きのこのみ＆蜂蜜少女 | B19: 0 | C19: 1 | D19: 0
A20: 33号部屋 | B20: 1 | C20: 1 | D20: 0
A21: 404便利通販 | B21: 1 | C21: 0 | D21: 1
A22: 44c_isaac | B22: 1 | C22: 0 | D22: 1
A23: 5年目の放課後 | B23: 0 | C23: 1 | D23: 0
A24: 74 Production | B24: 0 | C24: 1 | D24: 0
A25: 7B鉛筆 | B25: 0 | C25: 0 | D25: 1
A26: 8七兔 | B26: 1 | C26: 0 | D26: 0
A27: A-Brei Atelier | B27: 0 | C27: 0 | D27: 2
... A1333: 鱷魚恐龍工作室 | B1333: 0 | C1333: 1 | D1333: 2

Sheet 整理進度
A1: =IFERROR(__xludf.DUMMYFUNCTION("IMPORTRANGE(""https://docs.google.com/spreadsheets/d/19o9oHQTeznK_QNRjWlIvU6k3aAhW0SjEDxdYIiw60QE"",""FF47!A:F"")"),"攤位總數") -> 攤位總數 | B1: =IFERROR(__xludf.DUMMYFUNCTION("""COMPUTED_VALUE"""),1336.0) -> 1336 | C1: =IFERROR(__xludf.DUMMYFUNCTION("""COMPUTED_VALUE"""),"攤位總數") -> 攤位總數 | D1: =IFERROR(__xludf.DUMMYFUNCTION("""COMPUTED_VALUE"""),1336.0) -> 1336
A2: =IFERROR(__xludf.DUMMYFUNCTION("""COMPUTED_VALUE"""),"無資料攤位") -> 無資料攤位 | B2: =IFERROR(__xludf.DUMMYFUNCTION("""COMPUTED_VALUE"""),68.0) -> 68 | C2: =IFERROR(__xludf.DUMMYFUNCTION("""COMPUTED_VALUE"""),"無資料攤位") -> 無資料攤位 | D2: =IFERROR(__xludf.DUMMYFUNCTION("""COMPUTED_VALUE"""),68.0) -> 68
A3: =IFERROR(__xludf.DUMMYFUNCTION("""COMPUTED_VALUE"""),"有攤位資料 (SNS、攤主資訊、本場販售資訊、品書)") -> 有攤位資料 (SNS、攤主資訊、本場販售資訊、品書) | B3: =IFERROR(__xludf.DUMMYFUNCTION("""COMPUTED_VALUE"""),621.0) -> 621 | C3: =IFERROR(__xludf.DUMMYFUNCTION("""COMPUTED_VALUE"""),"有攤位資料 (SNS、攤主資訊、本場販售資訊、品書)") -> 有攤位資料 (SNS、攤主資訊、本場販售資訊、品書) | D3: =IFERROR(__xludf.DUMMYFUNCTION("""COMPUTED_VALUE"""),621.0) -> 621 | E3: =IFERROR(__xludf.DUMMYFUNCTION("""COMPUTED_VALUE"""),"無SNS資料但有販售資訊") -> 無SNS資料但有販售資訊 | F3: =IFERROR(__xludf.DUMMYFUNCTION("""COMPUTED_VALUE"""),18.0) -> 18
C4: =IFERROR(__xludf.DUMMYFUNCTION("""COMPUTED_VALUE"""),"有FF47相關資訊攤位") -> 有FF47相關資訊攤位 | D4: =IFERROR(__xludf.DUMMYFUNCTION("""COMPUTED_VALUE"""),235.0) -> 235
C5: =IFERROR(__xludf.DUMMYFUNCTION("""COMPUTED_VALUE"""),"有預告攤位") -> 有預告攤位 | D5: =IFERROR(__xludf.DUMMYFUNCTION("""COMPUTED_VALUE"""),204.0) -> 204
C6: =IFERROR(__xludf.DUMMYFUNCTION("""COMPUTED_VALUE"""),"有品書攤位") -> 有品書攤位 | D6: =IFERROR(__xludf.DUMMYFUNCTION("""COMPUTED_VALUE"""),204.0) -> 204
A7: =IFERROR(__xludf.DUMMYFUNCTION("""COMPUTED_VALUE"""),"有FF47相關資訊攤位") -> 有FF47相關資訊攤位 | B7: =IFERROR(__xludf.DUMMYFUNCTION("""COMPUTED_VALUE"""),235.0) -> 235
A8: =IFERROR(__xludf.DUMMYFUNCTION("""COMPUTED_VALUE"""),"有預告攤位") -> 有預告攤位 | B8: =IFERROR(__xludf.DUMMYFUNCTION("""COMPUTED_VALUE"""),204.0) -> 204
A9: =IFERROR(__xludf.DUMMYFUNCTION("""COMPUTED_VALUE"""),"有品書攤位") -> 有品書攤位 | B9: =IFERROR(__xludf.DUMMYFUNCTION("""COMPUTED_VALUE"""),204.0) -> 204 | C9: =IFERROR(__xludf.DUMMYFUNCTION("""COMPUTED_VALUE"""),"有預告且有品書") -> 有預告且有品書 | D9: =IFERROR(__xludf.DUMMYFUNCTION("""COMPUTED_VALUE"""),"0") -> 0
D10: =IFERROR(__xludf.DUMMYFUNCTION("""COMPUTED_VALUE"""),73.0) -> 73
D11: =IFERROR(__xludf.DUMMYFUNCTION("""COMPUTED_VALUE"""),"有無縮圖") -> 有無縮圖 | E11: =IFERROR(__xludf.DUMMYFUNCTION("""COMPUTED_VALUE"""),"有縮圖") -> 有縮圖 | F11: =IFERROR(__xludf.DUMMYFUNCTION("""COMPUTED_VALUE"""),"無縮圖") -> 無縮圖
D12: =IFERROR(__xludf.DUMMYFUNCTION("""COMPUTED_VALUE"""),"有無縮圖") -> 有無縮圖 | E12: =IFERROR(__xludf.DUMMYFUNCTION("""COMPUTED_VALUE"""),262.0) -> 262 | F12: =IFERROR(__xludf.DUMMYFUNCTION("""COMPUTED_VALUE"""),1074.0) -> 1074
A13: =IFERROR(__xludf.DUMMYFUNCTION("""COMPUTED_VALUE"""),"時間") -> 時間 | B13: =IFERROR(__xludf.DUMMYFUNCTION("""COMPUTED_VALUE"""),"無資料攤位") -> 無資料攤位 | C13: =IFERROR(__xludf.DUMMYFUNCTION("""COMPUTED_VALUE"""),"有社群連結攤位") -> 有社群連結攤位 | D13: =IFERROR(__xludf.DUMMYFUNCTION("""COMPUTED_VALUE"""),"有FF47相關資訊攤位") -> 有FF47相關資訊攤位 | E13: =IFERROR(__xludf.DUMMYFUNCTION("""COMPUTED_VALUE"""),"有預告攤位") -> 有預告攤位 | F13: =IFERROR(__xludf.DUMMYFUNCTION("""COMPUTED_VALUE"""),"有品書攤位") -> 有品書攤位
A14: =IFERROR(__xludf.DUMMYFUNCTION("""COMPUTED_VALUE"""),46172.0) -> 46172 | B14: =IFERROR(__xludf.DUMMYFUNCTION("""COMPUTED_VALUE"""),384.0) -> 384 | C14: =IFERROR(__xludf.DUMMYFUNCTION("""COMPUTED_VALUE"""),926.0) -> 926 | D14: =IFERROR(__xludf.DUMMYFUNCTION("""COMPUTED_VALUE"""),"#N/A") -> #N/A | E14: =IFERROR(__xludf.DUMMYFUNCTION("""COMPUTED_VALUE"""),"#N/A") -> #N/A | F14: =IFERROR(__xludf.DUMMYFUNCTION("""COMPUTED_VALUE"""),"#N/A") -> #N/A
A15: =IFERROR(__xludf.DUMMYFUNCTION("""COMPUTED_VALUE"""),46173.0) -> 46173 | B15: =IFERROR(__xludf.DUMMYFUNCTION("""COMPUTED_VALUE"""),348.0) -> 348 | C15: =IFERROR(__xludf.DUMMYFUNCTION("""COMPUTED_VALUE"""),958.0) -> 958 | D15: =IFERROR(__xludf.DUMMYFUNCTION("""COMPUTED_VALUE"""),4.0) -> 4 | E15: =IFERROR(__xludf.DUMMYFUNCTION("""COMPUTED_VALUE"""),"#N/A") -> #N/A | F15: =IFERROR(__xludf.DUMMYFUNCTION("""COMPUTED_VALUE"""),"#N/A") -> #N/A
A16: =IFERROR(__xludf.DUMMYFUNCTION("""COMPUTED_VALUE"""),46174.0) -> 46174 | B16: =IFERROR(__xludf.DUMMYFUNCTION("""COMPUTED_VALUE"""),267.0) -> 267 | C16: =IFERROR(__xludf.DUMMYFUNCTION("""COMPUTED_VALUE"""),980.0) -> 980 | D16: =IFERROR(__xludf.DUMMYFUNCTION("""COMPUTED_VALUE"""),4.0) -> 4 | E16: =IFERROR(__xludf.DUMMYFUNCTION("""COMPUTED_VALUE"""),61.0) -> 61 | F16: =IFERROR(__xludf.DUMMYFUNCTION("""COMPUTED_VALUE"""),"#N/A") -> #N/A
A17: =IFERROR(__xludf.DUMMYFUNCTION("""COMPUTED_VALUE"""),46175.0) -> 46175 | B17: =IFERROR(__xludf.DUMMYFUNCTION("""COMPUTED_VALUE"""),243.0) -> 243 | C17: =IFERROR(__xludf.DUMMYFUNCTION("""COMPUTED_VALUE"""),968.0) -> 968 | D17: =IFERROR(__xludf.DUMMYFUNCTION("""COMPUTED_VALUE"""),5.0) -> 5 | E17: =IFERROR(__xludf.DUMMYFUNCTION("""COMPUTED_VALUE"""),99.0) -> 99 | F17: =IFERROR(__xludf.DUMMYFUNCTION("""COMPUTED_VALUE"""),"#N/A") -> #N/A
A18: =IFERROR(__xludf.DUMMYFUNCTION("""COMPUTED_VALUE"""),46176.0) -> 46176 | B18: =IFERROR(__xludf.DUMMYFUNCTION("""COMPUTED_VALUE"""),219.0) -> 219 | C18: =IFERROR(__xludf.DUMMYFUNCTION("""COMPUTED_VALUE"""),987.0) -> 987 | D18: =IFERROR(__xludf.DUMMYFUNCTION("""COMPUTED_VALUE"""),6.0) -> 6 | E18: =IFERROR(__xludf.DUMMYFUNCTION("""COMPUTED_VALUE"""),102.0) -> 102 | F18: =IFERROR(__xludf.DUMMYFUNCTION("""COMPUTED_VALUE"""),"#N/A") -> #N/A
A19: =IFERROR(__xludf.DUMMYFUNCTION("""COMPUTED_VALUE"""),46177.0) -> 46177 | B19: =IFERROR(__xludf.DUMMYFUNCTION("""COMPUTED_VALUE"""),195.0) -> 195 | C19: =IFERROR(__xludf.DUMMYFUNCTION("""COMPUTED_VALUE"""),1011.0) -> 1011 | D19: =IFERROR(__xludf.DUMMYFUNCTION("""COMPUTED_VALUE"""),6.0) -> 6 | E19: =IFERROR(__xludf.DUMMYFUNCTION("""COMPUTED_VALUE"""),102.0) -> 102 | F19: =IFERROR(__xludf.DUMMYFUNCTION("""COMPUTED_VALUE"""),"#N/A") -> #N/A
A20: =IFERROR(__xludf.DUMMYFUNCTION("""COMPUTED_VALUE"""),46178.0) -> 46178 | B20: =IFERROR(__xludf.DUMMYFUNCTION("""COMPUTED_VALUE"""),183.0) -> 183 | C20: =IFERROR(__xludf.DUMMYFUNCTION("""COMPUTED_VALUE"""),1020.0) -> 1020 | D20: =IFERROR(__xludf.DUMMYFUNCTION("""COMPUTED_VALUE"""),6.0) -> 6 | E20: =IFERROR(__xludf.DUMMYFUNCTION("""COMPUTED_VALUE"""),102.0) -> 102 | F20: =IFERROR(__xludf.DUMMYFUNCTION("""COMPUTED_VALUE"""),1.0) -> 1
A21: =IFERROR(__xludf.DUMMYFUNCTION("""COMPUTED_VALUE"""),46179.0) -> 46179 | B21: =IFERROR(__xludf.DUMMYFUNCTION("""COMPUTED_VALUE"""),164.0) -> 164 | C21: =IFERROR(__xludf.DUMMYFUNCTION("""COMPUTED_VALUE"""),1035.0) -> 1035 | D21: =IFERROR(__xludf.DUMMYFUNCTION("""COMPUTED_VALUE"""),6.0) -> 6 | E21: =IFERROR(__xludf.DUMMYFUNCTION("""COMPUTED_VALUE"""),106.0) -> 106 | F21: =IFERROR(__xludf.DUMMYFUNCTION("""COMPUTED_VALUE"""),1.0) -> 1
A22: =IFERROR(__xludf.DUMMYFUNCTION("""COMPUTED_VALUE"""),46180.0) -> 46180 | B22: =IFERROR(__xludf.DUMMYFUNCTION("""COMPUTED_VALUE"""),164.0) -> 164 | C22: =IFERROR(__xludf.DUMMYFUNCTION("""COMPUTED_VALUE"""),1034.0) -> 1034 | D22: =IFERROR(__xludf.DUMMYFUNCTION("""COMPUTED_VALUE"""),7.0) -> 7 | E22: =IFERROR(__xludf.DUMMYFUNCTION("""COMPUTED_VALUE"""),106.0) -> 106 | F22: =IFERROR(__xludf.DUMMYFUNCTION("""COMPUTED_VALUE"""),1.0) -> 1
A23: =IFERROR(__xludf.DUMMYFUNCTION("""COMPUTED_VALUE"""),46181.0) -> 46181 | B23: =IFERROR(__xludf.DUMMYFUNCTION("""COMPUTED_VALUE"""),146.0) -> 146 | C23: =IFERROR(__xludf.DUMMYFUNCTION("""COMPUTED_VALUE"""),1049.0) -> 1049 | D23: =IFERROR(__xludf.DUMMYFUNCTION("""COMPUTED_VALUE"""),9.0) -> 9 | E23: =IFERROR(__xludf.DUMMYFUNCTION("""COMPUTED_VALUE"""),106.0) -> 106 | F23: =IFERROR(__xludf.DUMMYFUNCTION("""COMPUTED_VALUE"""),1.0) -> 1
A24: =IFERROR(__xludf.DUMMYFUNCTION("""COMPUTED_VALUE"""),46182.0) -> 46182 | B24: =IFERROR(__xludf.DUMMYFUNCTION("""COMPUTED_VALUE"""),130.0) -> 130 | C24: =IFERROR(__xludf.DUMMYFUNCTION("""COMPUTED_VALUE"""),1057.0) -> 1057 | D24: =IFERROR(__xludf.DUMMYFUNCTION("""COMPUTED_VALUE"""),9.0) -> 9 | E24: =IFERROR(__xludf.DUMMYFUNCTION("""COMPUTED_VALUE"""),114.0) -> 114 | F24: =IFERROR(__xludf.DUMMYFUNCTION("""COMPUTED_VALUE"""),1.0) -> 1
A25: =IFERROR(__xludf.DUMMYFUNCTION("""COMPUTED_VALUE"""),46183.0) -> 46183 | B25: =IFERROR(__xludf.DUMMYFUNCTION("""COMPUTED_VALUE"""),117.0) -> 117 | C25: =IFERROR(__xludf.DUMMYFUNCTION("""COMPUTED_VALUE"""),1069.0) -> 1069 | D25: =IFERROR(__xludf.DUMMYFUNCTION("""COMPUTED_VALUE"""),9.0) -> 9 | E25: =IFERROR(__xludf.DUMMYFUNCTION("""COMPUTED_VALUE"""),114.0) -> 114 | F25: =IFERROR(__xludf.DUMMYFUNCTION("""COMPUTED_VALUE"""),1.0) -> 1
A26: =IFERROR(__xludf.DUMMYFUNCTION("""COMPUTED_VALUE"""),46185.0) -> 46185 | B26: =IFERROR(__xludf.DUMMYFUNCTION("""COMPUTED_VALUE"""),117.0) -> 117 | C26: =IFERROR(__xludf.DUMMYFUNCTION("""COMPUTED_VALUE"""),1069.0) -> 1069 | D26: =IFERROR(__xludf.DUMMYFUNCTION("""COMPUTED_VALUE"""),9.0) -> 9 | E26: =IFERROR(__xludf.DUMMYFUNCTION("""COMPUTED_VALUE"""),114.0) -> 114 | F26: =IFERROR(__xludf.DUMMYFUNCTION("""COMPUTED_VALUE"""),1.0) -> 1
A27: =IFERROR(__xludf.DUMMYFUNCTION("""COMPUTED_VALUE"""),46186.0) -> 46186 | B27: =IFERROR(__xludf.DUMMYFUNCTION("""COMPUTED_VALUE"""),117.0) -> 117 | C27: =IFERROR(__xludf.DUMMYFUNCTION("""COMPUTED_VALUE"""),1060.0) -> 1060 | D27: =IFERROR(__xludf.DUMMYFUNCTION("""COMPUTED_VALUE"""),9.0) -> 9 | E27: =IFERROR(__xludf.DUMMYFUNCTION("""COMPUTED_VALUE"""),123.0) -> 123 | F27: =IFERROR(__xludf.DUMMYFUNCTION("""COMPUTED_VALUE"""),1.0) -> 1
A28: =IFERROR(__xludf.DUMMYFUNCTION("""COMPUTED_VALUE"""),46187.0) -> 46187 | B28: =IFERROR(__xludf.DUMMYFUNCTION("""COMPUTED_VALUE"""),117.0) -> 117 | C28: =IFERROR(__xludf.DUMMYFUNCTION("""COMPUTED_VALUE"""),1067.0) -> 1067 | D28: =IFERROR(__xludf.DUMMYFUNCTION("""COMPUTED_VALUE"""),10.0) -> 10 | E28: =IFERROR(__xludf.DUMMYFUNCTION("""COMPUTED_VALUE"""),123.0) -> 123 | F28: =IFERROR(__xludf.DUMMYFUNCTION("""COMPUTED_VALUE"""),1.0) -> 1
A29: =IFERROR(__xludf.DUMMYFUNCTION("""COMPUTED_VALUE"""),46188.0) -> 46188 | B29: =IFERROR(__xludf.DUMMYFUNCTION("""COMPUTED_VALUE"""),117.0) -> 117 | C29: =IFERROR(__xludf.DUMMYFUNCTION("""COMPUTED_VALUE"""),1065.0) -> 1065 | D29: =IFERROR(__xludf.DUMMYFUNCTION("""COMPUTED_VALUE"""),12.0) -> 12 | E29: =IFERROR(__xludf.DUMMYFUNCTION("""COMPUTED_VALUE"""),123.0) -> 123 | F29: =IFERROR(__xludf.DUMMYFUNCTION("""COMPUTED_VALUE"""),1.0) -> 1
A30: =IFERROR(__xludf.DUMMYFUNCTION("""COMPUTED_VALUE"""),46189.0) -> 46189 | B30: =IFERROR(__xludf.DUMMYFUNCTION("""COMPUTED_VALUE"""),117.0) -> 117 | C30: =IFERROR(__xludf.DUMMYFUNCTION("""COMPUTED_VALUE"""),1065.0) -> 1065 | D30: =IFERROR(__xludf.DUMMYFUNCTION("""COMPUTED_VALUE"""),12.0) -> 12 | E30: =IFERROR(__xludf.DUMMYFUNCTION("""COMPUTED_VALUE"""),123.0) -> 123 | F30: =IFERROR(__xludf.DUMMYFUNCTION("""COMPUTED_VALUE"""),1.0) -> 1
A31: =IFERROR(__xludf.DUMMYFUNCTION("""COMPUTED_VALUE"""),46190.0) -> 46190 | B31: =IFERROR(__xludf.DUMMYFUNCTION("""COMPUTED_VALUE"""),117.0) -> 117 | C31: =IFERROR(__xludf.DUMMYFUNCTION("""COMPUTED_VALUE"""),1065.0) -> 1065 | D31: =IFERROR(__xludf.DUMMYFUNCTION("""COMPUTED_VALUE"""),12.0) -> 12 | E31: =IFERROR(__xludf.DUMMYFUNCTION("""COMPUTED_VALUE"""),123.0) -> 123 | F31: =IFERROR(__xludf.DUMMYFUNCTION("""COMPUTED_VALUE"""),1.0) -> 1
A32: =IFERROR(__xludf.DUMMYFUNCTION("""COMPUTED_VALUE"""),46191.0) -> 46191 | B32: =IFERROR(__xludf.DUMMYFUNCTION("""COMPUTED_VALUE"""),117.0) -> 117 | C32: =IFERROR(__xludf.DUMMYFUNCTION("""COMPUTED_VALUE"""),1065.0) -> 1065 | D32: =IFERROR(__xludf.DUMMYFUNCTION("""COMPUTED_VALUE"""),12.0) -> 12 | E32: =IFERROR(__xludf.DUMMYFUNCTION("""COMPUTED_VALUE"""),123.0) -> 123 | F32: =IFERROR(__xludf.DUMMYFUNCTION("""COMPUTED_VALUE"""),1.0) -> 1
A33: =IFERROR(__xludf.DUMMYFUNCTION("""COMPUTED_VALUE"""),46192.0) -> 46192 | B33: =IFERROR(__xludf.DUMMYFUNCTION("""COMPUTED_VALUE"""),117.0) -> 117 | C33: =IFERROR(__xludf.DUMMYFUNCTION("""COMPUTED_VALUE"""),1065.0) -> 1065 | D33: =IFERROR(__xludf.DUMMYFUNCTION("""COMPUTED_VALUE"""),12.0) -> 12 | E33: =IFERROR(__xludf.DUMMYFUNCTION("""COMPUTED_VALUE"""),123.0) -> 123 | F33: =IFERROR(__xludf.DUMMYFUNCTION("""COMPUTED_VALUE"""),1.0) -> 1
A34: =IFERROR(__xludf.DUMMYFUNCTION("""COMPUTED_VALUE"""),46193.0) -> 46193 | B34: =IFERROR(__xludf.DUMMYFUNCTION("""COMPUTED_VALUE"""),117.0) -> 117 | C34: =IFERROR(__xludf.DUMMYFUNCTION("""COMPUTED_VALUE"""),1065.0) -> 1065 | D34: =IFERROR(__xludf.DUMMYFUNCTION("""COMPUTED_VALUE"""),12.0) -> 12 | E34: =IFERROR(__xludf.DUMMYFUNCTION("""COMPUTED_VALUE"""),123.0) -> 123 | F34: =IFERROR(__xludf.DUMMYFUNCTION("""COMPUTED_VALUE"""),1.0) -> 1
A35: =IFERROR(__xludf.DUMMYFUNCTION("""COMPUTED_VALUE"""),46194.0) -> 46194 | B35: =IFERROR(__xludf.DUMMYFUNCTION("""COMPUTED_VALUE"""),116.0) -> 116 | C35: =IFERROR(__xludf.DUMMYFUNCTION("""COMPUTED_VALUE"""),1065.0) -> 1065 | D35: =IFERROR(__xludf.DUMMYFUNCTION("""COMPUTED_VALUE"""),13.0) -> 13 | E35: =IFERROR(__xludf.DUMMYFUNCTION("""COMPUTED_VALUE"""),123.0) -> 123 | F35: =IFERROR(__xludf.DUMMYFUNCTION("""COMPUTED_VALUE"""),1.0) -> 1
A36: =IFERROR(__xludf.DUMMYFUNCTION("""COMPUTED_VALUE"""),46195.0) -> 46195 | B36: =IFERROR(__xludf.DUMMYFUNCTION("""COMPUTED_VALUE"""),116.0) -> 116 | C36: =IFERROR(__xludf.DUMMYFUNCTION("""COMPUTED_VALUE"""),1065.0) -> 1065 | D36: =IFERROR(__xludf.DUMMYFUNCTION("""COMPUTED_VALUE"""),13.0) -> 13 | E36: =IFERROR(__xludf.DUMMYFUNCTION("""COMPUTED_VALUE"""),123.0) -> 123 | F36: =IFERROR(__xludf.DUMMYFUNCTION("""COMPUTED_VALUE"""),1.0) -> 1
A37: =IFERROR(__xludf.DUMMYFUNCTION("""COMPUTED_VALUE"""),46196.0) -> 46196 | B37: =IFERROR(__xludf.DUMMYFUNCTION("""COMPUTED_VALUE"""),116.0) -> 116 | C37: =IFERROR(__xludf.DUMMYFUNCTION("""COMPUTED_VALUE"""),1065.0) -> 1065 | D37: =IFERROR(__xludf.DUMMYFUNCTION("""COMPUTED_VALUE"""),13.0) -> 13 | E37: =IFERROR(__xludf.DUMMYFUNCTION("""COMPUTED_VALUE"""),123.0) -> 123 | F37: =IFERROR(__xludf.DUMMYFUNCTION("""COMPUTED_VALUE"""),1.0) -> 1
A38: =IFERROR(__xludf.DUMMYFUNCTION("""COMPUTED_VALUE"""),46197.0) -> 46197 | B38: =IFERROR(__xludf.DUMMYFUNCTION("""COMPUTED_VALUE"""),116.0) -> 116 | C38: =IFERROR(__xludf.DUMMYFUNCTION("""COMPUTED_VALUE"""),1065.0) -> 1065 | D38: =IFERROR(__xludf.DUMMYFUNCTION("""COMPUTED_VALUE"""),13.0) -> 13 | E38: =IFERROR(__xludf.DUMMYFUNCTION("""COMPUTED_VALUE"""),123.0) -> 123 | F38: =IFERROR(__xludf.DUMMYFUNCTION("""COMPUTED_VALUE"""),1.0) -> 1
A39: =IFERROR(__xludf.DUMMYFUNCTION("""COMPUTED_VALUE"""),46198.0) -> 46198 | B39: =IFERROR(__xludf.DUMMYFUNCTION("""COMPUTED_VALUE"""),116.0) -> 116 | C39: =IFERROR(__xludf.DUMMYFUNCTION("""COMPUTED_VALUE"""),1065.0) -> 1065 | D39: =IFERROR(__xludf.DUMMYFUNCTION("""COMPUTED_VALUE"""),13.0) -> 13 | E39: =IFERROR(__xludf.DUMMYFUNCTION("""COMPUTED_VALUE"""),123.0) -> 123 | F39: =IFERROR(__xludf.DUMMYFUNCTION("""COMPUTED_VALUE"""),1.0) -> 1
A40: =IFERROR(__xludf.DUMMYFUNCTION("""COMPUTED_VALUE"""),46199.0) -> 46199 | B40: =IFERROR(__xludf.DUMMYFUNCTION("""COMPUTED_VALUE"""),116.0) -> 116 | C40: =IFERROR(__xludf.DUMMYFUNCTION("""COMPUTED_VALUE"""),1064.0) -> 1064 | D40: =IFERROR(__xludf.DUMMYFUNCTION("""COMPUTED_VALUE"""),14.0) -> 14 | E40: =IFERROR(__xludf.DUMMYFUNCTION("""COMPUTED_VALUE"""),122.0) -> 122 | F40: =IFERROR(__xludf.DUMMYFUNCTION("""COMPUTED_VALUE"""),1.0) -> 1
A41: =IFERROR(__xludf.DUMMYFUNCTION("""COMPUTED_VALUE"""),46200.0) -> 46200 | B41: =IFERROR(__xludf.DUMMYFUNCTION("""COMPUTED_VALUE"""),116.0) -> 116 | C41: =IFERROR(__xludf.DUMMYFUNCTION("""COMPUTED_VALUE"""),1063.0) -> 1063 | D41: =IFERROR(__xludf.DUMMYFUNCTION("""COMPUTED_VALUE"""),16.0) -> 16 | E41: =IFERROR(__xludf.DUMMYFUNCTION("""COMPUTED_VALUE"""),122.0) -> 122 | F41: =IFERROR(__xludf.DUMMYFUNCTION("""COMPUTED_VALUE"""),1.0) -> 1
A42: =IFERROR(__xludf.DUMMYFUNCTION("""COMPUTED_VALUE"""),46202.0) -> 46202 | B42: =IFERROR(__xludf.DUMMYFUNCTION("""COMPUTED_VALUE"""),107.0) -> 107 | C42: =IFERROR(__xludf.DUMMYFUNCTION("""COMPUTED_VALUE"""),1023.0) -> 1023 | D42: =IFERROR(__xludf.DUMMYFUNCTION("""COMPUTED_VALUE"""),14.0) -> 14 | E42: =IFERROR(__xludf.DUMMYFUNCTION("""COMPUTED_VALUE"""),173.0) -> 173 | F42: =IFERROR(__xludf.DUMMYFUNCTION("""COMPUTED_VALUE"""),1.0) -> 1
A43: =IFERROR(__xludf.DUMMYFUNCTION("""COMPUTED_VALUE"""),46203.0) -> 46203 | B43: =IFERROR(__xludf.DUMMYFUNCTION("""COMPUTED_VALUE"""),107.0) -> 107 | C43: =IFERROR(__xludf.DUMMYFUNCTION("""COMPUTED_VALUE"""),1022.0) -> 1022 | D43: =IFERROR(__xludf.DUMMYFUNCTION("""COMPUTED_VALUE"""),14.0) -> 14 | E43: =IFERROR(__xludf.DUMMYFUNCTION("""COMPUTED_VALUE"""),173.0) -> 173 | F43: =IFERROR(__xludf.DUMMYFUNCTION("""COMPUTED_VALUE"""),2.0) -> 2
A44: =IFERROR(__xludf.DUMMYFUNCTION("""COMPUTED_VALUE"""),46204.0) -> 46204 | B44: =IFERROR(__xludf.DUMMYFUNCTION("""COMPUTED_VALUE"""),107.0) -> 107 | C44: =IFERROR(__xludf.DUMMYFUNCTION("""COMPUTED_VALUE"""),1022.0) -> 1022 | D44: =IFERROR(__xludf.DUMMYFUNCTION("""COMPUTED_VALUE"""),14.0) -> 14 | E44: =IFERROR(__xludf.DUMMYFUNCTION("""COMPUTED_VALUE"""),173.0) -> 173 | F44: =IFERROR(__xludf.DUMMYFUNCTION("""COMPUTED_VALUE"""),2.0) -> 2
A45: =IFERROR(__xludf.DUMMYFUNCTION("""COMPUTED_VALUE"""),46205.0) -> 46205 | B45: =IFERROR(__xludf.DUMMYFUNCTION("""COMPUTED_VALUE"""),106.0) -> 106 | C45: =IFERROR(__xludf.DUMMYFUNCTION("""COMPUTED_VALUE"""),1021.0) -> 1021 | D45: =IFERROR(__xludf.DUMMYFUNCTION("""COMPUTED_VALUE"""),15.0) -> 15 | E45: =IFERROR(__xludf.DUMMYFUNCTION("""COMPUTED_VALUE"""),173.0) -> 173 | F45: =IFERROR(__xludf.DUMMYFUNCTION("""COMPUTED_VALUE"""),3.0) -> 3
A46: =IFERROR(__xludf.DUMMYFUNCTION("""COMPUTED_VALUE"""),46206.0) -> 46206 | B46: =IFERROR(__xludf.DUMMYFUNCTION("""COMPUTED_VALUE"""),106.0) -> 106 | C46: =IFERROR(__xludf.DUMMYFUNCTION("""COMPUTED_VALUE"""),1021.0) -> 1021 | D46: =IFERROR(__xludf.DUMMYFUNCTION("""COMPUTED_VALUE"""),15.0) -> 15 | E46: =IFERROR(__xludf.DUMMYFUNCTION("""COMPUTED_VALUE"""),173.0) -> 173 | F46: =IFERROR(__xludf.DUMMYFUNCTION("""COMPUTED_VALUE"""),3.0) -> 3
A47: =IFERROR(__xludf.DUMMYFUNCTION("""COMPUTED_VALUE"""),46207.0) -> 46207 | B47: =IFERROR(__xludf.DUMMYFUNCTION("""COMPUTED_VALUE"""),106.0) -> 106 | C47: =IFERROR(__xludf.DUMMYFUNCTION("""COMPUTED_VALUE"""),1021.0) -> 1021 | D47: =IFERROR(__xludf.DUMMYFUNCTION("""COMPUTED_VALUE"""),15.0) -> 15 | E47: =IFERROR(__xludf.DUMMYFUNCTION("""COMPUTED_VALUE"""),173.0) -> 173 | F47: =IFERROR(__xludf.DUMMYFUNCTION("""COMPUTED_VALUE"""),3.0) -> 3
A48: =IFERROR(__xludf.DUMMYFUNCTION("""COMPUTED_VALUE"""),46208.0) -> 46208 | B48: =IFERROR(__xludf.DUMMYFUNCTION("""COMPUTED_VALUE"""),106.0) -> 106 | C48: =IFERROR(__xludf.DUMMYFUNCTION("""COMPUTED_VALUE"""),1021.0) -> 1021 | D48: =IFERROR(__xludf.DUMMYFUNCTION("""COMPUTED_VALUE"""),15.0) -> 15 | E48: =IFERROR(__xludf.DUMMYFUNCTION("""COMPUTED_VALUE"""),173.0) -> 173 | F48: =IFERROR(__xludf.DUMMYFUNCTION("""COMPUTED_VALUE"""),3.0) -> 3
A49: =IFERROR(__xludf.DUMMYFUNCTION("""COMPUTED_VALUE"""),46209.0) -> 46209 | B49: =IFERROR(__xludf.DUMMYFUNCTION("""COMPUTED_VALUE"""),106.0) -> 106 | C49: =IFERROR(__xludf.DUMMYFUNCTION("""COMPUTED_VALUE"""),1021.0) -> 1021 | D49: =IFERROR(__xludf.DUMMYFUNCTION("""COMPUTED_VALUE"""),15.0) -> 15 | E49: =IFERROR(__xludf.DUMMYFUNCTION("""COMPUTED_VALUE"""),173.0) -> 173 | F49: =IFERROR(__xludf.DUMMYFUNCTION("""COMPUTED_VALUE"""),3.0) -> 3
A50: =IFERROR(__xludf.DUMMYFUNCTION("""COMPUTED_VALUE"""),46210.0) -> 46210 | B50: =IFERROR(__xludf.DUMMYFUNCTION("""COMPUTED_VALUE"""),105.0) -> 105 | C50: =IFERROR(__xludf.DUMMYFUNCTION("""COMPUTED_VALUE"""),1011.0) -> 1011 | D50: =IFERROR(__xludf.DUMMYFUNCTION("""COMPUTED_VALUE"""),17.0) -> 17 | E50: =IFERROR(__xludf.DUMMYFUNCTION("""COMPUTED_VALUE"""),181.0) -> 181 | F50: =IFERROR(__xludf.DUMMYFUNCTION("""COMPUTED_VALUE"""),3.0) -> 3
A51: =IFERROR(__xludf.DUMMYFUNCTION("""COMPUTED_VALUE"""),46211.0) -> 46211 | B51: =IFERROR(__xludf.DUMMYFUNCTION("""COMPUTED_VALUE"""),105.0) -> 105 | C51: =IFERROR(__xludf.DUMMYFUNCTION("""COMPUTED_VALUE"""),1010.0) -> 1010 | D51: =IFERROR(__xludf.DUMMYFUNCTION("""COMPUTED_VALUE"""),17.0) -> 17 | E51: =IFERROR(__xludf.DUMMYFUNCTION("""COMPUTED_VALUE"""),181.0) -> 181 | F51: =IFERROR(__xludf.DUMMYFUNCTION("""COMPUTED_VALUE"""),4.0) -> 4
A52: =IFERROR(__xludf.DUMMYFUNCTION("""COMPUTED_VALUE"""),46212.0) -> 46212 | B52: =IFERROR(__xludf.DUMMYFUNCTION("""COMPUTED_VALUE"""),94.0) -> 94 | C52: =IFERROR(__xludf.DUMMYFUNCTION("""COMPUTED_VALUE"""),856.0) -> 856 | D52: =IFERROR(__xludf.DUMMYFUNCTION("""COMPUTED_VALUE"""),192.0) -> 192 | E52: =IFERROR(__xludf.DUMMYFUNCTION("""COMPUTED_VALUE"""),182.0) -> 182 | F52: =IFERROR(__xludf.DUMMYFUNCTION("""COMPUTED_VALUE"""),4.0) -> 4
A53: =IFERROR(__xludf.DUMMYFUNCTION("""COMPUTED_VALUE"""),46213.0) -> 46213 | B53: =IFERROR(__xludf.DUMMYFUNCTION("""COMPUTED_VALUE"""),94.0) -> 94 | C53: =IFERROR(__xludf.DUMMYFUNCTION("""COMPUTED_VALUE"""),770.0) -> 770 | D53: =IFERROR(__xludf.DUMMYFUNCTION("""COMPUTED_VALUE"""),282.0) -> 282 | E53: =IFERROR(__xludf.DUMMYFUNCTION("""COMPUTED_VALUE"""),181.0) -> 181 | F53: =IFERROR(__xludf.DUMMYFUNCTION("""COMPUTED_VALUE"""),4.0) -> 4
A54: =IFERROR(__xludf.DUMMYFUNCTION("""COMPUTED_VALUE"""),46214.0) -> 46214 | B54: =IFERROR(__xludf.DUMMYFUNCTION("""COMPUTED_VALUE"""),86.0) -> 86 | C54: =IFERROR(__xludf.DUMMYFUNCTION("""COMPUTED_VALUE"""),768.0) -> 768 | D54: =IFERROR(__xludf.DUMMYFUNCTION("""COMPUTED_VALUE"""),282.0) -> 282 | E54: =IFERROR(__xludf.DUMMYFUNCTION("""COMPUTED_VALUE"""),184.0) -> 184 | F54: =IFERROR(__xludf.DUMMYFUNCTION("""COMPUTED_VALUE"""),9.0) -> 9
A55: =IFERROR(__xludf.DUMMYFUNCTION("""COMPUTED_VALUE"""),46215.0) -> 46215 | B55: =IFERROR(__xludf.DUMMYFUNCTION("""COMPUTED_VALUE"""),86.0) -> 86 | C55: =IFERROR(__xludf.DUMMYFUNCTION("""COMPUTED_VALUE"""),767.0) -> 767 | D55: =IFERROR(__xludf.DUMMYFUNCTION("""COMPUTED_VALUE"""),282.0) -> 282 | E55: =IFERROR(__xludf.DUMMYFUNCTION("""COMPUTED_VALUE"""),185.0) -> 185 | F55: =IFERROR(__xludf.DUMMYFUNCTION("""COMPUTED_VALUE"""),9.0) -> 9
A56: =IFERROR(__xludf.DUMMYFUNCTION("""COMPUTED_VALUE"""),46216.0) -> 46216 | B56: =IFERROR(__xludf.DUMMYFUNCTION("""COMPUTED_VALUE"""),86.0) -> 86 | C56: =IFERROR(__xludf.DUMMYFUNCTION("""COMPUTED_VALUE"""),767.0) -> 767 | D56: =IFERROR(__xludf.DUMMYFUNCTION("""COMPUTED_VALUE"""),282.0) -> 282 | E56: =IFERROR(__xludf.DUMMYFUNCTION("""COMPUTED_VALUE"""),185.0) -> 185 | F56: =IFERROR(__xludf.DUMMYFUNCTION("""COMPUTED_VALUE"""),9.0) -> 9
A57: =IFERROR(__xludf.DUMMYFUNCTION("""COMPUTED_VALUE"""),46217.0) -> 46217 | B57: =IFERROR(__xludf.DUMMYFUNCTION("""COMPUTED_VALUE"""),86.0) -> 86 | C57: =IFERROR(__xludf.DUMMYFUNCTION("""COMPUTED_VALUE"""),767.0) -> 767 | D57: =IFERROR(__xludf.DUMMYFUNCTION("""COMPUTED_VALUE"""),282.0) -> 282 | E57: =IFERROR(__xludf.DUMMYFUNCTION("""COMPUTED_VALUE"""),185.0) -> 185 | F57: =IFERROR(__xludf.DUMMYFUNCTION("""COMPUTED_VALUE"""),9.0) -> 9
A58: =IFERROR(__xludf.DUMMYFUNCTION("""COMPUTED_VALUE"""),46218.0) -> 46218 | B58: =IFERROR(__xludf.DUMMYFUNCTION("""COMPUTED_VALUE"""),85.0) -> 85 | C58: =IFERROR(__xludf.DUMMYFUNCTION("""COMPUTED_VALUE"""),759.0) -> 759 | D58: =IFERROR(__xludf.DUMMYFUNCTION("""COMPUTED_VALUE"""),279.0) -> 279 | E58: =IFERROR(__xludf.DUMMYFUNCTION("""COMPUTED_VALUE"""),194.0) -> 194 | F58: =IFERROR(__xludf.DUMMYFUNCTION("""COMPUTED_VALUE"""),12.0) -> 12
A59: =IFERROR(__xludf.DUMMYFUNCTION("""COMPUTED_VALUE"""),46219.0) -> 46219 | B59: =IFERROR(__xludf.DUMMYFUNCTION("""COMPUTED_VALUE"""),85.0) -> 85 | C59: =IFERROR(__xludf.DUMMYFUNCTION("""COMPUTED_VALUE"""),758.0) -> 758 | D59: =IFERROR(__xludf.DUMMYFUNCTION("""COMPUTED_VALUE"""),276.0) -> 276 | E59: =IFERROR(__xludf.DUMMYFUNCTION("""COMPUTED_VALUE"""),195.0) -> 195 | F59: =IFERROR(__xludf.DUMMYFUNCTION("""COMPUTED_VALUE"""),15.0) -> 15
A60: =IFERROR(__xludf.DUMMYFUNCTION("""COMPUTED_VALUE"""),46220.0) -> 46220 | B60: =IFERROR(__xludf.DUMMYFUNCTION("""COMPUTED_VALUE"""),85.0) -> 85 | C60: =IFERROR(__xludf.DUMMYFUNCTION("""COMPUTED_VALUE"""),757.0) -> 757 | D60: =IFERROR(__xludf.DUMMYFUNCTION("""COMPUTED_VALUE"""),277.0) -> 277 | E60: =IFERROR(__xludf.DUMMYFUNCTION("""COMPUTED_VALUE"""),195.0) -> 195 | F60: =IFERROR(__xludf.DUMMYFUNCTION("""COMPUTED_VALUE"""),15.0) -> 15
A61: =IFERROR(__xludf.DUMMYFUNCTION("""COMPUTED_VALUE"""),46221.0) -> 46221 | B61: =IFERROR(__xludf.DUMMYFUNCTION("""COMPUTED_VALUE"""),85.0) -> 85 | C61: =IFERROR(__xludf.DUMMYFUNCTION("""COMPUTED_VALUE"""),757.0) -> 757 | D61: =IFERROR(__xludf.DUMMYFUNCTION("""COMPUTED_VALUE"""),277.0) -> 277 | E61: =IFERROR(__xludf.DUMMYFUNCTION("""COMPUTED_VALUE"""),195.0) -> 195 | F61: =IFERROR(__xludf.DUMMYFUNCTION("""COMPUTED_VALUE"""),15.0) -> 15
A62: =IFERROR(__xludf.DUMMYFUNCTION("""COMPUTED_VALUE"""),46222.0) -> 46222 | B62: =IFERROR(__xludf.DUMMYFUNCTION("""COMPUTED_VALUE"""),85.0) -> 85 | C62: =IFERROR(__xludf.DUMMYFUNCTION("""COMPUTED_VALUE"""),757.0) -> 757 | D62: =IFERROR(__xludf.DUMMYFUNCTION("""COMPUTED_VALUE"""),277.0) -> 277 | E62: =IFERROR(__xludf.DUMMYFUNCTION("""COMPUTED_VALUE"""),195.0) -> 195 | F62: =IFERROR(__xludf.DUMMYFUNCTION("""COMPUTED_VALUE"""),15.0) -> 15
A63: =IFERROR(__xludf.DUMMYFUNCTION("""COMPUTED_VALUE"""),46223.0) -> 46223 | B63: =IFERROR(__xludf.DUMMYFUNCTION("""COMPUTED_VALUE"""),85.0) -> 85 | C63: =IFERROR(__xludf.DUMMYFUNCTION("""COMPUTED_VALUE"""),757.0) -> 757 | D63: =IFERROR(__xludf.DUMMYFUNCTION("""COMPUTED_VALUE"""),277.0) -> 277 | E63: =IFERROR(__xludf.DUMMYFUNCTION("""COMPUTED_VALUE"""),195.0) -> 195 | F63: =IFERROR(__xludf.DUMMYFUNCTION("""COMPUTED_VALUE"""),15.0) -> 15
A64: =IFERROR(__xludf.DUMMYFUNCTION("""COMPUTED_VALUE"""),46224.0) -> 46224 | B64: =IFERROR(__xludf.DUMMYFUNCTION("""COMPUTED_VALUE"""),84.0) -> 84 | C64: =IFERROR(__xludf.DUMMYFUNCTION("""COMPUTED_VALUE"""),751.0) -> 751 | D64: =IFERROR(__xludf.DUMMYFUNCTION("""COMPUTED_VALUE"""),277.0) -> 277 | E64: =IFERROR(__xludf.DUMMYFUNCTION("""COMPUTED_VALUE"""),195.0) -> 195 | F64: =IFERROR(__xludf.DUMMYFUNCTION("""COMPUTED_VALUE"""),23.0) -> 23
A65: =IFERROR(__xludf.DUMMYFUNCTION("""COMPUTED_VALUE"""),46225.0) -> 46225 | B65: =IFERROR(__xludf.DUMMYFUNCTION("""COMPUTED_VALUE"""),84.0) -> 84 | C65: =IFERROR(__xludf.DUMMYFUNCTION("""COMPUTED_VALUE"""),745.0) -> 745 | D65: =IFERROR(__xludf.DUMMYFUNCTION("""COMPUTED_VALUE"""),276.0) -> 276 | E65: =IFERROR(__xludf.DUMMYFUNCTION("""COMPUTED_VALUE"""),198.0) -> 198 | F65: =IFERROR(__xludf.DUMMYFUNCTION("""COMPUTED_VALUE"""),27.0) -> 27
A66: =IFERROR(__xludf.DUMMYFUNCTION("""COMPUTED_VALUE"""),46226.0) -> 46226 | B66: =IFERROR(__xludf.DUMMYFUNCTION("""COMPUTED_VALUE"""),84.0) -> 84 | C66: =IFERROR(__xludf.DUMMYFUNCTION("""COMPUTED_VALUE"""),743.0) -> 743 | D66: =IFERROR(__xludf.DUMMYFUNCTION("""COMPUTED_VALUE"""),277.0) -> 277 | E66: =IFERROR(__xludf.DUMMYFUNCTION("""COMPUTED_VALUE"""),198.0) -> 198 | F66: =IFERROR(__xludf.DUMMYFUNCTION("""COMPUTED_VALUE"""),28.0) -> 28
A67: =IFERROR(__xludf.DUMMYFUNCTION("""COMPUTED_VALUE"""),46227.0) -> 46227 | B67: =IFERROR(__xludf.DUMMYFUNCTION("""COMPUTED_VALUE"""),84.0) -> 84 | C67: =IFERROR(__xludf.DUMMYFUNCTION("""COMPUTED_VALUE"""),742.0) -> 742 | D67: =IFERROR(__xludf.DUMMYFUNCTION("""COMPUTED_VALUE"""),277.0) -> 277 | E67: =IFERROR(__xludf.DUMMYFUNCTION("""COMPUTED_VALUE"""),196.0) -> 196 | F67: =IFERROR(__xludf.DUMMYFUNCTION("""COMPUTED_VALUE"""),31.0) -> 31
A68: =IFERROR(__xludf.DUMMYFUNCTION("""COMPUTED_VALUE"""),46228.0) -> 46228 | B68: =IFERROR(__xludf.DUMMYFUNCTION("""COMPUTED_VALUE"""),84.0) -> 84 | C68: =IFERROR(__xludf.DUMMYFUNCTION("""COMPUTED_VALUE"""),742.0) -> 742 | D68: =IFERROR(__xludf.DUMMYFUNCTION("""COMPUTED_VALUE"""),277.0) -> 277 | E68: =IFERROR(__xludf.DUMMYFUNCTION("""COMPUTED_VALUE"""),196.0) -> 196 | F68: =IFERROR(__xludf.DUMMYFUNCTION("""COMPUTED_VALUE"""),31.0) -> 31
A69: =IFERROR(__xludf.DUMMYFUNCTION("""COMPUTED_VALUE"""),46229.0) -> 46229 | B69: =IFERROR(__xludf.DUMMYFUNCTION("""COMPUTED_VALUE"""),84.0) -> 84 | C69: =IFERROR(__xludf.DUMMYFUNCTION("""COMPUTED_VALUE"""),742.0) -> 742 | D69: =IFERROR(__xludf.DUMMYFUNCTION("""COMPUTED_VALUE"""),277.0) -> 277 | E69: =IFERROR(__xludf.DUMMYFUNCTION("""COMPUTED_VALUE"""),196.0) -> 196 | F69: =IFERROR(__xludf.DUMMYFUNCTION("""COMPUTED_VALUE"""),31.0) -> 31
A70: =IFERROR(__xludf.DUMMYFUNCTION("""COMPUTED_VALUE"""),46230.0) -> 46230 | B70: =IFERROR(__xludf.DUMMYFUNCTION("""COMPUTED_VALUE"""),82.0) -> 82 | C70: =IFERROR(__xludf.DUMMYFUNCTION("""COMPUTED_VALUE"""),737.0) -> 737 | D70: =IFERROR(__xludf.DUMMYFUNCTION("""COMPUTED_VALUE"""),275.0) -> 275 | E70: =IFERROR(__xludf.DUMMYFUNCTION("""COMPUTED_VALUE"""),200.0) -> 200 | F70: =IFERROR(__xludf.DUMMYFUNCTION("""COMPUTED_VALUE"""),36.0) -> 36
A71: =IFERROR(__xludf.DUMMYFUNCTION("""COMPUTED_VALUE"""),46231.0) -> 46231 | B71: =IFERROR(__xludf.DUMMYFUNCTION("""COMPUTED_VALUE"""),81.0) -> 81 | C71: =IFERROR(__xludf.DUMMYFUNCTION("""COMPUTED_VALUE"""),731.0) -> 731 | D71: =IFERROR(__xludf.DUMMYFUNCTION("""COMPUTED_VALUE"""),275.0) -> 275 | E71: =IFERROR(__xludf.DUMMYFUNCTION("""COMPUTED_VALUE"""),204.0) -> 204 | F71: =IFERROR(__xludf.DUMMYFUNCTION("""COMPUTED_VALUE"""),39.0) -> 39
A72: =IFERROR(__xludf.DUMMYFUNCTION("""COMPUTED_VALUE"""),46232.0) -> 46232 | B72: =IFERROR(__xludf.DUMMYFUNCTION("""COMPUTED_VALUE"""),81.0) -> 81 | C72: =IFERROR(__xludf.DUMMYFUNCTION("""COMPUTED_VALUE"""),731.0) -> 731 | D72: =IFERROR(__xludf.DUMMYFUNCTION("""COMPUTED_VALUE"""),275.0) -> 275 | E72: =IFERROR(__xludf.DUMMYFUNCTION("""COMPUTED_VALUE"""),204.0) -> 204 | F72: =IFERROR(__xludf.DUMMYFUNCTION("""COMPUTED_VALUE"""),39.0) -> 39
A73: =IFERROR(__xludf.DUMMYFUNCTION("""COMPUTED_VALUE"""),46233.0) -> 46233 | B73: =IFERROR(__xludf.DUMMYFUNCTION("""COMPUTED_VALUE"""),81.0) -> 81 | C73: =IFERROR(__xludf.DUMMYFUNCTION("""COMPUTED_VALUE"""),727.0) -> 727 | D73: =IFERROR(__xludf.DUMMYFUNCTION("""COMPUTED_VALUE"""),271.0) -> 271 | E73: =IFERROR(__xludf.DUMMYFUNCTION("""COMPUTED_VALUE"""),204.0) -> 204 | F73: =IFERROR(__xludf.DUMMYFUNCTION("""COMPUTED_VALUE"""),47.0) -> 47
A74: =IFERROR(__xludf.DUMMYFUNCTION("""COMPUTED_VALUE"""),46234.0) -> 46234 | B74: =IFERROR(__xludf.DUMMYFUNCTION("""COMPUTED_VALUE"""),81.0) -> 81 | C74: =IFERROR(__xludf.DUMMYFUNCTION("""COMPUTED_VALUE"""),721.0) -> 721 | D74: =IFERROR(__xludf.DUMMYFUNCTION("""COMPUTED_VALUE"""),268.0) -> 268 | E74: =IFERROR(__xludf.DUMMYFUNCTION("""COMPUTED_VALUE"""),205.0) -> 205 | F74: =IFERROR(__xludf.DUMMYFUNCTION("""COMPUTED_VALUE"""),56.0) -> 56
A75: =IFERROR(__xludf.DUMMYFUNCTION("""COMPUTED_VALUE"""),46235.0) -> 46235 | B75: =IFERROR(__xludf.DUMMYFUNCTION("""COMPUTED_VALUE"""),80.0) -> 80 | C75: =IFERROR(__xludf.DUMMYFUNCTION("""COMPUTED_VALUE"""),713.0) -> 713 | D75: =IFERROR(__xludf.DUMMYFUNCTION("""COMPUTED_VALUE"""),268.0) -> 268 | E75: =IFERROR(__xludf.DUMMYFUNCTION("""COMPUTED_VALUE"""),206.0) -> 206 | F75: =IFERROR(__xludf.DUMMYFUNCTION("""COMPUTED_VALUE"""),64.0) -> 64
A76: =IFERROR(__xludf.DUMMYFUNCTION("""COMPUTED_VALUE"""),46236.0) -> 46236 | B76: =IFERROR(__xludf.DUMMYFUNCTION("""COMPUTED_VALUE"""),77.0) -> 77 | C76: =IFERROR(__xludf.DUMMYFUNCTION("""COMPUTED_VALUE"""),700.0) -> 700 | D76: =IFERROR(__xludf.DUMMYFUNCTION("""COMPUTED_VALUE"""),266.0) -> 266 | E76: =IFERROR(__xludf.DUMMYFUNCTION("""COMPUTED_VALUE"""),216.0) -> 216 | F76: =IFERROR(__xludf.DUMMYFUNCTION("""COMPUTED_VALUE"""),73.0) -> 73
A77: =IFERROR(__xludf.DUMMYFUNCTION("""COMPUTED_VALUE"""),46237.0) -> 46237 | B77: =IFERROR(__xludf.DUMMYFUNCTION("""COMPUTED_VALUE"""),76.0) -> 76 | C77: =IFERROR(__xludf.DUMMYFUNCTION("""COMPUTED_VALUE"""),696.0) -> 696 | D77: =IFERROR(__xludf.DUMMYFUNCTION("""COMPUTED_VALUE"""),262.0) -> 262 | E77: =IFERROR(__xludf.DUMMYFUNCTION("""COMPUTED_VALUE"""),217.0) -> 217 | F77: =IFERROR(__xludf.DUMMYFUNCTION("""COMPUTED_VALUE"""),81.0) -> 81
A78: =IFERROR(__xludf.DUMMYFUNCTION("""COMPUTED_VALUE"""),46238.0) -> 46238 | B78: =IFERROR(__xludf.DUMMYFUNCTION("""COMPUTED_VALUE"""),73.0) -> 73 | C78: =IFERROR(__xludf.DUMMYFUNCTION("""COMPUTED_VALUE"""),690.0) -> 690 | D78: =IFERROR(__xludf.DUMMYFUNCTION("""COMPUTED_VALUE"""),259.0) -> 259 | E78: =IFERROR(__xludf.DUMMYFUNCTION("""COMPUTED_VALUE"""),218.0) -> 218 | F78: =IFERROR(__xludf.DUMMYFUNCTION("""COMPUTED_VALUE"""),92.0) -> 92
A79: =IFERROR(__xludf.DUMMYFUNCTION("""COMPUTED_VALUE"""),46239.0) -> 46239 | B79: =IFERROR(__xludf.DUMMYFUNCTION("""COMPUTED_VALUE"""),73.0) -> 73 | C79: =IFERROR(__xludf.DUMMYFUNCTION("""COMPUTED_VALUE"""),679.0) -> 679 | D79: =IFERROR(__xludf.DUMMYFUNCTION("""COMPUTED_VALUE"""),254.0) -> 254 | E79: =IFERROR(__xludf.DUMMYFUNCTION("""COMPUTED_VALUE"""),225.0) -> 225 | F79: =IFERROR(__xludf.DUMMYFUNCTION("""COMPUTED_VALUE"""),101.0) -> 101
A80: =IFERROR(__xludf.DUMMYFUNCTION("""COMPUTED_VALUE"""),46240.0) -> 46240 | B80: =IFERROR(__xludf.DUMMYFUNCTION("""COMPUTED_VALUE"""),73.0) -> 73 | C80: =IFERROR(__xludf.DUMMYFUNCTION("""COMPUTED_VALUE"""),674.0) -> 674 | D80: =IFERROR(__xludf.DUMMYFUNCTION("""COMPUTED_VALUE"""),251.0) -> 251 | E80: =IFERROR(__xludf.DUMMYFUNCTION("""COMPUTED_VALUE"""),220.0) -> 220 | F80: =IFERROR(__xludf.DUMMYFUNCTION("""COMPUTED_VALUE"""),114.0) -> 114
A81: =IFERROR(__xludf.DUMMYFUNCTION("""COMPUTED_VALUE"""),46241.0) -> 46241 | B81: =IFERROR(__xludf.DUMMYFUNCTION("""COMPUTED_VALUE"""),71.0) -> 71 | C81: =IFERROR(__xludf.DUMMYFUNCTION("""COMPUTED_VALUE"""),665.0) -> 665 | D81: =IFERROR(__xludf.DUMMYFUNCTION("""COMPUTED_VALUE"""),245.0) -> 245 | E81: =IFERROR(__xludf.DUMMYFUNCTION("""COMPUTED_VALUE"""),226.0) -> 226 | F81: =IFERROR(__xludf.DUMMYFUNCTION("""COMPUTED_VALUE"""),125.0) -> 125
A82: =IFERROR(__xludf.DUMMYFUNCTION("""COMPUTED_VALUE"""),46242.0) -> 46242 | B82: =IFERROR(__xludf.DUMMYFUNCTION("""COMPUTED_VALUE"""),70.0) -> 70 | C82: =IFERROR(__xludf.DUMMYFUNCTION("""COMPUTED_VALUE"""),665.0) -> 665 | D82: =IFERROR(__xludf.DUMMYFUNCTION("""COMPUTED_VALUE"""),244.0) -> 244 | E82: =IFERROR(__xludf.DUMMYFUNCTION("""COMPUTED_VALUE"""),226.0) -> 226 | F82: =IFERROR(__xludf.DUMMYFUNCTION("""COMPUTED_VALUE"""),127.0) -> 127
A83: =IFERROR(__xludf.DUMMYFUNCTION("""COMPUTED_VALUE"""),46243.0) -> 46243 | B83: =IFERROR(__xludf.DUMMYFUNCTION("""COMPUTED_VALUE"""),70.0) -> 70 | C83: =IFERROR(__xludf.DUMMYFUNCTION("""COMPUTED_VALUE"""),661.0) -> 661 | D83: =IFERROR(__xludf.DUMMYFUNCTION("""COMPUTED_VALUE"""),244.0) -> 244 | E83: =IFERROR(__xludf.DUMMYFUNCTION("""COMPUTED_VALUE"""),224.0) -> 224 | F83: =IFERROR(__xludf.DUMMYFUNCTION("""COMPUTED_VALUE"""),133.0) -> 133
A84: =IFERROR(__xludf.DUMMYFUNCTION("""COMPUTED_VALUE"""),46244.0) -> 46244 | B84: =IFERROR(__xludf.DUMMYFUNCTION("""COMPUTED_VALUE"""),70.0) -> 70 | C84: =IFERROR(__xludf.DUMMYFUNCTION("""COMPUTED_VALUE"""),645.0) -> 645 | D84: =IFERROR(__xludf.DUMMYFUNCTION("""COMPUTED_VALUE"""),238.0) -> 238 | E84: =IFERROR(__xludf.DUMMYFUNCTION("""COMPUTED_VALUE"""),212.0) -> 212 | F84: =IFERROR(__xludf.DUMMYFUNCTION("""COMPUTED_VALUE"""),167.0) -> 167
A85: =IFERROR(__xludf.DUMMYFUNCTION("""COMPUTED_VALUE"""),46245.0) -> 46245 | B85: =IFERROR(__xludf.DUMMYFUNCTION("""COMPUTED_VALUE"""),69.0) -> 69 | C85: =IFERROR(__xludf.DUMMYFUNCTION("""COMPUTED_VALUE"""),626.0) -> 626 | D85: =IFERROR(__xludf.DUMMYFUNCTION("""COMPUTED_VALUE"""),234.0) -> 234 | E85: =IFERROR(__xludf.DUMMYFUNCTION("""COMPUTED_VALUE"""),207.0) -> 207 | F85: =IFERROR(__xludf.DUMMYFUNCTION("""COMPUTED_VALUE"""),196.0) -> 196

Sheet DAY1
A1: 攤位編號 | B1: 攤位名稱
A2: A01,A02 | B2: OriginZero
A3: A03 | B3: MAI
A4: A04 | B4: 心重力動漫工作室
A5: A05,A06 | B5: 蒼銀之星
A6: A07 | B6: 殺必死天國
A7: A08,A09 | B7: 闇夢館
A8: A10,A11 | B8: 三色坊
A9: A12,A13 | B9: 有害蕈類集會所
A10: A14 | B10: BsWs黑星白星
A11: A15,A16 | B11: 黑蛛白蛛
A12: A17,A18 | B12: 御狐亭
... A285: J07,J08 | B285: 克特小舖
A286: J09,J10 | B286: =+喵耳園魔法道具屋+ -> #ERROR!
A287: J11 | B287: 三分糖手作中
A288: J12 | B288: 光影之下
A289: J13,J14 | B289: 瑪魯瑪魯手創
A290: J15 | B290: 愛做夢的人
A291: J16 | B291: Cunomon庫糯夢
A292: J17,J18 | B292: 模型優創
A293: J19 | B293: ブルーブルルー
A294: J20 | B294: 奶油玉米的呆毛
A295: J21,J22 | B295: FuwaFuwa軟趴趴
A296: J23 | B296: M片 m-pien
A297: J24 | B297: RayP
A298: J25 | B298: M.O.K.茶包
... A713: W41,W42 | B713: 雨波HaneAme

Sheet 工作表25
A1: 攤位名稱 | B1: 筆名 | C1: 第一天 | D1: 第二天 | E1: 第三天 | F1: 創作者類型 | G1: 二創參考作品 (原創免填) | H1: 商品年齡分類 | I1: 作品類型 (原創、二創) | J1: 販售資訊 | K1: 特殊標籤或備註 | L1: {={ "有無資料"; BYROW(R5:AL2391, LAMBDA(currRow, COUNTA(currRow)>0)) }} -> 有無資料 | M1: {={ "有無販售資訊"; BYROW(H5:K2391, LAMBDA(currRow,COUNTA(currRow)>0)) }} -> 有無販售資訊 | N1: {={"有無預告";MAP(AM5:AM2391, LAMBDA(cell, ISTEXT(cell)))}} -> 有無預告 | O1: {={"有無品書";MAP(AN5:AN2391, LAMBDA(cell, ISTEXT(cell)))}} -> 有無品書 | P1: 資料信心度 | Q1: 印量調查 請至印調區填寫 | R1: FB (1) | S1: FB (2) | T1: Bluesky (1) | U1: Bluesky (2) | V1: TWITTER (1) | W1: TWITTER (2) | X1: PLURK | Y1: Pixiv | Z1: Fanbox | AA1: Fantia | AB1: 可洛斯 | AC1: 其他贊助平台 | AD1: IG | AE1: YOUTUBE | AF1: TWITCH | AG1: LINE | AH1: DISCORD | AI1: 巴哈姆特 | AJ1: 官方網站 | AK1: Linktree等連結整合網頁 | AL1: 其他連結 | AM1: 預告 | AN1: 品書 | AO1: 預購/通販 | AP1: 縮圖[請備註] | AQ1: 是否有縮圖 | AR1: 試閱
A2: KAWORU卡歐露 | C2: F25,F26 | D2: F25 | F2: 繪師, 台灣Vtuber個人勢 | G2: VTuber 小森クマ | H2: 一般 | I2: 原創 | J2: 💠同人誌【PRIVATA WARDROBE vol.2】250元 💠短髮立牌 💠拍立得 💠明信片 💠飯友 💠新刊小套組 700元 (同人誌+短髮立牌+拍立得+明信片+飯友) 💠護士立牌 💠護士飯友 💠新刊中套組 1300元 (小套組+護士立牌+護士飯友) 💠鎖邊滑鼠墊 600元 💠造型寫字板 💠小吊飾 💠新刊大套組 2000元 (中套組 + 滑鼠墊+寫字板+小吊飾) | L2: TRUE | M2: TRUE | N2: FALSE | O2: TRUE | Q2: {=IFERROR(INDEX('印量調查區'!G:G, MATCH(A2, '印量調查區'!A:A, 0)), "")} | R2: https://www.facebook.com/Kaworu1030 | V2: https://twitter.com/kaworu1030 | W2: https://twitter.com/kaworu_art | X2: https://www.plurk.com/kaworu1030 | Y2: https://www.pixiv.net/users/1671960 | AC2: https://www.patreon.com/Kaworu | AD2: https://www.instagram.com/kaworu1030/ | AF2: https://www.twitch.tv/kaworu1030 | AH2: https://discord.gg/pczy9uBGHd | AK2: https://lit.link/en/kaworu1030 | AM2: https://www.myacg.com.tw/goods_detail.php?gid=6637488 https://www.facebook.com/reel/1758198108184216/ | AN2: https://www.facebook.com/Kaworu1030/posts/pfbid02ty2hERdzKqeu9cJtgGhLQoq37SKdLJxxvUcyoZwL1ztfryAE2hYmF2iRHi5XiNcJl | AO2: https://www.myacg.com.tw/goods_detail.php?gid=6637488 | AQ2: =IFERROR(__xludf.DUMMYFUNCTION("IF(IFERROR(VLOOKUP(A2, IMPORTRANGE(""https://docs.google.com/spreadsheets/d/1eazy315Oas8TkAoTsdzUl6gNf3VsnwZeSo-bRfkZzOs"", ""工作表1!A:B""), 2, FALSE), """") <> """", ""有縮圖"", ""無縮圖"")"),"無縮圖") -> 無縮圖
A3: 枳枳zhizih | E3: R14 | F3: Coser | G3: 2.5次元的誘惑 | I3: 二創 | J3: 💠寫真集【2.5次元的天使】800元 💠寫真集套組 2400元 (寫真集 + 徽章 + 拍立得 + 吊飾 + 電子檔) 💠生寫真3枚 100元 💠圓形徽章 100元 💠拍立得 300元 💠迷你CD造型吊飾 350元 💠寫真電子檔700元 | L3: TRUE | M3: TRUE | N3: FALSE | O3: TRUE | Q3: {=IFERROR(INDEX('印量調查區'!G:G, MATCH(A3, '印量調查區'!A:A, 0)), "")} | AD3: https://www.instagram.com/zhizih0501/ | AN3: https://www.facebook.com/permalink.php?story_fbid=pfbid0T63kJejsvXVNETYmxr8mWaRKwheTrjtHFagQekHg824kPK5tzvwefGNy2xcqcx9Hl&id=61577006345762 | AQ3: =IFERROR(__xludf.DUMMYFUNCTION("IF(IFERROR(VLOOKUP(A3, IMPORTRANGE(""https://docs.google.com/spreadsheets/d/1eazy315Oas8TkAoTsdzUl6gNf3VsnwZeSo-bRfkZzOs"", ""工作表1!A:B""), 2, FALSE), """") <> """", ""有縮圖"", ""無縮圖"")"),"無縮圖") -> 無縮圖
A4: 蛞蝓.菠菜丼 | D4: P32[寄] | E4: P31,P32 | F4: 繪師 | G4: 2.5次元的誘惑，戀上換裝娃娃, 蔚藍檔案 / Blue Archive / ブルーアーカイブ | H4: R18, 一般 | I4: 二創 | J4: 💠海夢抱枕 2300元 💠掛軸 500元 💠等身掛軸 1000元 💠壓克力立牌 350元 💠防水桌墊 600元 | L4: TRUE | M4: TRUE | N4: FALSE | O4: TRUE | Q4: {=IFERROR(INDEX('印量調查區'!G:G, MATCH(A4, '印量調查區'!A:A, 0)), "")} | R4: https://www.facebook.com/SLUGTT666/ | V4: https://twitter.com/henny60225 | Y4: https://www.pixiv.net/users/14155307 | AN4: https://www.facebook.com/share/p/16gCNYqRoX/ | AQ4: =IFERROR(__xludf.DUMMYFUNCTION("IF(IFERROR(VLOOKUP(A4, IMPORTRANGE(""https://docs.google.com/spreadsheets/d/1eazy315Oas8TkAoTsdzUl6gNf3VsnwZeSo-bRfkZzOs"", ""工作表1!A:B""), 2, FALSE), """") <> """", ""有縮圖"", ""無縮圖"")"),"無縮圖") -> 無縮圖
A5: 共聚物精靈Copolymer Wizard | B5: 間宮ゆき/シマウマの頭 | C5: D33 | F5: 繪師 | G5: 千戀萬花、柚子社 | H5: 一般 | I5: 二創 | J5: 💠同人誌【Yuzusoft】200元 💠胸章 50元 💠15公分立牌 300元 💠小吊飾 50元 | L5: TRUE | M5: TRUE | N5: FALSE | O5: TRUE | Q5: {=IFERROR(INDEX('印量調查區'!G:G, MATCH(A5, '印量調查區'!A:A, 0)), "")} | R5: https://www.facebook.com/CopolymerWizard/ | V5: https://twitter.com/jiangongyouji1?fbclid=IwAR3pDPJdZv_CR-KCd4yvnhd0iBTTKTlLxY3PuioEuDFYVyCbxnApP_HZdic | W5: https://x.com/a29573359 | AI5: 巴哈姆特 | AN5: https://www.facebook.com/jeff.shu.7/posts/pfbid09TJGPK8Cd3F9GmTsnbRKnW2mtz5TNLa2Vc4XwRh8bq2eoKXEw1LX5nUZJoEAWPyvl | AQ5: =IFERROR(__xludf.DUMMYFUNCTION("IF(IFERROR(VLOOKUP(A5, IMPORTRANGE(""https://docs.google.com/spreadsheets/d/1eazy315Oas8TkAoTsdzUl6gNf3VsnwZeSo-bRfkZzOs"", ""工作表1!A:B""), 2, FALSE), """") <> """", ""有縮圖"", ""無縮圖"")"),"無縮圖") -> 無縮圖
A6: 全糖里斯 | B6: 里斯 | C6: V41 [寄] | D6: K17,K18 [寄] | E6: E31,E32 [寄] | F6: 繪師 | G6: 子午計畫 | H6: 一般 | I6: 二創 | J6: 壓克力色紙、Rei約會立牌、飯友、FF46套組 800元 | L6: TRUE | M6: TRUE | N6: FALSE | O6: FALSE | R6: https://www.facebook.com/ke.li.si.439192 | V6: https://x.com/tobunchudoku?fbclid=IwY2xjawPu6g5leHRuA2FlbQIxMABicmlkETE5ejhSdWUxNU5waFBwa2hac3J0YwZhcHBfaWQQMjIyMDM5MTc4ODIwMDg5MgABHthoKkK3Ue6M2MPpIUtI-5Gp7ecdon3dT0iM8JTflKc6K1VGJcwpGWGpJp9C_aem_psNr4gRaB1bGWyEzBKc-yA | AN6: https://www.facebook.com/photo/?fbid=2385347228593739&set=pcb.2385355538592908 | AQ6: =IFERROR(__xludf.DUMMYFUNCTION("IF(IFERROR(VLOOKUP(A6, IMPORTRANGE(""https://docs.google.com/spreadsheets/d/1eazy315Oas8TkAoTsdzUl6gNf3VsnwZeSo-bRfkZzOs"", ""工作表1!A:B""), 2, FALSE), """") <> """", ""有縮圖"", ""無縮圖"")"),"無縮圖") -> 無縮圖
A7: 米型自動複製單元 | B7: 米登卡爾 | C7: M36 | D7: M36 | F7: 繪師 | G7: 子午計畫,澪Rei | H7: 一般 | I7: 二創 | J7: 《有狸出沒注意報》刊物：NT.150 壓克力吊飾：NT.150 立牌：NT.350 燙金票卡：套組限定 不織布袋：套組限定 | L7: TRUE | M7: TRUE | N7: TRUE | O7: TRUE | Q7: {=IFERROR(INDEX('印量調查區'!G:G, MATCH(A7, '印量調查區'!A:A, 0)), "")} | R7: https://www.facebook.com/xi.jun.779/ | V7: https://twitter.com/setoharukano_12?fbclid=IwAR1HQF8M2DXctPL16LGe0DpaiF_9nInlCNQR1Fvo6Ysev2M7IPZhkNH6DNY | X7: https://www.plurk.com/Siawasenosekai | Y7: https://www.pixiv.net/users/14655223 | AN7: https://www.facebook.com/share/p/1C8L3KqAjz/ | AO7: https://www.myacg.com.tw/goods_detail.php?gid=6760962 | AQ7: =IFERROR(__xludf.DUMMYFUNCTION("IF(IFERROR(VLOOKUP(A7, IMPORTRANGE(""https://docs.google.com/spreadsheets/d/1eazy315Oas8TkAoTsdzUl6gNf3VsnwZeSo-bRfkZzOs"", ""工作表1!A:B""), 2, FALSE), """") <> """", ""有縮圖"", ""無縮圖"")"),"有縮圖") -> 有縮圖
A8: 虛擬家長會 | C8: V41 [寄] | D8: K17,K18 [寄] | E8: E31,E32 | F8: 繪師 | G8: 子午計劃 | H8: 一般 | I8: 二創 | J8: Kirali 約會立牌 350元 | L8: TRUE | M8: TRUE | N8: TRUE | O8: TRUE | Q8: {=IFERROR(INDEX('印量調查區'!G:G, MATCH(A8, '印量調查區'!A:A, 0)), "")} | R8: https://www.facebook.com/yu.an.chen.684671 | AN8: https://www.facebook.com/yu.an.chen.684671/posts/pfbid0gBAwxywRFnAS9Lfs3FjgQgXZ8Yq9GNYX6d83A4JeWbbNbYtqyHdVfRdAP3Y3ECYgl | AQ8: =IFERROR(__xludf.DUMMYFUNCTION("IF(IFERROR(VLOOKUP(A8, IMPORTRANGE(""https://docs.google.com/spreadsheets/d/1eazy315Oas8TkAoTsdzUl6gNf3VsnwZeSo-bRfkZzOs"", ""工作表1!A:B""), 2, FALSE), """") <> """", ""有縮圖"", ""無縮圖"")"),"無縮圖") -> 無縮圖
A9: に向思考 | B9: 貓崎 葵 | D9: V01 | E9: V09,V10 | F9: 繪師 | G9: 小智是女孩啦！ | H9: R18 | I9: 二創 | L9: TRUE | M9: TRUE | N9: FALSE | O9: TRUE | Q9: {=IFERROR(INDEX('印量調查區'!G:G, MATCH(A9, '印量調查區'!A:A, 0)), "")} | V9: https://x.com/NekosakiAoi | X9: https://www.plurk.com/sss4361 | Y9: https://www.pixiv.net/users/3318611 | AI9: https://home.gamer.com.tw/homeindex.php?owner=louieca400 | AQ9: =IFERROR(__xludf.DUMMYFUNCTION("IF(IFERROR(VLOOKUP(A9, IMPORTRANGE(""https://docs.google.com/spreadsheets/d/1eazy315Oas8TkAoTsdzUl6gNf3VsnwZeSo-bRfkZzOs"", ""工作表1!A:B""), 2, FALSE), """") <> """", ""有縮圖"", ""無縮圖"")"),"有縮圖") -> 有縮圖
A10: Bygin-白巾 | B10: Bygin-白巾 | C10: U43,U44 | D10: U21,U22 | E10: U21,U22 | F10: 繪師 | G10: 不時輕聲地以俄語遮羞的鄰座艾莉同學 | H10: R15, R18 | I10: 二創 | J10: 同人誌、龍心小悅套組 200元、捲到不行大套組 1000元 (本子+明信片+掛軸+杯墊+手機架+不織布提袋) | L10: TRUE | M10: TRUE | N10: FALSE | O10: TRUE | Q10: {=IFERROR(INDEX('印量調查區'!G:G, MATCH(A10, '印量調查區'!A:A, 0)), "")} | R10: https://www.facebook.com/byginartwork/ | S10: https://www.facebook.com/bygin01/ | T10: https://bsky.app/profile/bygin.bsky.social | V10: https://twitter.com/ByginArtist | W10: https://x.com/ByGin712576 | X10: https://www.plurk.com/chenyangyang100 | Y10: https://www.pixiv.net/users/13795156 | Z10: https://bygin.fanbox.cc/ | AC10: https://www.patreon.com/c/bygin?vanity=user | AD10: https://www.instagram.com/bygin_artwork/?hl=zh-tw | AH10: https://discord.gg/qCs4qX3T9x | AI10: https://home.gamer.com.tw/creation.php?owner=chenyang100 | AL10: https://linkgoods.com/bygin | AM10: https://www.myacg.com.tw/goods_detail.php?gid=6618082 https://www.myacg.com.tw/goods_detail.php?gid=6618075 https://www.myacg.com.tw/goods_detail.php?gid=6618072 | AN10: https://drive.google.com/drive/folders/1AYddpb6Rs63qS3q43DT0Id6tFaFLqJTu?usp=sharing | AO10: https://www.myacg.com.tw/goods_detail.php?gid=6618082 https://www.myacg.com.tw/goods_detail.php?gid=6618075 https://www.myacg.com.tw/goods_detail.php?gid=6618072 https://www.myacg.com.tw/seller_market.php?seller=693547 | AQ10: =IFERROR(__xludf.DUMMYFUNCTION("IF(IFERROR(VLOOKUP(A10, IMPORTRANGE(""https://docs.google.com/spreadsheets/d/1eazy315Oas8TkAoTsdzUl6gNf3VsnwZeSo-bRfkZzOs"", ""工作表1!A:B""), 2, FALSE), """") <> """", ""有縮圖"", ""無縮圖"")"),"有縮圖") -> 有縮圖 | AR10: https://www.facebook.com/byginartwork/posts/pfbid02AAZVLpecrEFT6XzJ2WQEhsYdw95qdueiUp9N8K9Znm5CaLDJhfyZ2TD3M6UkdJCdl
A11: 壞菇社 | B11: 凡爾賽菇雞三世、4why | C11: T43,T44 | D11: T43,T44 | F11: 繪師 | G11: 五等分的新娘 | H11: R18 | I11: 二創 | J11: 同人誌 100元 - 500元、桌墊 600元、掛軸 600元、立牌 300元 | L11: TRUE | M11: TRUE | N11: TRUE | O11: TRUE | Q11: {=IFERROR(INDEX('印量調查區'!G:G, MATCH(A11, '印量調查區'!A:A, 0)), "")} | R11: https://www.facebook.com/MARK4why/ | V11: https://twitter.com/ChickeIII | X11: https://www.plurk.com/fg3517 | Y11: https://www.pixiv.net/users/9752301 | AM11: https://www.plurk.com/p/3i6qaejivv | AN11: https://www.facebook.com/MARK4why/posts/pfbid09ECDKTqStxVzmmJjCP7u4hPDURCBgVc15opYujH8n2xonKYT7wtVDRxisyANfh2Ul | AQ11: =IFERROR(__xludf.DUMMYFUNCTION("IF(IFERROR(VLOOKUP(A11, IMPORTRANGE(""https://docs.google.com/spreadsheets/d/1eazy315Oas8TkAoTsdzUl6gNf3VsnwZeSo-bRfkZzOs"", ""工作表1!A:B""), 2, FALSE), """") <> """", ""有縮圖"", ""無縮圖"")"),"無縮圖") -> 無縮圖
A12: グリモア | B12: マカ | C12: N12 | D12: P39, P40 [寄] | F12: 繪師 | G12: 公主連結 | H12: R18 | I12: 二創 | J12: 💠同人誌新刊 400元 💠入浴劑100元 💠立牌共浴套組 2000元 💠既刊 💠限定掛軸 600元 | L12: TRUE | M12: TRUE | N12: TRUE | O12: TRUE | Q12: {=IFERROR(INDEX('印量調查區'!G:G, MATCH(A12, '印量調查區'!A:A, 0)), "")} | V12: https://x.com/a83d8 | X12: https://www.plurk.com/Maca105 | Y12: https://www.pixiv.net/users/834194 | Z12: https://macaca12.fanbox.cc/ | AL12: https://skeb.jp/@a83d8 | AN12: https://www.plurk.com/p/3i8zolr211 | AQ12: =IFERROR(__xludf.DUMMYFUNCTION("IF(IFERROR(VLOOKUP(A12, IMPORTRANGE(""https://docs.google.com/spreadsheets/d/1eazy315Oas8TkAoTsdzUl6gNf3VsnwZeSo-bRfkZzOs"", ""工作表1!A:B""), 2, FALSE), """") <> """", ""有縮圖"", ""無縮圖"")"),"有縮圖") -> 有縮圖
A13: ななしのはなし | D13: C08 | E13: D36 | F13: 音聲作品 | G13: 少女前線 / Girls' Frontline / ドールズフロントライン | H13: 一般 | I13: 二創 | J13: 同人誌 200元、海報 600元 | L13: FALSE | M13: TRUE | N13: FALSE | O13: FALSE | Q13: {=IFERROR(INDEX('印量調查區'!G:G, MATCH(A13, '印量調查區'!A:A, 0)), "")} | V13: https://x.com/nanasi_RPG | AJ13: https://nanashinohanashi.wixsite.com/nanahana | AN13: https://x.com/nanasi_RPG/status/2019249469838225910 | AQ13: =IFERROR(__xludf.DUMMYFUNCTION("IF(IFERROR(VLOOKUP(A13, IMPORTRANGE(""https://docs.google.com/spreadsheets/d/1eazy315Oas8TkAoTsdzUl6gNf3VsnwZeSo-bRfkZzOs"", ""工作表1!A:B""), 2, FALSE), """") <> """", ""有縮圖"", ""無縮圖"")"),"無縮圖") -> 無縮圖
A14: 英國酒狐 | B14: 妖怪名取 | E14: H12 | F14: 繪師 | G14: 少女前線 / Girls' Frontline / ドールズフロントライン | H14: 一般 | I14: 二創, 原創 | J14: 💠同人誌【元素少女】300元 💠吊飾 150元 💠既刊 100-300元 💠吊飾 150元 💠立牌 700元 💠桌墊 500元 💠卡套 300元 💠親筆簽繪板 | L14: TRUE | M14: TRUE | N14: TRUE | O14: FALSE | Q14: {=IFERROR(INDEX('印量調查區'!G:G, MATCH(A14, '印量調查區'!A:A, 0)), "")} | R14: https://www.facebook.com/NatoriYoukai/ | V14: https://x.com/NatoriYoukai | X14: https://www.plurk.com/YoukaiNatori | Y14: https://www.pixiv.net/users/8590070 | AB14: https://clusters.tw/profile/3B460821-62FF-401B-AD3F-9491B9A78669/works | AK14: https://linktr.ee/YoukaiNatori | AM14: https://www.facebook.com/NatoriYoukai/posts/pfbid0bSpTXEpRmgXWMkBzU9DRmwajjAwTMatEfokzRb2WJhGyfJAjJWdYcsiFtWfqfzCcl https://www.facebook.com/NatoriYoukai/posts/pfbid0J68GvLdKp5pYu8woXj8QqU3LkBfE7QPeDumWbk6dKbB36DZtmMTKFJNdKhH66Lkwl | AN14: https://www.plurk.com/p/3i8pn1yts5 | AQ14: =IFERROR(__xludf.DUMMYFUNCTION("IF(IFERROR(VLOOKUP(A14, IMPORTRANGE(""https://docs.google.com/spreadsheets/d/1eazy315Oas8TkAoTsdzUl6gNf3VsnwZeSo-bRfkZzOs"", ""工作表1!A:B""), 2, FALSE), """") <> """", ""有縮圖"", ""無縮圖"")"),"有縮圖") -> 有縮圖
A15: 萌妹子前線 | C15: E29,E30 | E15: D37,D38 | F15: 繪師 | G15: 少女前線 / Girls' Frontline / ドールズフロントライン | H15: 一般 | I15: 二創 | J15: 同人誌 150元、小吊飾 100元、抱枕 500元、短袖 500元、紅包 | L15: TRUE | M15: TRUE | N15: FALSE | O15: TRUE | Q15: {=IFERROR(INDEX('印量調查區'!G:G, MATCH(A15, '印量調查區'!A:A, 0)), "")} | R15: https://www.facebook.com/LiushengArt | V15: https://twitter.com/LiuSheng_Art | X15: https://www.plurk.com/mopackp09062 | Y15: https://www.pixiv.net/users/4237973 | AM15: https://www.facebook.com/LiushengArt/posts/pfbid022fZaqbnrcJxi7GCu6HmxEWmJPdMvAoPRZBbWyGSWSdPVdvzGRixc97ZTPVG4AZXgl?__cft__[0]=AZWb82CQ283o_XCMVuOaJdEAN2Xzwxvnc0ZyeytZXiAdce0g704HX3mQphbvMr88OA_uWz_PzMZjUJT4SAtTlJwC6Ns6yPT-9RsCuWID0Y7LoP_mP4tIjnUTuHhyQLGDho7RVl1KzKd0c730Qs8-g40k7Rsl4lXqHBy8JmWpT1BwX_bwHmqImWhowQcPOlg6JEk&__tn__=%2CO%2CP-R | AN15: https://www.plurk.com/p/3iacvx3oek | AQ15: =IFERROR(__xludf.DUMMYFUNCTION("IF(IFERROR(VLOOKUP(A15, IMPORTRANGE(""https://docs.google.com/spreadsheets/d/1eazy315Oas8TkAoTsdzUl6gNf3VsnwZeSo-bRfkZzOs"", ""工作表1!A:B""), 2, FALSE), """") <> """", ""有縮圖"", ""無縮圖"")"),"有縮圖") -> 有縮圖
A16: 曇焉幻獸閣 | B16: DINA | C16: E28 | F16: 繪師 | G16: 少女前線 / Girls' Frontline / ドールズフロントライン | H16: R18 | I16: 二創 | J16: T91同人誌 | L16: TRUE | M16: TRUE | N16: FALSE | O16: TRUE | Q16: {=IFERROR(INDEX('印量調查區'!G:G, MATCH(A16, '印量調查區'!A:A, 0)), "")} | AQ16: =IFERROR(__xludf.DUMMYFUNCTION("IF(IFERROR(VLOOKUP(A16, IMPORTRANGE(""https://docs.google.com/spreadsheets/d/1eazy315Oas8TkAoTsdzUl6gNf3VsnwZeSo-bRfkZzOs"", ""工作表1!A:B""), 2, FALSE), """") <> """", ""有縮圖"", ""無縮圖"")"),"無縮圖") -> 無縮圖
A17: 待援生活 | C17: D09 | D17: D11,D12 | G17: 少女樂團吶喊吧 / ガールズバンドクライ、Ave Mujica 、文豪野犬、第五人格 | H17: 一般 | I17: 二創 | J17: 💠少女樂團吶喊吧 - 7CM 旋轉立牌 / 6CM 迷你立牌 💠Ave Mujica - 7CM 旋轉立牌 💠文豪野犬 - 7.5CM 閃光特效徽章 💠第五人格 - 8CM 旋轉立牌 | L17: TRUE | M17: TRUE | N17: TRUE | O17: TRUE | Q17: {=IFERROR(INDEX('印量調查區'!G:G, MATCH(A17, '印量調查區'!A:A, 0)), "")} | R17: https://www.facebook.com/profile.php?id=61554084372762 | AM17: https://www.facebook.com/share/p/1C6PMoPYPD/ https://www.facebook.com/share/p/1GaWAXaEge/ https://www.facebook.com/share/p/1GEAXdpwSr/ https://www.facebook.com/share/p/18MhBcW2gy/ | AQ17: =IFERROR(__xludf.DUMMYFUNCTION("IF(IFERROR(VLOOKUP(A17, IMPORTRANGE(""https://docs.google.com/spreadsheets/d/1eazy315Oas8TkAoTsdzUl6gNf3VsnwZeSo-bRfkZzOs"", ""工作表1!A:B""), 2, FALSE), """") <> """", ""有縮圖"", ""無縮圖"")"),"無縮圖") -> 無縮圖
A18: 芸草冰 | D18: T13,T14 [寄] | E18: T13,T14 [寄] | F18: 繪師 | G18: 少女樂團吶喊吧 GBC | H18: 一般 | I18: 二創 | J18: 💠同人誌【晴空】500元 💠同人誌【陌路】400元 💠壓克力色紙 300元 💠徽章 300元 💠壓克力磚 350元 💠立牌 300元 | L18: TRUE | M18: TRUE | N18: FALSE | O18: FALSE | Q18: {=IFERROR(INDEX('印量調查區'!G:G, MATCH(A18, '印量調查區'!A:A, 0)), "")} | V18: https://x.com/su_yun81037 | Y18: https://www.pixiv.net/users/6586231 | AN18: https://x.com/su_yun81037/status/2017554151484621024/photo/2 | AQ18: =IFERROR(__xludf.DUMMYFUNCTION("IF(IFERROR(VLOOKUP(A18, IMPORTRANGE(""https://docs.google.com/spreadsheets/d/1eazy315Oas8TkAoTsdzUl6gNf3VsnwZeSo-bRfkZzOs"", ""工作表1!A:B""), 2, FALSE), """") <> """", ""有縮圖"", ""無縮圖"")"),"無縮圖") -> 無縮圖
A19: Yupipi | B19: Yupipi | E19: T27 | F19: 繪師 | G19: 少女樂團吶喊吧 GBC | H19: 一般 | I19: 二創 | J19: 💠TOGE PICK! 吊飾 / 項鍊 120元 💠TOGE PICK! 耳環 200元 💠豎起小 / 中指吧! 決策幣 50元 💠光柵卡 20元 💠貼紙包 100元 💠特殊明信片 30元 | L19: TRUE | M19: TRUE | N19: FALSE | O19: TRUE | P19: 高 | Q19: {=IFERROR(INDEX('印量調查區'!G:G, MATCH(A19, '印量調查區'!A:A, 0)), "")} | R19: https://www.facebook.com/benson.tu.526/ | X19: https://www.plurk.com/yupicopia | AN19: https://www.facebook.com/share/p/17mJyMDevt/ | AQ19: =IFERROR(__xludf.DUMMYFUNCTION("IF(IFERROR(VLOOKUP(A19, IMPORTRANGE(""https://docs.google.com/spreadsheets/d/1eazy315Oas8TkAoTsdzUl6gNf3VsnwZeSo-bRfkZzOs"", ""工作表1!A:B""), 2, FALSE), """") <> """", ""有縮圖"", ""無縮圖"")"),"無縮圖") -> 無縮圖
A20: 獸耳麵包 | D20: P05,P06 | E20: P05,P06 | F20: 繪師 | G20: 少女樂團吶喊吧、MyGO!!!!!、Ave Mujica | H20: 一般 | I20: 二創 | J20: GBC插畫合本、GBC畫冊、雷射卡、胸章、手偶、壓克力立牌、飯友 | L20: TRUE | M20: TRUE | N20: TRUE | O20: TRUE | Q20: {=IFERROR(INDEX('印量調查區'!G:G, MATCH(A20, '印量調查區'!A:A, 0)), "")} | AL20: https://5qvucp7gsmavuumjkspf53hjq31x9nm.world.taobao.com/shop/view_shop.htm?appUid=RAzN8HWYwW1gZcHo52KSaWNcQbVdu4xciUUUzZisPC9z9xKi7X1&spm=a21n57.1.hoverItem.4 | AM20: https://drive.google.com/file/d/1wcer2rVM2mL65RIYSpHCjqoPDy29L7Iv/view?usp=drive_link | AN20: https://drive.google.com/file/d/1PeqPSUwMrkherEB74GjIrTc5wQoIpbJy/view?usp=drive_link https://drive.google.com/file/d/1oau8BCcT_ivt_vr3IszkSbJARerRIubE/view?usp=sharing | AQ20: =IFERROR(__xludf.DUMMYFUNCTION("IF(IFERROR(VLOOKUP(A20, IMPORTRANGE(""https://docs.google.com/spreadsheets/d/1eazy315Oas8TkAoTsdzUl6gNf3VsnwZeSo-bRfkZzOs"", ""工作表1!A:B""), 2, FALSE), """") <> """", ""有縮圖"", ""無縮圖"")"),"有縮圖") -> 有縮圖
A21: Single Type | B21: 立、全白 | C21: F19,F20 | F21: 繪師 | G21: 世界計畫，勝利女神妮姬 / NIKKE: The Goddess of Victory / 勝利の女神:NIKKE | H21: R18 | I21: 二創, 原創 | J21: 💠原創獸耳同人誌+世界計畫同人誌 150元 💠妮姬灰姑娘抱枕 2000元 | K21: 獸耳 | L21: TRUE | M21: TRUE | N21: FALSE | O21: TRUE | Q21: {=IFERROR(INDEX('印量調查區'!G:G, MATCH(A21, '印量調查區'!A:A, 0)), "")} | V21: https://x.com/Aokihoshi | W21: https://x.com/flandremoe | Y21: https://www.pixiv.net/users/11067101 | Z21: PIXIV | AQ21: =IFERROR(__xludf.DUMMYFUNCTION("IF(IFERROR(VLOOKUP(A21, IMPORTRANGE(""https://docs.google.com/spreadsheets/d/1eazy315Oas8TkAoTsdzUl6gNf3VsnwZeSo-bRfkZzOs"", ""工作表1!A:B""), 2, FALSE), """") <> """", ""有縮圖"", ""無縮圖"")"),"有縮圖") -> 有縮圖
A22: 實體化技師團-次元突破計畫 | D22: L32 | E22: L32 | F22: 空間投影(MMD創作) | G22: 世界計畫、初音未來 / Hatsune Miku、Hololive | H22: 一般 | I22: 二創 | J22: 立體投影裝置/雷雕杯墊/印章 | L22: TRUE | M22: TRUE | N22: TRUE | O22: TRUE | Q22: {=IFERROR(INDEX('印量調查區'!G:G, MATCH(A22, '印量調查區'!A:A, 0)), "")} | R22: https://www.facebook.com/jittaika.tech | V22: https://x.com/tech_otaku_acg | AE22: https://www.youtube.com/@tech_otaku_holo | AK22: https://portaly.cc/acg_tech | AN22: https://www.facebook.com/jittaika.tech/posts/pfbid0TdiVGn8pGp19w7LhEFSgvfHyHZHPeJBmmbrwHKvftoyX2bMttPiFrimxtuBNXwr9l | AQ22: =IFERROR(__xludf.DUMMYFUNCTION("IF(IFERROR(VLOOKUP(A22, IMPORTRANGE(""https://docs.google.com/spreadsheets/d/1eazy315Oas8TkAoTsdzUl6gNf3VsnwZeSo-bRfkZzOs"", ""工作表1!A:B""), 2, FALSE), """") <> """", ""有縮圖"", ""無縮圖"")"),"無縮圖") -> 無縮圖
A23: Meikoです | B23: Meiko | C23: R34 | E23: Q12 | F23: Coser | G23: 出包王女 | H23: R15 | I23: 二創 | J23: 💠 寫真集「YAMIyummy」 1000 元 💠 電子DETA 800 元 💠 可愛小小鐵盒子 300 元 💠 串串吊飾 200 元 💠 拍立得/cuteccc 500 元 💠 一起去超市袋袋 350 元 💠 小小掛軸 600 元 💠 FULL SET 2500 元 💠 yami SET 1800 元 | L23: TRUE | M23: TRUE | N23: FALSE | O23: TRUE | P23: 高 | Q23: {=IFERROR(INDEX('印量調查區'!G:G, MATCH(A23, '印量調查區'!A:A, 0)), "")} | R23: https://www.facebook.com/meikoHuang0722/?locale=ja_JP | AM23: https://www.facebook.com/share/p/1DFRRciLJC/ | AN23: https://docs.google.com/forms/d/e/1FAIpQLSekokqYo3452LKFmL3BzZH83416o7QNoi1JKO4GgWou_Fj0Mg/viewform | AO23: https://docs.google.com/forms/d/e/1FAIpQLSekokqYo3452LKFmL3BzZH83416o7QNoi1JKO4GgWou_Fj0Mg/viewform | AQ23: =IFERROR(__xludf.DUMMYFUNCTION("IF(IFERROR(VLOOKUP(A23, IMPORTRANGE(""https://docs.google.com/spreadsheets/d/1eazy315Oas8TkAoTsdzUl6gNf3VsnwZeSo-bRfkZzOs"", ""工作表1!A:B""), 2, FALSE), """") <> """", ""有縮圖"", ""無縮圖"")"),"無縮圖") -> 無縮圖
A24: 鳥語花箱 | B24: 鳥語 | C24: V03,V04 [寄] | D24: M40 [寄] | E24: M40 [寄] | F24: 繪師 | G24: 台灣Vtuber，極深空計劃，鳴潮 / Wuthering Waves | H24: 一般 | I24: 二創 | J24: 💠卡牌 300元 💠壓克力板 400元 💠迷你立牌 350元 | L24: TRUE | M24: TRUE | N24: FALSE | O24: TRUE | Q24: {=IFERROR(INDEX('印量調查區'!G:G, MATCH(A24, '印量調查區'!A:A, 0)), "")} | V24: https://x.com/bird09_art | AC24: https://www.patreon.com/bird09 | AN24: https://x.com/bird09_art/status/2014467207963804006 | AQ24: =IFERROR(__xludf.DUMMYFUNCTION("IF(IFERROR(VLOOKUP(A24, IMPORTRANGE(""https://docs.google.com/spreadsheets/d/1eazy315Oas8TkAoTsdzUl6gNf3VsnwZeSo-bRfkZzOs"", ""工作表1!A:B""), 2, FALSE), """") <> """", ""有縮圖"", ""無縮圖"")"),"無縮圖") -> 無縮圖
A25: 社觸同好會 | C25: M26 | D25: M26 | F25: 繪師 | G25: 台V | H25: 一般 | I25: 二創 | J25: 馬年SET【雙面立牌 / 掛軸】 馬年桌曆SET【壓克力架座 / 明信片桌曆組】 明信片 SET【明信片 / 燙金明信片】 馬年最速SEY【壓克力架座 / 馬 / 蛇 /龍 / 兔年立牌 】 磚屬於你SET【壓克力磚】 | L25: TRUE | M25: TRUE | N25: TRUE | O25: TRUE | P25: 高 | Q25: {=IFERROR(INDEX('印量調查區'!G:G, MATCH(A25, '印量調查區'!A:A, 0)), "")} | V25: https://x.com/johnson51112 | AM25: https://x.com/johnson51112/status/1995749669532479920 | AN25: https://x.com/johnson51112/status/1995749669532479920 | AQ25: =IFERROR(__xludf.DUMMYFUNCTION("IF(IFERROR(VLOOKUP(A25, IMPORTRANGE(""https://docs.google.com/spreadsheets/d/1eazy315Oas8TkAoTsdzUl6gNf3VsnwZeSo-bRfkZzOs"", ""工作表1!A:B""), 2, FALSE), """") <> """", ""有縮圖"", ""無縮圖"")"),"無縮圖") -> 無縮圖
A26: ALG | C26: 企業攤 | D26: 企業攤 | E26: 企業攤 | F26: 動漫商品店 | G26: 台V、日V、Hololive、vtuber | I26: 二創 | J26: 各期生簽名卡、拍立得卡、Furyu 趴姿娃娃、手偶、friends with u 坐姿娃娃、誕生日小娃、hololive OFFICIAL CARD GAME相關系列的卡包、單卡、多層次壓克力磚、複合組裝壓克力立牌、卡套、卡盒、拍立得保護套、拍立得、語音收藏小卡、徽章 | L26: TRUE | M26: TRUE | N26: TRUE | O26: FALSE | R26: https://www.facebook.com/profile.php?id=61558040934069 | AN26: https://www.facebook.com/permalink.php?story_fbid=pfbid0tyMPKjCxx1JefzMDBVScGu7LQgcDAZu3ZE8cBzUkGyTZaPYpc7AqCvUPBcPhgN67l&id=61558040934069 | AQ26: =IFERROR(__xludf.DUMMYFUNCTION("IF(IFERROR(VLOOKUP(A26, IMPORTRANGE(""https://docs.google.com/spreadsheets/d/1eazy315Oas8TkAoTsdzUl6gNf3VsnwZeSo-bRfkZzOs"", ""工作表1!A:B""), 2, FALSE), """") <> """", ""有縮圖"", ""無縮圖"")"),"無縮圖") -> 無縮圖
A27: みゆき·Miyuki | C27: S19 | D27: S19 | F27: Coser | G27: 尼爾：自動人形 | H27: 一般 | I27: 二創 | J27: ⚫️《Recorded Echoes》寫真書 ❥ 售價 NT$ 700元 ⚫️ 休眠眼罩 ❥ 售價 NT$ 250元 ⚫️ 證件套 ❥ 售價 NT$ 200元 ⚫️ 2B拍立得 ❥ 豪華款 NT$ 400元/ 普通簽繪款NT$ 250元 🔷 套組 ⚪️ Access: Entry 小套組 ❥ 售價 NT$ 1000元 包含：寫真書x1冊_眼罩x1_卡套x1 ⚪️ Access: Core 中套組 ❥ 售價 NT$ 1200元 包含：寫真書x1冊_眼罩x1_卡套x1_一般拍立得x1 ⚪️ Access: Full 大套組 ❥ 售價 NT$ 1750元 包含：寫真書x1冊_眼罩x1_卡套x1_豪華拍立得×2 | L27: TRUE | M27: TRUE | N27: FALSE | O27: TRUE | Q27: {=IFERROR(INDEX('印量調查區'!G:G, MATCH(A27, '印量調查區'!A:A, 0)), "")} | R27: https://www.facebook.com/MiyukiTW | V27: https://x.com/doremiyukiii | AE27: https://www.youtube.com/channel/UC4WqAL2TOuty3gZXFwu84Hg?view_as=subscriber | AN27: https://www.facebook.com/MiyukiTW/posts/pfbid03TtbokKbVB5vRPaHAnE3so6JBVzDMj7VKDuQ6bJGAAQKRGSLVz2KqSdTGN2vTNxel | AQ27: =IFERROR(__xludf.DUMMYFUNCTION("IF(IFERROR(VLOOKUP(A27, IMPORTRANGE(""https://docs.google.com/spreadsheets/d/1eazy315Oas8TkAoTsdzUl6gNf3VsnwZeSo-bRfkZzOs"", ""工作表1!A:B""), 2, FALSE), """") <> """", ""有縮圖"", ""無縮圖"")"),"無縮圖") -> 無縮圖
A28: 醉宮Yomiya | C28: R25,R26 | D28: R25,R26 | E28: S01,S02 [寄] | F28: Coser | G28: 尼爾自動人形 | H28: R15, R18 | I28: 二創 | J28: 💠 尼爾自動人形 寫真集 900元 💠 電子寫真 600元 💠 一般套組 2500元 💠 限定套組 4000元 💠 掛軸 💠 電子寫真 💠 壓克力色紙 💠 滑鼠墊 | L28: TRUE | M28: TRUE | N28: TRUE | O28: FALSE | Q28: {=IFERROR(INDEX('印量調查區'!G:G, MATCH(A28, '印量調查區'!A:A, 0)), "")} | R28: https://www.facebook.com/yomiya.cos/ | V28: https://twitter.com/yomiya0918 | X28: PLURK | AD28: https://www.instagram.com/yomiya_cosplay/ | AM28: https://www.facebook.com/share/p/14TY88BK9sh/ | AN28: https://www.facebook.com/photo.php?fbid=1496885215133325&set=p.1496885215133325&type=3 | AO28: https://www.kkcospalyshop.com/products/2B | AQ28: =IFERROR(__xludf.DUMMYFUNCTION("IF(IFERROR(VLOOKUP(A28, IMPORTRANGE(""https://docs.google.com/spreadsheets/d/1eazy315Oas8TkAoTsdzUl6gNf3VsnwZeSo-bRfkZzOs"", ""工作表1!A:B""), 2, FALSE), """") <> """", ""有縮圖"", ""無縮圖"")"),"有縮圖") -> 有縮圖
A29: 1569 | B29: 菊壱Kiku | D29: R09 | F29: Coser，日本 | G29: 幼女戰記、OVERLORD、絕區零 / ZenlessZoneZero / ゼンレスゾーンゼロ | I29: 二創 | J29: 寫真集 | L29: TRUE | M29: TRUE | N29: TRUE | O29: TRUE | Q29: {=IFERROR(INDEX('印量調查區'!G:G, MATCH(A29, '印量調查區'!A:A, 0)), "")} | R29: http://www.facebook.com/1569kikuichi/ | V29: https://x.com/kiku1569 | X29: https://www.plurk.com/kiku1569 | Z29: https://kiku1569.fanbox.cc/ | AA29: https://fantia.jp/fanclubs/23118 | AC29: https://www.patreon.com/kiku1569 | AD29: https://www.instagram.com/kiku1569/ | AK29: https://linktr.ee/Kiku1569 | AM29: https://x.com/kiku1569/status/1994924603777704307 https://www.plurk.com/p/3i82ro5vtd | AQ29: =IFERROR(__xludf.DUMMYFUNCTION("IF(IFERROR(VLOOKUP(A29, IMPORTRANGE(""https://docs.google.com/spreadsheets/d/1eazy315Oas8TkAoTsdzUl6gNf3VsnwZeSo-bRfkZzOs"", ""工作表1!A:B""), 2, FALSE), """") <> """", ""有縮圖"", ""無縮圖"")"),"無縮圖") -> 無縮圖
A30: GODNASK | B30: 幽零 | C30: G37,G38 | D30: G37 | F30: 繪師 | G30: 永恆輪迴 | H30: R15 | I30: 二創 | J30: 💠艾茵兔女郎立牌 💠Shen li 老師 遊戲明信片套組 (明信片+同人誌三本) 400元 💠STEAM序號卡 100元 💠STEAM序號書籤 180元 💠18公分角色立牌 300元 💠同人誌【黑行者】100元 💠八公分立牌 200元 💠15公分立牌 300元 💠15公分立牌 300元 💠5公分磁鐵 140元 💠5公分吊飾 130元 💠便條紙 60元 💠明信片 50元 | L30: TRUE | M30: TRUE | N30: FALSE | O30: TRUE | Q30: {=IFERROR(INDEX('印量調查區'!G:G, MATCH(A30, '印量調查區'!A:A, 0)), "")} | R30: https://www.facebook.com/kamina0813 | V30: https://x.com/death0813 | X30: https://www.plurk.com/yorin0813 | Y30: https://www.pixiv.net/users/4003754/artworks | AI30: https://home.gamer.com.tw/profile/index.php?&owner=zero0813 | AJ30: https://yorin.weebly.com/ | AN30: https://www.plurk.com/p/3i94g2wpx5 | AQ30: =IFERROR(__xludf.DUMMYFUNCTION("IF(IFERROR(VLOOKUP(A30, IMPORTRANGE(""https://docs.google.com/spreadsheets/d/1eazy315Oas8TkAoTsdzUl6gNf3VsnwZeSo-bRfkZzOs"", ""工作表1!A:B""), 2, FALSE), """") <> """", ""有縮圖"", ""無縮圖"")"),"無縮圖") -> 無縮圖
A31: Kazeki風希 | D31: R32 | F31: Coser | G31: 米塔 | I31: 二創 | J31: 寫真集 | L31: TRUE | M31: TRUE | N31: TRUE | O31: TRUE | Q31: {=IFERROR(INDEX('印量調查區'!G:G, MATCH(A31, '印量調查區'!A:A, 0)), "")} | R31: https://www.facebook.com/kazeki012 | V31: https://x.com/ckazeki | AD31: https://www.instagram.com/kazeki0123/ | AM31: https://www.facebook.com/kazeki012/posts/pfbid02rS2ZKaT2psuw8YzcHPKSamEk3LqHZrko9uJphciYQ8qXKSzEk7DNL4GK3dDmHJp8l | AQ31: =IFERROR(__xludf.DUMMYFUNCTION("IF(IFERROR(VLOOKUP(A31, IMPORTRANGE(""https://docs.google.com/spreadsheets/d/1eazy315Oas8TkAoTsdzUl6gNf3VsnwZeSo-bRfkZzOs"", ""工作表1!A:B""), 2, FALSE), """") <> """", ""有縮圖"", ""無縮圖"")"),"無縮圖") -> 無縮圖
A32: UNKNOWN | C32: F29,F30 | D32: F29,F30 | F32: 繪師 | G32: 艾爾登法環 / ELDEN RING / エルデンリング | H32: R18 | I32: 原創, 二創 | J32: 💠同人誌【地方的太太去電影院不看電影】200元 💠同人誌 1+2 500元 1.同人誌【永恆女王的大屁屁】300元 2.同人誌【永恆女王的大捏捏】300元 💠鐵罐姊姊1號刊+鐵罐人組合包 200元 💠二創作品集(一般向+成人男性向 兩本) 500元 | L32: TRUE | M32: TRUE | N32: FALSE | O32: TRUE | Q32: {=IFERROR(INDEX('印量調查區'!G:G, MATCH(A32, '印量調查區'!A:A, 0)), "")} | R32: https://www.facebook.com/people/Aoin-Hatsu/100003209545299/ | V32: https://x.com/AoinHatsu | X32: https://www.plurk.com/Aoin | Y32: https://www.pixiv.net/users/537853 | Z32: https://aoin-riku.fanbox.cc/ | AE32: https://www.youtube.com/@aoinhatsu | AM32: https://www.facebook.com/share/p/17YeU6shbK/ | AN32: https://www.facebook.com/share/p/1FmZSjmCcn/ | AQ32: =IFERROR(__xludf.DUMMYFUNCTION("IF(IFERROR(VLOOKUP(A32, IMPORTRANGE(""https://docs.google.com/spreadsheets/d/1eazy315Oas8TkAoTsdzUl6gNf3VsnwZeSo-bRfkZzOs"", ""工作表1!A:B""), 2, FALSE), """") <> """", ""有縮圖"", ""無縮圖"")"),"有縮圖") -> 有縮圖
A33: 加零在電線桿下 | B33: 加零 | C33: I15,I16 | D33: I15,I16 | F33: 繪師 | G33: 初音未來 | H33: 一般 | I33: 原創, 二創 | J33: 💠春聯 💠壓克力夾子 💠貼紙 💠無框畫 💠行李束帶 💠識別牌 | L33: TRUE | M33: TRUE | N33: FALSE | O33: TRUE | Q33: {=IFERROR(INDEX('印量調查區'!G:G, MATCH(A33, '印量調查區'!A:A, 0)), "")} | R33: https://www.facebook.com/jia0kelvin/?locale=zh_TW | V33: https://twitter.com/jia0kelvin | X33: https://www.plurk.com/jia0kelvin | AD33: https://www.instagram.com/jia0kelvin/ | AE33: https://www.youtube.com/@jia0kelvin | AK33: https://portaly.cc/jia0kelvin?fbclid=IwY2xjawHB71lleHRuA2FlbQIxMAABHYB-Ljb5n_pq-9QHaQ4yrI-u_34kHpdo5rNks-bO-xAkwx4Lgp5COwWKuA_aem_bX7BH5gSF9EToG4X4pzI6A | AN33: https://www.facebook.com/share/p/14YDh62kVFk/ | AQ33: =IFERROR(__xludf.DUMMYFUNCTION("IF(IFERROR(VLOOKUP(A33, IMPORTRANGE(""https://docs.google.com/spreadsheets/d/1eazy315Oas8TkAoTsdzUl6gNf3VsnwZeSo-bRfkZzOs"", ""工作表1!A:B""), 2, FALSE), """") <> """", ""有縮圖"", ""無縮圖"")"),"無縮圖") -> 無縮圖
A34: 恐怖白果醬 | B34: 西米不是米 | E34: N18 | F34: 繪師 | G34: 初音未來 | H34: 一般, R18 | I34: 原創, 二創 | J34: 同人誌, 桌墊, 飯友, 鑰匙圈, 簽繪色紙 | L34: TRUE | M34: TRUE | N34: TRUE | O34: TRUE | Q34: {=IFERROR(INDEX('印量調查區'!G:G, MATCH(A34, '印量調查區'!A:A, 0)), "")} | R34: https://www.facebook.com/simelu2016?locale=ja_JP | V34: https://twitter.com/simelu1209 | X34: https://www.plurk.com/simelu | AM34: https://www.plurk.com/p/3i0rf4c3eo | AN34: https://www.facebook.com/share/p/1QKWcsu6hE/ | AQ34: =IFERROR(__xludf.DUMMYFUNCTION("IF(IFERROR(VLOOKUP(A34, IMPORTRANGE(""https://docs.google.com/spreadsheets/d/1eazy315Oas8TkAoTsdzUl6gNf3VsnwZeSo-bRfkZzOs"", ""工作表1!A:B""), 2, FALSE), """") <> """", ""有縮圖"", ""無縮圖"")"),"無縮圖") -> 無縮圖
A35: WHO YUA | C35: R33 | D35: R33 | F35: Coser，日本 | G35: 初音未來 | H35: 一般 | I35: 原創, 二創 | J35: 寫真集、拍立得、立牌、提袋、外套、拍立得 | L35: TRUE | M35: TRUE | N35: TRUE | O35: TRUE | Q35: {=IFERROR(INDEX('印量調查區'!G:G, MATCH(A35, '印量調查區'!A:A, 0)), "")} | V35: https://x.com/yuazzing | AE35: https://www.youtube.com/channel/UCQJUpyKgEI0HLYq6rBJYqVw/featured | AF35: https://www.twitch.tv/who_yuayura | AN35: https://x.com/yuazzing/status/2019059695697195451 | AQ35: =IFERROR(__xludf.DUMMYFUNCTION("IF(IFERROR(VLOOKUP(A35, IMPORTRANGE(""https://docs.google.com/spreadsheets/d/1eazy315Oas8TkAoTsdzUl6gNf3VsnwZeSo-bRfkZzOs"", ""工作表1!A:B""), 2, FALSE), """") <> """", ""有縮圖"", ""無縮圖"")"),"無縮圖") -> 無縮圖
A36: miling彌靈 | B36: 彌靈 | C36: U28 | D36: U31 | F36: 繪師 | G36: 初音未來 / Hatsune Miku | H36: 一般 | I36: 二創 | J36: 💠同人誌【RACING MIKU】200元 💠CD造型吊飾掉卡 100元 💠滿版立牌 100元 | L36: TRUE | M36: TRUE | N36: FALSE | O36: TRUE | P36: 高 | Q36: {=IFERROR(INDEX('印量調查區'!G:G, MATCH(A36, '印量調查區'!A:A, 0)), "")} | R36: https://www.facebook.com/mi.ling.yin.yue | V36: https://twitter.com/miiling447 | Y36: https://www.pixiv.net/users/25091153 | AD36: https://www.instagram.com/mi_ling447/ | AF36: https://www.twitch.tv/miiling | AK36: https://portaly.cc/miiling?utm_source=ig&utm_medium=social&utm_content=link_in_bio&fbclid=PAZXh0bgNhZW0CMTEAc3J0YwZhcHBfaWQMMjU2MjgxMDQwNTU4AAGnGjyQ0iSb84nSTIItbO05ktD5BbACdpqCEHat_RZ6DI1vC5IhlY2atIIIo_A_aem_-5iffaIVfo1YHGsAggnUHA | AN36: https://www.instagram.com/p/DTuU8znjxt_/ | AQ36: =IFERROR(__xludf.DUMMYFUNCTION("IF(IFERROR(VLOOKUP(A36, IMPORTRANGE(""https://docs.google.com/spreadsheets/d/1eazy315Oas8TkAoTsdzUl6gNf3VsnwZeSo-bRfkZzOs"", ""工作表1!A:B""), 2, FALSE), """") <> """", ""有縮圖"", ""無縮圖"")"),"無縮圖") -> 無縮圖
A37: MinuetWorks | B37: Tr@vis、安安淡定、BEEK | D37: U33 | E37: U23,U24 | F37: 繪師,音聲作品 | G37: 初音未來 / Hatsune Miku | H37: 一般 | I37: 二創 | J37: 音樂專輯「Smile Compiler 微笑編譯器」、滑鼠墊 450元、吸水杯墊 200元、既品 | L37: TRUE | M37: TRUE | N37: FALSE | O37: TRUE | Q37: {=IFERROR(INDEX('印量調查區'!G:G, MATCH(A37, '印量調查區'!A:A, 0)), "")} | R37: https://www.facebook.com/MinuetWorks/ | V37: https://twitter.com/travis_minuet | X37: https://www.plurk.com/travis1203 | Y37: https://www.pixiv.net/users/4157601 | AD37: https://www.instagram.com/travis_minuet/ | AE37: https://www.youtube.com/channel/UCZ-eKlQF__bbbXJJdK0BPhA?sub_confirmation=1 | AH37: https://discord.gg/j2xUmsZzdp | AI37: https://home.gamer.com.tw/profile/index.php?owner=rockmanz1203 | AJ37: https://solo.to/minuetworks | AM37: https://www.facebook.com/MinuetWorks/posts/pfbid02NfwvRERp78PkZ4VQykeM1xSirNcLuZ6anfX8MtnuaaahX54rGgsDSqxH3RaeLvdZl | AN37: https://www.facebook.com/photo/?fbid=1516144147177931&set=a.132016572257369 https://www.facebook.com/share/p/1CAF1s8FuT/ | AQ37: =IFERROR(__xludf.DUMMYFUNCTION("IF(IFERROR(VLOOKUP(A37, IMPORTRANGE(""https://docs.google.com/spreadsheets/d/1eazy315Oas8TkAoTsdzUl6gNf3VsnwZeSo-bRfkZzOs"", ""工作表1!A:B""), 2, FALSE), """") <> """", ""有縮圖"", ""無縮圖"")"),"無縮圖") -> 無縮圖
A38: 全糖雞蛋卷 | B38: 楓黎 | C38: U29,U30 | D38: U30 | F38: 繪師 | G38: 初音未來 / Hatsune Miku，Vocaloid | H38: 一般 | I38: 二創 | J38: 雪初音雙面立牌 300元 Q版旋轉立牌 150元 雪初音愛心徽章 50元 雪初音拍立得組 50元 握握飯友 100元 壓克力吊飾 100元 GUMI車貼包 150元 鏡音車貼包 150元 10cm大車貼 50元 | L38: TRUE | M38: TRUE | N38: TRUE | O38: TRUE | Q38: {=IFERROR(INDEX('印量調查區'!G:G, MATCH(A38, '印量調查區'!A:A, 0)), "")} | R38: https://www.facebook.com/profile.php?id=61569358773274 | T38: https://bsky.app/profile/fengliart.bsky.social/post/3l6u27ykrzx2a | AJ38: https://fengliart520.wixsite.com/my-site-2 | AL38: https://www.doujin.com.tw/groups/info/7808 | AM38: https://www.facebook.com/fengliart520/posts/pfbid022cJhNLaFNxNgT1FS69XApa6BmURGCtyGcV1fpTCNB9JdjypRX8SFtokiUW4T2LQ1l | AN38: https://www.facebook.com/share/p/1AuXJfxPex/ https://www.facebook.com/permalink.php?story_fbid=pfbid0Erx875eER1XSpxxfg9L8UsRfdpo9LU7bHczF7jDmDHGba1pFZLze5SB83Dvayzqpl&id=61573054561350 | AQ38: =IFERROR(__xludf.DUMMYFUNCTION("IF(IFERROR(VLOOKUP(A38, IMPORTRANGE(""https://docs.google.com/spreadsheets/d/1eazy315Oas8TkAoTsdzUl6gNf3VsnwZeSo-bRfkZzOs"", ""工作表1!A:B""), 2, FALSE), """") <> """", ""有縮圖"", ""無縮圖"")"),"無縮圖") -> 無縮圖
A39: bbibinbing | B39: bbibinbing | C39: U26,U27 | D39: U25,U26 | F39: 繪師 | G39: 初音未來 / Hatsune Miku、MyGO!!!!!、Ave Mujica、蔚藍檔案 / Blue Archive / ブルーアーカイブ、台灣Vtuber、貓祭、Aoi、灰妲 | H39: 一般 | I39: 二創 | J39: 💠飯友 150元 💠初音旋轉立牌 150元 💠馬口鐵盒 150元 💠貓祭腿腿夾子 150元 💠AOI歐派夾子 150元 💠灰妲雞腿夾 150元 💠初音腿腿夾 150元 💠花圈夾 150元 💠2.5D立牌 150元 💠貼紙 50元 💠吊飾&立牌 100元 3個200元 | L39: TRUE | M39: TRUE | N39: TRUE | O39: TRUE | Q39: {=IFERROR(INDEX('印量調查區'!G:G, MATCH(A39, '印量調查區'!A:A, 0)), "")} | V39: https://twitter.com/bbibinbingART | X39: https://www.plurk.com/bbibinbing | Y39: https://www.pixiv.net/users/647294 | AN39: https://www.facebook.com/bbibinbingART/posts/pfbid033AeCXDhzaFiWP8WMDzSr56CczuBWr61hdWC7RzVzNfE5HvJgCC3WPJuymFkSsWiul | AQ39: =IFERROR(__xludf.DUMMYFUNCTION("IF(IFERROR(VLOOKUP(A39, IMPORTRANGE(""https://docs.google.com/spreadsheets/d/1eazy315Oas8TkAoTsdzUl6gNf3VsnwZeSo-bRfkZzOs"", ""工作表1!A:B""), 2, FALSE), """") <> """", ""有縮圖"", ""無縮圖"")"),"有縮圖") -> 有縮圖
A40: 緋紅工房 | C40: V18 | D40: V25 | F40: 繪師 | G40: 吹響吧！上低音號 | H40: 一般 | I40: 二創 | J40: 新刊套組 (同人誌+明信片+徽章) 200元、壓克力立牌 400元、大掛軸 800元、小掛軸 400元、大滑鼠墊 500元、既刊 200元、掛軸 400元、壓克力立牌 400元-600元 | L40: TRUE | M40: TRUE | N40: TRUE | O40: TRUE | Q40: {=IFERROR(INDEX('印量調查區'!G:G, MATCH(A40, '印量調查區'!A:A, 0)), "")} | R40: FB | V40: https://twitter.com/k1380426 | X40: https://www.plurk.com/kurenaizzzz | Y40: https://www.pixiv.net/users/1380426 | AN40: https://www.facebook.com/k1380426/posts/pfbid02fGCoqTzZZqNZ4jindovWZkpFyxSE5dySAKFReKuLmpofmQ3GXtLGMzCk554J4K7Tl | AQ40: =IFERROR(__xludf.DUMMYFUNCTION("IF(IFERROR(VLOOKUP(A40, IMPORTRANGE(""https://docs.google.com/spreadsheets/d/1eazy315Oas8TkAoTsdzUl6gNf3VsnwZeSo-bRfkZzOs"", ""工作表1!A:B""), 2, FALSE), """") <> """", ""有縮圖"", ""無縮圖"")"),"有縮圖") -> 有縮圖
A41: やわらか依存 | B41: 青ぎ | E41: C36 | F41: 繪師，日本 | G41: 杏仁咪嚕，Vtuber | H41: 一般 | I41: 二創 | J41: 不織布包包、壓克力吊飾、小抱枕、同人誌、資料夾、滑鼠墊、咪魯精品套組 1200元、杯墊 200元、橡膠墊 700元、毛毯1500元 | K41: FF46 以「僅限預約者」的方式帶到台灣。 平常不會做一般現場帶貨 請務必事先預約。 | L41: TRUE | M41: TRUE | N41: FALSE | O41: TRUE | Q41: {=IFERROR(INDEX('印量調查區'!G:G, MATCH(A41, '印量調查區'!A:A, 0)), "")} | R41: https://www.facebook.com/Aogi.fanpage/ | V41: https://x.com/aoiro_seigi | W41: https://x.com/yawarakaizonTW | X41: https://www.plurk.com/aiiro_seigi | Y41: https://www.pixiv.net/users/33170810 | Z41: https://aoiroseigi.fanbox.cc/ | AA41: https://fantia.jp/fanclubs/7388 | AH41: https://discord.com/invite/mGezkupHKA | AJ41: https://yawarakaizon.com/top/ | AK41: https://aoiroseigi.amebaownd.com/pages/2204970/page_201808230017 | AL41: https://skeb.jp/@aoiroseigi | AM41: https://www.plurk.com/p/3i69hh2cgp | AN41: https://www.plurk.com/p/3i9sp969kt https://www.facebook.com/share/p/16MTY9W9Le/ | AQ41: =IFERROR(__xludf.DUMMYFUNCTION("IF(IFERROR(VLOOKUP(A41, IMPORTRANGE(""https://docs.google.com/spreadsheets/d/1eazy315Oas8TkAoTsdzUl6gNf3VsnwZeSo-bRfkZzOs"", ""工作表1!A:B""), 2, FALSE), """") <> """", ""有縮圖"", ""無縮圖"")"),"有縮圖") -> 有縮圖
A42: 一隻盧魚 | B42: 盧魚 | D42: V31 | F42: 繪師 | G42: 灼眼的夏娜 | I42: 二創 | J42: 夏娜和風立牌300元、轉印貼100元、小禮服明信片50元、掛軸600元、小鐵盒100元、飯友100元、咖啡勺100元、漢堡包150元、夏娜明信片25元 | L42: TRUE | M42: TRUE | N42: FALSE | O42: TRUE | Q42: {=IFERROR(INDEX('印量調查區'!G:G, MATCH(A42, '印量調查區'!A:A, 0)), "")} | R42: https://www.facebook.com/cosfish0708/ | V42: https://twitter.com/Luyu0708_art | X42: PLURK | Y42: https://www.pixiv.net/users/11677192?fbclid=IwAR0qFaIgABeP-U-8idSH_e7rlj0KRxaVuKcQqBxdp-vRVrC4uuB5ugeaHBk | AD42: IG | AE42: YOUTUBE | AF42: TWITCH | AH42: DISCORD | AI42: 巴哈姆特 | AM42: https://www.facebook.com/cosfish0708/posts/pfbid0W8wRRkGpxE4JUPz1f29N2vpxUf4dzjiDoxT2HGR6dy3CHz9qByHwoLpWYHWvU4wtl?__cft__[0]=AZWtYqKKxt6uFPb6V-s86_g9YP8Fz-aV_yDq8FCCgPUWwBQ9GBHAGQa0Fv4Ak7V1UqccEYb0WoMQtGOQgmHr7obgjiWS17aTXCrqWFVWO2nRc7TLxfMpqJSsaIvZeUqDVJNp4kH17m7r1GtmmcY4yY3kt7hwwgC_uFNHFtspK-i13m9FH3I5ZmnSDY4n2cONE18&__tn__=%2CO%2CP-R | AN42: https://www.facebook.com/share/p/1DSeBfAcHr/ | AQ42: =IFERROR(__xludf.DUMMYFUNCTION("IF(IFERROR(VLOOKUP(A42, IMPORTRANGE(""https://docs.google.com/spreadsheets/d/1eazy315Oas8TkAoTsdzUl6gNf3VsnwZeSo-bRfkZzOs"", ""工作表1!A:B""), 2, FALSE), """") <> """", ""有縮圖"", ""無縮圖"")"),"有縮圖") -> 有縮圖
A43: STAR BERRY | B43: 山猫スズメ | D43: G13 | E43: G13 | F43: 繪師，日本 | G43: 貝露莎、夢幻拉拉、魔法之星愛美、愛花仙子、魔法小天使、精靈小咪咪、魔法少女小圓、艦隊收藏 / Kantai Collection / 艦コレ | H43: R18, R15 | I43: 原創, 二創 | J43: 💠同人誌【美浜小姐和朋友們都愛自慰】200元 💠新刊套組 (漫畫+特典本+紙袋+壓克力立牌) 400元 💠同人誌【魔法少女的日常】 💠壓克力立牌 300元/個 500元/2個 💠既刊 100元 💠掛軸 600元 | L43: TRUE | M43: TRUE | N43: FALSE | O43: TRUE | Q43: {=IFERROR(INDEX('印量調查區'!G:G, MATCH(A43, '印量調查區'!A:A, 0)), "")} | V43: https://x.com/suzumeyamaneko_ | X43: https://www.plurk.com/suzumeyamaneko | Y43: https://www.pixiv.net/users/2057449 | AM43: https://www.plurk.com/p/3i8uutfrud https://www.plurk.com/p/3i8kr51hym https://x.com/suzumeyamaneko_/status/2015627133591392358 | AN43: https://www.plurk.com/p/3i9k66ss9e | AQ43: =IFERROR(__xludf.DUMMYFUNCTION("IF(IFERROR(VLOOKUP(A43, IMPORTRANGE(""https://docs.google.com/spreadsheets/d/1eazy315Oas8TkAoTsdzUl6gNf3VsnwZeSo-bRfkZzOs"", ""工作表1!A:B""), 2, FALSE), """") <> """", ""有縮圖"", ""無縮圖"")"),"無縮圖") -> 無縮圖
A44: 白範工作室 | D44: I35,I36 | E44: F21,F22 | F44: 繪師 | G44: 孤獨搖滾 | H44: 一般 | I44: 原創, 二創 | J44: 💠《REVERCORE超常事件簿》限定套組 200元 💠同人誌【流量英雄】150元 💠同人誌【白濁的冠軍之戰！】150元 | L44: TRUE | M44: TRUE | N44: FALSE | O44: FALSE | P44: 高 | Q44: {=IFERROR(INDEX('印量調查區'!G:G, MATCH(A44, '印量調查區'!A:A, 0)), "")} | R44: https://www.facebook.com/StudioRise13?mibextid=ibOpuV | V44: https://twitter.com/StudioRise | AK44: https://portaly.cc/StudioRise | AN44: https://www.facebook.com/Studio.reRise/posts/pfbid02zN2bXSuaEJdrxVRszhBo8eXJHXBH8hvTbH9U5d324eKGuQiZm6g2oUf92xiF9gPBl | AQ44: =IFERROR(__xludf.DUMMYFUNCTION("IF(IFERROR(VLOOKUP(A44, IMPORTRANGE(""https://docs.google.com/spreadsheets/d/1eazy315Oas8TkAoTsdzUl6gNf3VsnwZeSo-bRfkZzOs"", ""工作表1!A:B""), 2, FALSE), """") <> """", ""有縮圖"", ""無縮圖"")"),"無縮圖") -> 無縮圖
A45: 烏烏烏大維 | C45: T19,T20 | D45: T33,T34 | G45: 孤獨搖滾 | H45: 一般 | I45: 二創 | L45: TRUE | M45: TRUE | N45: FALSE | O45: TRUE | Q45: {=IFERROR(INDEX('印量調查區'!G:G, MATCH(A45, '印量調查區'!A:A, 0)), "")} | R45: https://www.facebook.com/kuan.wei.lin.372350? | AN45: https://www.facebook.com/share/p/1C3yTrZWDR/ | AQ45: =IFERROR(__xludf.DUMMYFUNCTION("IF(IFERROR(VLOOKUP(A45, IMPORTRANGE(""https://docs.google.com/spreadsheets/d/1eazy315Oas8TkAoTsdzUl6gNf3VsnwZeSo-bRfkZzOs"", ""工作表1!A:B""), 2, FALSE), """") <> """", ""有縮圖"", ""無縮圖"")"),"無縮圖") -> 無縮圖 | AR45: https://www.facebook.com/share/p/1C3yTrZWDR/
A46: 小菊小花園 | C46: T17,T18 | D46: T33,T34 [寄] | E46: T33,T34 | G46: 孤獨搖滾、Hololive | H46: 一般 | I46: 二創 | J46: 同人誌 200-900元 小卡 | L46: TRUE | M46: TRUE | N46: FALSE | O46: TRUE | Q46: {=IFERROR(INDEX('印量調查區'!G:G, MATCH(A46, '印量調查區'!A:A, 0)), "")} | R46: https://www.facebook.com/hua.xiao.hua.859628?__cft__[0]=AZZwwRygjvJTlXqWm6dFkMAsEyaW8gZVAQVLJY7CC4Tuc61BDH4FZ6WpHREQUQLiYZpnmQ15FmKlX-EzDLzoCxEgj2jxIKqtPtBSNO5QrOWfyMiAWSSCaIfWuGYp8dr2bylU8dXOVmIU80DUiAbre58lqcOJcjAD6Mg9l2AMrFs42vcmzI5A0pE8_mA1ybQFLkBIZpnDTmCAOTkxz7i8SMc3SZbpua_wVirLwHeqRJ0wng&__tn__=-UC%2CP-y-R | V46: https://x.com/0_71_Rain?fbclid=IwY2xjawPq7ihleHRuA2FlbQIxMABicmlkETE1NzhLQXg0bEdLMldvZGVQc3J0YwZhcHBfaWQQMjIyMDM5MTc4ODIwMDg5MgABHv3woSAOCsTE5h_Ivke9ubA96GoTbsiooKbT45OISMCUlD52xm7CSqmPyERK_aem_DxIcxBc2lwI1xvbYm0uh3w | Y46: https://www.pixiv.net/users/13155227 | AN46: https://www.facebook.com/hua.xiao.hua.859628/posts/pfbid026GWmDBDNPKYnJah69hLLB2hB5vSb98pYvDXj3ZFNaYMt2NLgR2HFqpUWL21VjZTGl | AQ46: =IFERROR(__xludf.DUMMYFUNCTION("IF(IFERROR(VLOOKUP(A46, IMPORTRANGE(""https://docs.google.com/spreadsheets/d/1eazy315Oas8TkAoTsdzUl6gNf3VsnwZeSo-bRfkZzOs"", ""工作表1!A:B""), 2, FALSE), """") <> """", ""有縮圖"", ""無縮圖"")"),"無縮圖") -> 無縮圖
A47: みゆる〜む伊月的空間 | B47: いづき | D47: V18 | E47: V18 | F47: 繪師，日本 | G47: 幸運星 | I47: 二創 | J47: 同人誌【幸運星聖地巡禮指南】 | L47: TRUE | M47: TRUE | N47: FALSE | O47: TRUE | Q47: {=IFERROR(INDEX('印量調查區'!G:G, MATCH(A47, '印量調查區'!A:A, 0)), "")} | T47: https://bsky.app/profile/bluetwintail.bsky.social | V47: https://x.com/bluetwintail | X47: https://www.plurk.com/bluetwintail | AQ47: =IFERROR(__xludf.DUMMYFUNCTION("IF(IFERROR(VLOOKUP(A47, IMPORTRANGE(""https://docs.google.com/spreadsheets/d/1eazy315Oas8TkAoTsdzUl6gNf3VsnwZeSo-bRfkZzOs"", ""工作表1!A:B""), 2, FALSE), """") <> """", ""有縮圖"", ""無縮圖"")"),"無縮圖") -> 無縮圖
A48: 克蘿 | D48: M37 [寄] | F48: 繪師 | G48: 明日方舟 | H48: R15, 一般 | I48: 二創 | J48: 💠克蘿出浴小心心立牌 300元 💠特製簽繪 1000元 💠捏捏小羊 艾爾黛拉吊飾 150元 💠明信片 | L48: TRUE | M48: TRUE | N48: FALSE | O48: TRUE | Q48: {=IFERROR(INDEX('印量調查區'!G:G, MATCH(A48, '印量調查區'!A:A, 0)), "")} | R48: https://www.facebook.com/profile.php?id=61556467349710&locale=zh_TW | T48: https://bsky.app/profile/koro410177.bsky.social | V48: https://x.com/koro410177 | AD48: https://www.instagram.com/koro_410177/ | AK48: https://lit.link/en/koro410177 | AN48: https://x.com/koro410177/status/2015801001882898938 | AQ48: =IFERROR(__xludf.DUMMYFUNCTION("IF(IFERROR(VLOOKUP(A48, IMPORTRANGE(""https://docs.google.com/spreadsheets/d/1eazy315Oas8TkAoTsdzUl6gNf3VsnwZeSo-bRfkZzOs"", ""工作表1!A:B""), 2, FALSE), """") <> """", ""有縮圖"", ""無縮圖"")"),"無縮圖") -> 無縮圖
A49: 舍團 | C49: C10 | F49: 繪師 | G49: 明日方舟 | H49: R18 | I49: 二創 | J49: 同人誌 200元、立牌 300元、既刊 150元 | L49: TRUE | M49: TRUE | N49: FALSE | O49: TRUE | Q49: {=IFERROR(INDEX('印量調查區'!G:G, MATCH(A49, '印量調查區'!A:A, 0)), "")} | R49: https://www.facebook.com/dannysses | AN49: https://www.facebook.com/permalink.php?story_fbid=pfbid0Zmdzo33wGN85Pbvh2C4Tcgm4XaSundSQnArM8uVe7msnqG3Mk5mQjB5NP5TqNqe5l&id=61586894452311 | AQ49: =IFERROR(__xludf.DUMMYFUNCTION("IF(IFERROR(VLOOKUP(A49, IMPORTRANGE(""https://docs.google.com/spreadsheets/d/1eazy315Oas8TkAoTsdzUl6gNf3VsnwZeSo-bRfkZzOs"", ""工作表1!A:B""), 2, FALSE), """") <> """", ""有縮圖"", ""無縮圖"")"),"無縮圖") -> 無縮圖
A50: 幽塗 | B50: 幽幽 | C50: C04 | D50: N39,N40 [寄] | E50: C03,C04 | F50: 繪師 | G50: 明日方舟 | H50: R15 | I50: 二創 | J50: 💠同人誌【Turquoiseblue】200元 💠雙面立牌 450元 💠雷射票 💠立牌兩款 500元 💠既刊 200元 💠競標掛軸 | L50: TRUE | M50: TRUE | N50: FALSE | O50: TRUE | Q50: {=IFERROR(INDEX('印量調查區'!G:G, MATCH(A50, '印量調查區'!A:A, 0)), "")} | R50: https://www.facebook.com/@yiokaki.owo/ | V50: https://x.com/yuki__yu_owo?fbclid=IwY2xjawH8Fg1leHRuA2FlbQIxMAABHadKyY_lt5HbRU_9rvxs8N2PbAt9DVO-fyncX3TvhmcYsfaXTzIH6-cU7A_aem_g1LboBVI3TdKSjlV8nNzWA | Y50: https://www.pixiv.net/users/35767309?fbclid=IwY2xjawH8FhVleHRuA2FlbQIxMAABHSO4tQ8MeLBxcZ4GN_iBMK468fSWpCsBqJ25DluAqNk4I7k7emE8wrj1lw_aem_unXT7rxF7ZmFeKhvNaySQw | AD50: https://www.instagram.com/yuki_yu_owo?fbclid=IwY2xjawH8FgRleHRuA2FlbQIxMAABHSBm2F23cbgRlDW0Hmy8D-4ig21nMp2boWEvDR4BZYWZlDeVrp-nGI9IOg_aem_GWMXfrSAu7scm4Vo5ojllQ | AN50: https://www.facebook.com/share/p/17s5oWP6AD/ | AO50: https://www.myacg.com.tw/seller_market.php?seller=312001&keyword=%E3%80%90FF46%E3%80%91%E3%80%90%E5%B9%BD%E5%B9%BD%E3%83%A6%E3%82%AD%E3%80%91 | AQ50: =IFERROR(__xludf.DUMMYFUNCTION("IF(IFERROR(VLOOKUP(A50, IMPORTRANGE(""https://docs.google.com/spreadsheets/d/1eazy315Oas8TkAoTsdzUl6gNf3VsnwZeSo-bRfkZzOs"", ""工作表1!A:B""), 2, FALSE), """") <> """", ""有縮圖"", ""無縮圖"")"),"無縮圖") -> 無縮圖
A51: 博士還不能休息 | B51: 貓小樹 | C51: C08 | F51: 繪師 | G51: 明日方舟 | H51: 一般 | I51: 二創 | J51: 塑心立牌套組 500元、彩窗立牌、雷射票、徽章、壓克力吊飾 150元、砂磚吊飾 400元、壓克力吊飾 300元 | L51: TRUE | M51: TRUE | N51: FALSE | O51: TRUE | Q51: {=IFERROR(INDEX('印量調查區'!G:G, MATCH(A51, '印量調查區'!A:A, 0)), "")} | R51: https://www.facebook.com/profile.php?id=100083322383475 | AN51: https://www.facebook.com/photo?fbid=890926267028111&set=pcb.890926303694774 | AQ51: =IFERROR(__xludf.DUMMYFUNCTION("IF(IFERROR(VLOOKUP(A51, IMPORTRANGE(""https://docs.google.com/spreadsheets/d/1eazy315Oas8TkAoTsdzUl6gNf3VsnwZeSo-bRfkZzOs"", ""工作表1!A:B""), 2, FALSE), """") <> """", ""有縮圖"", ""無縮圖"")"),"無縮圖") -> 無縮圖
A52: 跑跑鼬 | C52: C09 | E52: F17,F18 | F52: 繪師 | G52: 明日方舟 | H52: R18 | I52: 二創 | J52: 💠同人誌【摸摸凱爾希】180元 💠明日方舟掛軸 600元 💠既刊 200-250元 | L52: TRUE | M52: TRUE | N52: FALSE | O52: TRUE | Q52: {=IFERROR(INDEX('印量調查區'!G:G, MATCH(A52, '印量調查區'!A:A, 0)), "")} | R52: https://www.facebook.com/RunyoDraws/ | S52: https://www.facebook.com/profile.php?id=100093293982816 | V52: https://x.com/runyouo | Y52: https://www.pixiv.net/users/9521897 | AD52: https://www.instagram.com/1drawing_everyday/ | AN52: https://www.facebook.com/photo/?fbid=853063637493580&set=a.128106206655997 | AO52: https://myship.7-11.com.tw/general/detail/GM2408121304591 | AQ52: =IFERROR(__xludf.DUMMYFUNCTION("IF(IFERROR(VLOOKUP(A52, IMPORTRANGE(""https://docs.google.com/spreadsheets/d/1eazy315Oas8TkAoTsdzUl6gNf3VsnwZeSo-bRfkZzOs"", ""工作表1!A:B""), 2, FALSE), """") <> """", ""有縮圖"", ""無縮圖"")"),"有縮圖") -> 有縮圖
A53: Ema箱 | C53: C05 | D53: C05 | F53: 繪師 | G53: 明日方舟 | H53: 一般 | I53: 二創 | J53: 💠新刊套組 500元 (同人誌+胸章+鑰匙圈+明信片) 💠同人誌【日余方舟新刊】200元 💠胸章 100元 💠阿米婭壓克力雙面鑰匙圈 150元 💠日常幹員明信片 100元 💠既刊 200-250元 | L53: TRUE | M53: TRUE | N53: FALSE | O53: FALSE | Q53: {=IFERROR(INDEX('印量調查區'!G:G, MATCH(A53, '印量調查區'!A:A, 0)), "")} | R53: https://www.facebook.com/KuguiEMA/?locale=zh_CN | V53: https://twitter.com/KuguiEMA?fbclid=IwAR3bwzVhf2GIisAnfKYbgInAAaQPIZYdIMhRp0-4Sde4t5NNnt-swmBuFyM | Y53: https://www.pixiv.net/users/8990183 | AD53: https://www.instagram.com/ema_qvq | AN53: https://www.facebook.com/photo?fbid=1467855492016593&set=a.457920249676794 | AQ53: =IFERROR(__xludf.DUMMYFUNCTION("IF(IFERROR(VLOOKUP(A53, IMPORTRANGE(""https://docs.google.com/spreadsheets/d/1eazy315Oas8TkAoTsdzUl6gNf3VsnwZeSo-bRfkZzOs"", ""工作表1!A:B""), 2, FALSE), """") <> """", ""有縮圖"", ""無縮圖"")"),"無縮圖") -> 無縮圖
A54: FOODpenguin | B54: 啞苦 | C54: L29 | D54: L29 | F54: 繪師 | G54: 明日方舟 | H54: R15 | I54: 二創 | J54: 💠 新刊套組 500 元 ▫️ 同人誌新刊《Trick and Treat》 200 元 ▫️ 御守 ▫️ 明信片 ▫️ 壓克力立繪版 ▫️ Q版貼紙 100 元 ▫️ 提袋 💠 吊飾 150 元 💠 像素吊飾 100 元 💠 銀河膜貼紙 100 元 💠 極光膜貼紙 50 元 💠 掛軸 800 元 💠 眼鏡布 100 元 💠 壓克力立牌 300 元 | L54: TRUE | M54: TRUE | N54: FALSE | O54: FALSE | Q54: {=IFERROR(INDEX('印量調查區'!G:G, MATCH(A54, '印量調查區'!A:A, 0)), "")} | R54: https://www.facebook.com/tsenp.shuju/ | V54: https://x.com/yaku_joan | W54: https://x.com/yaku_joan1818 | Y54: https://www.pixiv.net/users/14223271 | Z54: https://yakupenguin.fanbox.cc/ | AN54: https://www.facebook.com/tsenp.shuju/posts/pfbid0oNfwz8wQGAECrt2D16bsjYs2KhPDqRv6ehrx3Bgbq2Tg3f3v3GfNpegGJyCptdntl | AO54: https://reurl.cc/lZK9dY | AQ54: =IFERROR(__xludf.DUMMYFUNCTION("IF(IFERROR(VLOOKUP(A54, IMPORTRANGE(""https://docs.google.com/spreadsheets/d/1eazy315Oas8TkAoTsdzUl6gNf3VsnwZeSo-bRfkZzOs"", ""工作表1!A:B""), 2, FALSE), """") <> """", ""有縮圖"", ""無縮圖"")"),"有縮圖") -> 有縮圖
A55: 命由工作室 | C55: E05,E06 [寄] | D55: D04 [寄] | F55: 繪師 | G55: 東方Project | H55: 一般 | I55: 二創 | J55: 同人誌 200元 | L55: TRUE | M55: TRUE | N55: FALSE | O55: TRUE | Q55: {=IFERROR(INDEX('印量調查區'!G:G, MATCH(A55, '印量調查區'!A:A, 0)), "")} | R55: https://www.facebook.com/FreelLve? | Y55: https://www.pixiv.net/users/4972747?fbclid=IwRlRTSAPrc1NleHRuA2FlbQIxMABzcnRjBmFwcF9pZA8xNzM4NDc2NDI2NzAzNzAAAR4HiwMBXsBJhE2SQ-MtVL4qki3tYQGJA9kCMT6cL3Kr5qT8s-7Im56Zaym-Ew_aem_n7fxi29jBFiOOWAgfSoQXg | AN55: https://m.facebook.com/story.php?story_fbid=pfbid02BiZu3hR968hEwQWaYJNhoP9UekQZBJWWHbpjDJPxeDpqhWZZzr2RKAXsvPKFfXMtl&id=100063798126537 | AQ55: =IFERROR(__xludf.DUMMYFUNCTION("IF(IFERROR(VLOOKUP(A55, IMPORTRANGE(""https://docs.google.com/spreadsheets/d/1eazy315Oas8TkAoTsdzUl6gNf3VsnwZeSo-bRfkZzOs"", ""工作表1!A:B""), 2, FALSE), """") <> """", ""有縮圖"", ""無縮圖"")"),"無縮圖") -> 無縮圖
A56: 東方project文文新聞資訊部 | D56: E05 | E56: E05 | F56: 東方Project資訊網 | G56: 東方Project / Touhou Project | I56: 二創 | L56: TRUE | M56: TRUE | N56: FALSE | O56: FALSE | Q56: {=IFERROR(INDEX('印量調查區'!G:G, MATCH(A56, '印量調查區'!A:A, 0)), "")} | R56: https://www.facebook.com/p/%E6%9D%B1%E6%96%B9project-%E6%96%87%E6%96%87%E6%96%B0%E8%81%9E%E8%B3%87%E8%A8%8A%E9%83%A8-61554006466732/?locale=zh_TW | AQ56: =IFERROR(__xludf.DUMMYFUNCTION("IF(IFERROR(VLOOKUP(A56, IMPORTRANGE(""https://docs.google.com/spreadsheets/d/1eazy315Oas8TkAoTsdzUl6gNf3VsnwZeSo-bRfkZzOs"", ""工作表1!A:B""), 2, FALSE), """") <> """", ""有縮圖"", ""無縮圖"")"),"無縮圖") -> 無縮圖
A57: すなめりドリル | B57: 姉太郎 | D57: E15,E16 | E57: E15,E16 | F57: 社團，日本 | G57: 東方Project / Touhou Project | I57: 二創 | L57: TRUE | M57: TRUE | N57: FALSE | O57: TRUE | Q57: {=IFERROR(INDEX('印量調查區'!G:G, MATCH(A57, '印量調查區'!A:A, 0)), "")} | V57: https://x.com/sunameridrill | Y57: https://www.pixiv.net/users/31986233 | AD57: https://www.instagram.com/anetarou_monkid/ | AJ57: https://anetarou.com/ | AK57: https://lit.link/zh-tw/sunameridrill | AQ57: =IFERROR(__xludf.DUMMYFUNCTION("IF(IFERROR(VLOOKUP(A57, IMPORTRANGE(""https://docs.google.com/spreadsheets/d/1eazy315Oas8TkAoTsdzUl6gNf3VsnwZeSo-bRfkZzOs"", ""工作表1!A:B""), 2, FALSE), """") <> """", ""有縮圖"", ""無縮圖"")"),"無縮圖") -> 無縮圖
A58: A-One | C58: E07 | D58: E07 | F58: 音聲作品 | G58: 東方Project / Touhou Project | I58: 二創 | J58: 💠CD：THE ARCADE TRAX 600元 💠CD：EYE LOVE YOU,YOU LOVE ME? 400元 💠CD：The Night of the Chupacabra (ft.Mint Fantôme) 400元 💠CD：A-One 音ゲーBEST!! 600元 | L58: TRUE | M58: TRUE | N58: FALSE | O58: FALSE | Q58: {=IFERROR(INDEX('印量調查區'!G:G, MATCH(A58, '印量調查區'!A:A, 0)), "")} | V58: https://twitter.com/a_one_jp | AE58: https://www.youtube.com/channel/UCrIrRpXL1F7B03ozb_VECiQ | AN58: https://x.com/A_One_JP/status/2019304990238495012?s=20 | AQ58: =IFERROR(__xludf.DUMMYFUNCTION("IF(IFERROR(VLOOKUP(A58, IMPORTRANGE(""https://docs.google.com/spreadsheets/d/1eazy315Oas8TkAoTsdzUl6gNf3VsnwZeSo-bRfkZzOs"", ""工作表1!A:B""), 2, FALSE), """") <> """", ""有縮圖"", ""無縮圖"")"),"無縮圖") -> 無縮圖
A59: CrazyBeats | D59: E02,E03 | E59: E02,E03 | F59: 音聲作品 | G59: 東方Project / Touhou Project | I59: 二創 | L59: TRUE | M59: TRUE | N59: TRUE | O59: FALSE | Q59: {=IFERROR(INDEX('印量調查區'!G:G, MATCH(A59, '印量調查區'!A:A, 0)), "")} | AJ59: https://soundcloud.com/crazybeats-official | AQ59: =IFERROR(__xludf.DUMMYFUNCTION("IF(IFERROR(VLOOKUP(A59, IMPORTRANGE(""https://docs.google.com/spreadsheets/d/1eazy315Oas8TkAoTsdzUl6gNf3VsnwZeSo-bRfkZzOs"", ""工作表1!A:B""), 2, FALSE), """") <> """", ""有縮圖"", ""無縮圖"")"),"無縮圖") -> 無縮圖
A60: Crest | C60: E13 | D60: E06 | F60: 音聲作品 | G60: 東方Project / Touhou Project | H60: 一般 | I60: 二創 | J60: 💠「FF46新作套組」500元 ▫️新作CD「Chasing the First Light] 450元 ▫️新作EP「Reconnection」 50元 ▫️CD發行紀念演唱會鐳射票 50元 ▫️魔理沙記事本 50元 ▫️A4資料夾 50元 ▫️下載卡 (無單價) 💠16GB USB卡 450元 💠Catalog CD 350元/張，1000元/三張 【CD+下載卡】 💠Re:Alize 450元 💠Re:RISE 450元 💠Dual Circulation I + II 450元 💠Aria / Nocturne 450元 💠Hole In The Wall 350元 💠茜眩帷-SENGENI- 350元 | L60: TRUE | M60: TRUE | N60: TRUE | O60: FALSE | Q60: {=IFERROR(INDEX('印量調查區'!G:G, MATCH(A60, '印量調查區'!A:A, 0)), "")} | R60: https://www.facebook.com/jeetsingh.jp | V60: https://x.com/jeet_crest | AD60: https://www.instagram.com/crest_music_production | AJ60: https://crest-music.net/crest-biography | AN60: https://x.com/jeet_crest/status/2018975817049739543 | AQ60: =IFERROR(__xludf.DUMMYFUNCTION("IF(IFERROR(VLOOKUP(A60, IMPORTRANGE(""https://docs.google.com/spreadsheets/d/1eazy315Oas8TkAoTsdzUl6gNf3VsnwZeSo-bRfkZzOs"", ""工作表1!A:B""), 2, FALSE), """") <> """", ""有縮圖"", ""無縮圖"")"),"無縮圖") -> 無縮圖
A61: DiGiTAL WiNG | E61: E09,E10 | F61: 音聲作品 | G61: 東方Project / Touhou Project | I61: 二創 | L61: TRUE | M61: TRUE | N61: FALSE | O61: FALSE | Q61: {=IFERROR(INDEX('印量調查區'!G:G, MATCH(A61, '印量調查區'!A:A, 0)), "")} | AJ61: https://digital-wing.net/ | AQ61: =IFERROR(__xludf.DUMMYFUNCTION("IF(IFERROR(VLOOKUP(A61, IMPORTRANGE(""https://docs.google.com/spreadsheets/d/1eazy315Oas8TkAoTsdzUl6gNf3VsnwZeSo-bRfkZzOs"", ""工作表1!A:B""), 2, FALSE), """") <> """", ""有縮圖"", ""無縮圖"")"),"無縮圖") -> 無縮圖
A62: TAMUSIC | C62: E08 | D62: E08 | F62: 音聲作品 | G62: 東方Project / Touhou Project | H62: 一般 | I62: 二創 | L62: TRUE | M62: TRUE | N62: FALSE | O62: TRUE | P62: 高 | Q62: {=IFERROR(INDEX('印量調查區'!G:G, MATCH(A62, '印量調查區'!A:A, 0)), "")} | V62: https://twitter.com/tamusic/ | W62: https://x.com/TAMUSIC_staff | Y62: http://www.pixiv.net/member.php?id=240508 | AE62: http://www.youtube.com/user/violinpiano2 | AL62: https://vocadb.net/Ar/2474 | AM62: https://x.com/TAMUSIC_STAFF/status/2017512127771377836?s=20 | AQ62: =IFERROR(__xludf.DUMMYFUNCTION("IF(IFERROR(VLOOKUP(A62, IMPORTRANGE(""https://docs.google.com/spreadsheets/d/1eazy315Oas8TkAoTsdzUl6gNf3VsnwZeSo-bRfkZzOs"", ""工作表1!A:B""), 2, FALSE), """") <> """", ""有縮圖"", ""無縮圖"")"),"無縮圖") -> 無縮圖
A63: 交響アクティブNEETs | C63: E14 | F63: 音聲作品，日本 | G63: 東方Project / Touhou Project | I63: 二創 | L63: TRUE | M63: TRUE | N63: FALSE | O63: TRUE | P63: 高 | Q63: {=IFERROR(INDEX('印量調查區'!G:G, MATCH(A63, '印量調查區'!A:A, 0)), "")} | V63: https://twitter.com/active_neets | AJ63: https://neets.tokyo/index.html | AM63: https://www.plurk.com/p/3ia8oodot2 | AQ63: =IFERROR(__xludf.DUMMYFUNCTION("IF(IFERROR(VLOOKUP(A63, IMPORTRANGE(""https://docs.google.com/spreadsheets/d/1eazy315Oas8TkAoTsdzUl6gNf3VsnwZeSo-bRfkZzOs"", ""工作表1!A:B""), 2, FALSE), """") <> """", ""有縮圖"", ""無縮圖"")"),"無縮圖") -> 無縮圖
A64: 彩音 〜xi-on〜 | B64: 彩音 | C64: E11,E12 | D64: E11,E12 | F64: 音聲作品，日本 | G64: 東方Project / Touhou Project | I64: 二創 | L64: TRUE | M64: TRUE | N64: TRUE | O64: FALSE | Q64: {=IFERROR(INDEX('印量調查區'!G:G, MATCH(A64, '印量調查區'!A:A, 0)), "")} | V64: https://x.com/xion_p | AE64: https://www.youtube.com/@xionmusic | AL64: http://xion-music.com/ | AQ64: =IFERROR(__xludf.DUMMYFUNCTION("IF(IFERROR(VLOOKUP(A64, IMPORTRANGE(""https://docs.google.com/spreadsheets/d/1eazy315Oas8TkAoTsdzUl6gNf3VsnwZeSo-bRfkZzOs"", ""工作表1!A:B""), 2, FALSE), """") <> """", ""有縮圖"", ""無縮圖"")"),"無縮圖") -> 無縮圖
A65: 舞々 | C65: E09,E10 | D65: E09,E10 | F65: 音聲作品，日本 | G65: 東方Project / Touhou Project | H65: 一般 | I65: 二創 | J65: 💠CD 300元 💠農曆新年限量版套裝 1000元 💠舞々 毛巾 600元 💠眼鏡清潔布 150元 💠摩理沙 cosplay寫真集 600元 💠mini AL BUM 600元 💠B2尺寸 掛軸 900元 💠舞々 應援棒 900元 💠A4透明資料夾 150元 💠鍚徽章 150元 | L65: TRUE | M65: TRUE | N65: FALSE | O65: TRUE | Q65: {=IFERROR(INDEX('印量調查區'!G:G, MATCH(A65, '印量調查區'!A:A, 0)), "")} | V65: https://x.com/mai_nishijima | Z65: https://mai-mai.fanbox.cc/ | AD65: https://www.instagram.com/nishijima.maimai | AE65: https://www.youtube.com/channel/UChFLyijIQqVo513xP2vSn_w | AJ65: https://nishijimamai327.wixsite.com/-site | AK65: https://linktr.ee/nishijimamaimai | AN65: https://x.com/mai_nishijima/status/2016842739330273300?s=20 | AQ65: =IFERROR(__xludf.DUMMYFUNCTION("IF(IFERROR(VLOOKUP(A65, IMPORTRANGE(""https://docs.google.com/spreadsheets/d/1eazy315Oas8TkAoTsdzUl6gNf3VsnwZeSo-bRfkZzOs"", ""工作表1!A:B""), 2, FALSE), """") <> """", ""有縮圖"", ""無縮圖"")"),"無縮圖") -> 無縮圖
A66: OTAKU JAZZ COLONY | C66: E16 | D66: D40 | F66: 音響作品 | G66: 東方Project / Touhou Project | H66: 一般 | I66: 二創 | J66: C107新專輯 | L66: TRUE | M66: TRUE | N66: FALSE | O66: TRUE | Q66: {=IFERROR(INDEX('印量調查區'!G:G, MATCH(A66, '印量調查區'!A:A, 0)), "")} | V66: https://x.com/ota_colo | AE66: https://www.youtube.com/@OTA_COLO | AL66: https://otacolo.booth.pm/ | AN66: https://x.com/ota_colo/status/2018887110141604090?s=46&t=_iG90UUpIGYkYFDk5jW9Ig | AQ66: =IFERROR(__xludf.DUMMYFUNCTION("IF(IFERROR(VLOOKUP(A66, IMPORTRANGE(""https://docs.google.com/spreadsheets/d/1eazy315Oas8TkAoTsdzUl6gNf3VsnwZeSo-bRfkZzOs"", ""工作表1!A:B""), 2, FALSE), """") <> """", ""有縮圖"", ""無縮圖"")"),"無縮圖") -> 無縮圖
A67: Re:Volte | D67: D39 | E67: E11,E12 | F67: 音響作品，日本 | G67: 東方Project / Touhou Project | I67: 二創 | L67: TRUE | M67: TRUE | N67: TRUE | O67: TRUE | Q67: {=IFERROR(INDEX('印量調查區'!G:G, MATCH(A67, '印量調查區'!A:A, 0)), "")} | V67: https://x.com/ravy_revolte | AJ67: http://re-volte.net/ | AL67: https://soundcloud.com/ravy_revolte | AM67: https://x.com/saori_revolteSW/status/1994840869627990519 | AQ67: =IFERROR(__xludf.DUMMYFUNCTION("IF(IFERROR(VLOOKUP(A67, IMPORTRANGE(""https://docs.google.com/spreadsheets/d/1eazy315Oas8TkAoTsdzUl6gNf3VsnwZeSo-bRfkZzOs"", ""工作表1!A:B""), 2, FALSE), """") <> """", ""有縮圖"", ""無縮圖"")"),"無縮圖") -> 無縮圖
A68: 博麗神社社務所 | D68: E01 | E68: E01 | F68: 場次主辦，日本 | G68: 東方Project / Touhou Project | I68: 二創 | J68: 例大祭in台灣的宣傳以及過去的周邊產品 | L68: TRUE | M68: TRUE | N68: TRUE | O68: TRUE | Q68: {=IFERROR(INDEX('印量調查區'!G:G, MATCH(A68, '印量調查區'!A:A, 0)), "")} | V68: https://x.com/hakureijinjyas | AJ68: https://reitaisai.com/ | AN68: https://www.facebook.com/permalink.php?story_fbid=pfbid0N6yRomzYmR5DeUuFZPBcBdM4T2K9muEqHQw2Jj2xxhRE8aFt6YTXCTepuSWkaqU3l&id=61559627625110 | AQ68: =IFERROR(__xludf.DUMMYFUNCTION("IF(IFERROR(VLOOKUP(A68, IMPORTRANGE(""https://docs.google.com/spreadsheets/d/1eazy315Oas8TkAoTsdzUl6gNf3VsnwZeSo-bRfkZzOs"", ""工作表1!A:B""), 2, FALSE), """") <> """", ""有縮圖"", ""無縮圖"")"),"無縮圖") -> 無縮圖
A69: 林檎林 | B69: 𝐑𝐢𝐧𝐠𝐨𝐑𝐢𝐧 | C69: E05,E06 | D69: D44 | F69: 繪師 | G69: 東方Project / Touhou Project | H69: 一般 | I69: 二創 | J69: 💠同人誌 200元 💠壓克力色紙 150元 💠T-shirt 400元 💠貼紙包 100元 💠既刊 150元 💠壓克力吊飾 150元 | L69: TRUE | M69: TRUE | N69: TRUE | O69: TRUE | Q69: {=IFERROR(INDEX('印量調查區'!G:G, MATCH(A69, '印量調查區'!A:A, 0)), "")} | R69: https://www.facebook.com/Ringorin.art/ | AD69: https://www.instagram.com/ringorin.art/ | AN69: https://www.facebook.com/share/p/1CiXoMmRmB/ | AQ69: =IFERROR(__xludf.DUMMYFUNCTION("IF(IFERROR(VLOOKUP(A69, IMPORTRANGE(""https://docs.google.com/spreadsheets/d/1eazy315Oas8TkAoTsdzUl6gNf3VsnwZeSo-bRfkZzOs"", ""工作表1!A:B""), 2, FALSE), """") <> """", ""有縮圖"", ""無縮圖"")"),"無縮圖") -> 無縮圖
A70: 蓬萊賦形所&戀石同盟 | C70: E17 | D70: D43 | F70: 繪師 | G70: 東方Project / Touhou Project | H70: 一般 | I70: 二創 | J70: 💠1/6東方project MJD 1700/隻 | L70: TRUE | M70: TRUE | N70: FALSE | O70: FALSE | P70: 高 | Q70: {=IFERROR(INDEX('印量調查區'!G:G, MATCH(A70, '印量調查區'!A:A, 0)), "")} | R70: https://www.facebook.com/Dr.Sponga/ | S70: https://www.facebook.com/profile.php?id=61581887180431 | AM70: https://www.facebook.com/share/p/181SAXaqRq/ | AN70: https://www.facebook.com/share/p/18Jw2J8GBM/ | AQ70: =IFERROR(__xludf.DUMMYFUNCTION("IF(IFERROR(VLOOKUP(A70, IMPORTRANGE(""https://docs.google.com/spreadsheets/d/1eazy315Oas8TkAoTsdzUl6gNf3VsnwZeSo-bRfkZzOs"", ""工作表1!A:B""), 2, FALSE), """") <> """", ""有縮圖"", ""無縮圖"")"),"無縮圖") -> 無縮圖
A71: あかぎれ堂 | B71: 逢魔 | C71: E02 | D71: E21 | F71: 繪師 | G71: 東方Project / Touhou Project | H71: R18 | I71: 二創 | J71: FF46新刊早苗本 C107新刊幽々子本 C107新刊阿露本 抱枕三款 色紙四款（拍賣）手繪色紙 | L71: TRUE | M71: TRUE | N71: FALSE | O71: FALSE | P71: 高 | Q71: {=IFERROR(INDEX('印量調查區'!G:G, MATCH(A71, '印量調查區'!A:A, 0)), "")} | V71: https://x.com/touma00 | Y71: https://www.pixiv.net/users/23239 | Z71: https://touma00.fanbox.cc/ | AC71: https://skeb.jp/@touma00 | AM71: https://x.com/touma00/status/2017887346214236272?s=20 | AN71: https://x.com/touma00/status/2018891581068341716 | AQ71: =IFERROR(__xludf.DUMMYFUNCTION("IF(IFERROR(VLOOKUP(A71, IMPORTRANGE(""https://docs.google.com/spreadsheets/d/1eazy315Oas8TkAoTsdzUl6gNf3VsnwZeSo-bRfkZzOs"", ""工作表1!A:B""), 2, FALSE), """") <> """", ""有縮圖"", ""無縮圖"")"),"無縮圖") -> 無縮圖
A72: 二色幽紫蝶 | C72: E03,E04 | D72: D42 | F72: 繪師，中國 | G72: 東方Project / Touhou Project | I72: 二創 | J72: 壓克力立牌、色紙、壓克力吊飾、徽章、掛軸、撲克牌、塔羅牌、FUMO布布萌、睿智小人、吊飾 | L72: TRUE | M72: TRUE | N72: FALSE | O72: FALSE | Q72: {=IFERROR(INDEX('印量調查區'!G:G, MATCH(A72, '印量調查區'!A:A, 0)), "")} | V72: https://x.com/youziKK | AL72: https://space.bilibili.com/86865890 | AM72: https://drive.google.com/file/d/1PKMSpNRNKraeRF2YvUwfds-f4cM79A8T/view?usp=drive_link | AN72: https://drive.google.com/file/d/1M8te36f3szBgeP-xw1igjk1cZZEmmJ8U/view?usp=sharing https://drive.google.com/file/d/1m1EzJTPqLqRmrQEvN6QfOx4C-IKpXtOs/view?usp=sharing https://drive.google.com/file/d/1gIEGzUBlxr0FlqPkf1GCtm8ld60_4Bbf/view?usp=sharing https://drive.google.com/file/d/106VyNGNMPo9_6oXO168cbxDuH9NV0ndV/view?usp=drive_link https://drive.google.com/file/d/14I3gSh92XmHh1My9alBZcOPTJCJO6qdk/view?usp=drive_link https://drive.google.com/file/d/1Wn5Lkm-Nihr9Ir1iA6ydMNarshAGT9Pj/view?usp=sharing https://drive.google.com/file/d/1_aPLcdtLCKET0s7DcmZRuwmdmbltnzOB/view?usp=sharing | AQ72: =IFERROR(__xludf.DUMMYFUNCTION("IF(IFERROR(VLOOKUP(A72, IMPORTRANGE(""https://docs.google.com/spreadsheets/d/1eazy315Oas8TkAoTsdzUl6gNf3VsnwZeSo-bRfkZzOs"", ""工作表1!A:B""), 2, FALSE), """") <> """", ""有縮圖"", ""無縮圖"")"),"有縮圖") -> 有縮圖
A73: 梅之小町 | B73: 山中梅 | D73: D36 | F73: 繪師，日本 | G73: 東方Project / Touhou Project | I73: 二創 | J73: 💠同人誌 全彩插畫集 夢紡戲 300元 💠立牌 300-500元 💠滑鼠墊 600元 | L73: TRUE | M73: TRUE | N73: FALSE | O73: FALSE | P73: 高 | Q73: {=IFERROR(INDEX('印量調查區'!G:G, MATCH(A73, '印量調查區'!A:A, 0)), "")} | V73: https://x.com/UMEDAYO_sekaume | Y73: https://www.pixiv.net/users/12873498 | AQ73: =IFERROR(__xludf.DUMMYFUNCTION("IF(IFERROR(VLOOKUP(A73, IMPORTRANGE(""https://docs.google.com/spreadsheets/d/1eazy315Oas8TkAoTsdzUl6gNf3VsnwZeSo-bRfkZzOs"", ""工作表1!A:B""), 2, FALSE), """") <> """", ""有縮圖"", ""無縮圖"")"),"無縮圖") -> 無縮圖
A74: ぱいそんきっど | D74: E17,E18 | E74: E17,E18 | F74: 繪師，日本 | G74: 東方Project / Touhou Project | I74: 二創 | L74: TRUE | M74: TRUE | N74: FALSE | O74: FALSE | Q74: {=IFERROR(INDEX('印量調查區'!G:G, MATCH(A74, '印量調查區'!A:A, 0)), "")} | R74: https://www.facebook.com/profile.php?id=100043010862787&ref=_ig_profile_ac | V74: https://x.com/pythonkid2013 | Y74: https://www.pixiv.net/users/80703519 | AD74: https://www.instagram.com/pythonkid2 | AJ74: http://pythonkid.blog.fc2.com/ | AQ74: =IFERROR(__xludf.DUMMYFUNCTION("IF(IFERROR(VLOOKUP(A74, IMPORTRANGE(""https://docs.google.com/spreadsheets/d/1eazy315Oas8TkAoTsdzUl6gNf3VsnwZeSo-bRfkZzOs"", ""工作表1!A:B""), 2, FALSE), """") <> """", ""有縮圖"", ""無縮圖"")"),"無縮圖") -> 無縮圖
A75: ぱいんとさいず | D75: E19,E20 | E75: E19,E20 | F75: 繪師，日本 | G75: 東方Project / Touhou Project | I75: 二創 | L75: TRUE | M75: TRUE | N75: FALSE | O75: TRUE | Q75: {=IFERROR(INDEX('印量調查區'!G:G, MATCH(A75, '印量調查區'!A:A, 0)), "")} | V75: https://x.com/pintsize_tks | Y75: https://www.pixiv.net/users/473403 | AQ75: =IFERROR(__xludf.DUMMYFUNCTION("IF(IFERROR(VLOOKUP(A75, IMPORTRANGE(""https://docs.google.com/spreadsheets/d/1eazy315Oas8TkAoTsdzUl6gNf3VsnwZeSo-bRfkZzOs"", ""工作表1!A:B""), 2, FALSE), """") <> """", ""有縮圖"", ""無縮圖"")"),"無縮圖") -> 無縮圖
A76: 夜大大工作室 | D76: D37 | E76: E06 | F76: Coser | G76: 東方Project / Touhou Project | I76: 二創 | L76: TRUE | M76: TRUE | N76: FALSE | O76: FALSE | Q76: {=IFERROR(INDEX('印量調查區'!G:G, MATCH(A76, '印量調查區'!A:A, 0)), "")} | R76: https://www.facebook.com/zephyryr | V76: https://twitter.com/zephyryryr | X76: https://www.plurk.com/zephyryr | Y76: https://www.pixiv.net/users/2336843/artworks | AQ76: =IFERROR(__xludf.DUMMYFUNCTION("IF(IFERROR(VLOOKUP(A76, IMPORTRANGE(""https://docs.google.com/spreadsheets/d/1eazy315Oas8TkAoTsdzUl6gNf3VsnwZeSo-bRfkZzOs"", ""工作表1!A:B""), 2, FALSE), """") <> """", ""有縮圖"", ""無縮圖"")"),"無縮圖") -> 無縮圖
A77: 洩矢米米米 | D77: D38 | G77: 東方Project / Touhou Project | I77: 二創 | L77: TRUE | M77: TRUE | N77: FALSE | O77: TRUE | Q77: {=IFERROR(INDEX('印量調查區'!G:G, MATCH(A77, '印量調查區'!A:A, 0)), "")} | R77: https://www.facebook.com/profile.php?id=61555937236894 | AQ77: =IFERROR(__xludf.DUMMYFUNCTION("IF(IFERROR(VLOOKUP(A77, IMPORTRANGE(""https://docs.google.com/spreadsheets/d/1eazy315Oas8TkAoTsdzUl6gNf3VsnwZeSo-bRfkZzOs"", ""工作表1!A:B""), 2, FALSE), """") <> """", ""有縮圖"", ""無縮圖"")"),"無縮圖") -> 無縮圖
A78: Reverse Noise | C78: E01 | D78: E22 | F78: 繪師，日本 | G78: 東方Project / Touhou Project | H78: R18 | I78: 二創 | J78: 💠同人誌 150元 💠壓克力色紙 350元 💠掛軸 400元 💠色紙拍賣 💠斜背包 | L78: TRUE | M78: TRUE | N78: FALSE | O78: TRUE | Q78: {=IFERROR(INDEX('印量調查區'!G:G, MATCH(A78, '印量調查區'!A:A, 0)), "")} | V78: https://twitter.com/yamu_RN | X78: https://www.plurk.com/yamu_RN | Y78: https://www.pixiv.net/member.php?id=23621 | Z78: https://yamu-rn.fanbox.cc/ | AB78: https://clusters.tw/profile/72AD1D07-168F-44DC-BC2F-0396E692BDD3/works | AC78: https://skeb.jp/@yamu_RN | AN78: https://www.plurk.com/p/3i8zfmbicb | AQ78: =IFERROR(__xludf.DUMMYFUNCTION("IF(IFERROR(VLOOKUP(A78, IMPORTRANGE(""https://docs.google.com/spreadsheets/d/1eazy315Oas8TkAoTsdzUl6gNf3VsnwZeSo-bRfkZzOs"", ""工作表1!A:B""), 2, FALSE), """") <> """", ""有縮圖"", ""無縮圖"")"),"無縮圖") -> 無縮圖
A79: 悶KID | D79: E13,E14 | E79: E13,E14 | F79: 同人社團，日本 | G79: 東方Project / Touhou Project，蔚藍檔案 / Blue Archive / ブルーアーカイブ | I79: 二創 | L79: TRUE | M79: TRUE | N79: FALSE | O79: TRUE | Q79: {=IFERROR(INDEX('印量調查區'!G:G, MATCH(A79, '印量調查區'!A:A, 0)), "")} | V79: https://x.com/SunameriDrill | AD79: https://www.instagram.com/sunameridrill/ | AK79: https://lit.link/zh-tw/sunameridrill | AQ79: =IFERROR(__xludf.DUMMYFUNCTION("IF(IFERROR(VLOOKUP(A79, IMPORTRANGE(""https://docs.google.com/spreadsheets/d/1eazy315Oas8TkAoTsdzUl6gNf3VsnwZeSo-bRfkZzOs"", ""工作表1!A:B""), 2, FALSE), """") <> """", ""有縮圖"", ""無縮圖"")"),"無縮圖") -> 無縮圖
A80: 少女爆肝中 | C80: E33 | D80: C28 | F80: 繪師 | G80: 東方Project / Touhou Project，maimai，音樂遊戲 | H80: 一般 | I80: 二創 | J80: Acid 或百合咲角色套組 650元、12公分立牌 350元、卡套 250元、吊飾 150元、紙袋、壓克力彩窗御守 150元、貼紙包 100元、東方同人誌既刊 200元、吊飾 150元、紙袋、貼紙、東方既刊套組 600元、掛軸 600元、芙蘭立牌 350元、全都要套組 1550元、T-Shirt 600元、御守150元、貼紙包 120元 各類音遊機台吊飾、滑蓋吊飾、Maimai系列、便利貼 50元、錢包 | K80: 音遊列島 | L80: TRUE | M80: TRUE | N80: TRUE | O80: TRUE | Q80: {=IFERROR(INDEX('印量調查區'!G:G, MATCH(A80, '印量調查區'!A:A, 0)), "")} | V80: https://x.com/MoonDesuuu?fbclid=PAZXh0bgNhZW0CMTEAc3J0YwZhcHBfaWQMMjU2MjgxMDQwNTU4AAGnZN8uvAYqBYwYp0_9Z1n3Dw_HVo_HhsoqRYmzOStpXmzvo33HpQCAleK1KWA_aem_qSPqgvLp7vc1R3Wu0vysfQ | AD80: https://www.instagram.com/_moon.desu_/ | AN80: https://www.facebook.com/XMoonX2/posts/pfbid0h1LGutVpzM6r3jVBrVpuNwkEA8JZCoRE4k6ETqj8br3HxZ6Q2k5kHB5eRT5GmPZ4l https://www.facebook.com/yuenying.luk.1/posts/pfbid02A51f91W3e7w3eHuck9C4nDjrTW9xgPGWqeThsCenkBKPLSXNrGe5WhggYpPFgjnYl | AQ80: =IFERROR(__xludf.DUMMYFUNCTION("IF(IFERROR(VLOOKUP(A80, IMPORTRANGE(""https://docs.google.com/spreadsheets/d/1eazy315Oas8TkAoTsdzUl6gNf3VsnwZeSo-bRfkZzOs"", ""工作表1!A:B""), 2, FALSE), """") <> """", ""有縮圖"", ""無縮圖"")"),"無縮圖") -> 無縮圖
A81: 田書坊 | D81: E04 | E81: E04 | F81: 繪師 | G81: 東方Project / Touhou Project、蔚藍檔案 / Blue Archive / ブルーアーカイブ | H81: 一般 | I81: 二創 | J81: 同人誌 200-300元 | L81: TRUE | M81: TRUE | N81: FALSE | O81: TRUE | Q81: {=IFERROR(INDEX('印量調查區'!G:G, MATCH(A81, '印量調查區'!A:A, 0)), "")} | R81: https://www.facebook.com/SatoriMelon/ | V81: TWITTER | X81: https://www.plurk.com/gameboy931024 | Y81: PIXIV | AN81: https://www.facebook.com/SatoriMelon/posts/pfbid0ACmPv9i1JpE13xvz21BXtx45fVdtEPKQ8f2qM4rAHg7FtvJCEA8nepkoBwY9RiBAl | AQ81: =IFERROR(__xludf.DUMMYFUNCTION("IF(IFERROR(VLOOKUP(A81, IMPORTRANGE(""https://docs.google.com/spreadsheets/d/1eazy315Oas8TkAoTsdzUl6gNf3VsnwZeSo-bRfkZzOs"", ""工作表1!A:B""), 2, FALSE), """") <> """", ""有縮圖"", ""無縮圖"")"),"無縮圖") -> 無縮圖
A82: 規尬的地下競馬場 | B82: 規尬 | D82: T13,T14 | E82: T13,T14 | F82: 繪師 | G82: 金牌得主、曠野冰原 | H82: 一般 | I82: 二創 | J82: 💠同人誌【Spin with You 光祈光 畫冊】300元 💠旋轉立牌 350元 💠書籤 100元 💠光柵卡 100元 💠生日票根 200元 💠流沙磚 500元 💠相框 250元 💠徽章 100元 💠吊飾 150元 💠鹿本玲立牌 300元 💠小立牌 150元 💠小吊飾 150元 💠巴黎冰雪大皇宮掛軸 400元 💠功夫水仙掛軸 450元 💠光祈壓克力磚 250元 💠破曉 暮色 掛軸 350元 💠雷射票 300元 💠壓克力色紙 300元 💠壓克力立牌 750元 💠同人誌 光祈光畫冊 350元 💠實依實人魚公主串串吊飾 250元 | L82: TRUE | M82: TRUE | N82: FALSE | O82: TRUE | Q82: {=IFERROR(INDEX('印量調查區'!G:G, MATCH(A82, '印量調查區'!A:A, 0)), "")} | R82: https://www.facebook.com/UpClassGuaga | AN82: https://www.facebook.com/UpClassGuaga/posts/pfbid02ZR6p8tawDwCdE8NPkybkhD8zK4fX8NKGiQcMD8sFWardNSYJUjdr54tbQmsX8zqTl https://www.facebook.com/share/p/185kNgQNVL/ | AO82: https://www.myacg.com.tw/seller_market.php?seller=564376 | AQ82: =IFERROR(__xludf.DUMMYFUNCTION("IF(IFERROR(VLOOKUP(A82, IMPORTRANGE(""https://docs.google.com/spreadsheets/d/1eazy315Oas8TkAoTsdzUl6gNf3VsnwZeSo-bRfkZzOs"", ""工作表1!A:B""), 2, FALSE), """") <> """", ""有縮圖"", ""無縮圖"")"),"無縮圖") -> 無縮圖
A83: 鴨子塗鴉 | B83: 王家豪 | C83: T03,T04 | D83: T28 | F83: 繪師 | G83: 前橋魔女、MyGO!!!!! | H83: 一般 | I83: 二創 | J83: 同人誌 200元-300元 既刊 200元-300元 MyGO!!!!!吊飾 100元 | K83: 百合 | L83: TRUE | M83: TRUE | N83: FALSE | O83: TRUE | Q83: {=IFERROR(INDEX('印量調查區'!G:G, MATCH(A83, '印量調查區'!A:A, 0)), "")} | R83: https://www.facebook.com/MrFBA2 | V83: https://x.com/MrFBA2 | X83: https://www.plurk.com/sw5231715 | Y83: https://www.pixiv.net/users/38136786 | AM83: https://www.facebook.com/MrFBA2/posts/pfbid0ngNDLMZrRTRFT3fszyru9zcYFm76o5pJytTw6C6pKbdauoZtrMLR5TbBE8gskfT9l https://www.plurk.com/p/3i80248ihi | AN83: https://www.facebook.com/photo/?fbid=1472905657752256&set=pcb.1472909947751827 | AQ83: =IFERROR(__xludf.DUMMYFUNCTION("IF(IFERROR(VLOOKUP(A83, IMPORTRANGE(""https://docs.google.com/spreadsheets/d/1eazy315Oas8TkAoTsdzUl6gNf3VsnwZeSo-bRfkZzOs"", ""工作表1!A:B""), 2, FALSE), """") <> """", ""有縮圖"", ""無縮圖"")"),"有縮圖") -> 有縮圖
A84: 西谷雷 | C84: D15,D16 [寄] | F84: 繪師 | G84: 型月 | H84: R15 | I84: 二創 | J84: 小櫻壓克力立牌 250元 | L84: TRUE | M84: TRUE | N84: TRUE | O84: TRUE | R84: https://www.facebook.com/xi.gu.lei | V84: https://twitter.com/shigure_43 | Y84: https://www.pixiv.net/users/32629835?fbclid=IwY2xjawPu7iZleHRuA2FlbQIxMABicmlkETFzbG5yYWwzbmtka3V5ZVlic3J0YwZhcHBfaWQQMjIyMDM5MTc4ODIwMDg5MgABHiTK5tJQgB89yYwblrCElaYtJ3TFiyMShPq3V-vM_EBpC_4NBENRCt6qzd06_aem_nZ5Re6txwQ1rdG91ORmLRA | AN84: https://www.facebook.com/xi.gu.lei/posts/pfbid02b1wDcT4n6GAo6GBC51Cz5FCBsbXHnnYburq4B8DuNrfKp92wgokv5UVPs9nnxu5ol | AQ84: =IFERROR(__xludf.DUMMYFUNCTION("IF(IFERROR(VLOOKUP(A84, IMPORTRANGE(""https://docs.google.com/spreadsheets/d/1eazy315Oas8TkAoTsdzUl6gNf3VsnwZeSo-bRfkZzOs"", ""工作表1!A:B""), 2, FALSE), """") <> """", ""有縮圖"", ""無縮圖"")"),"無縮圖") -> 無縮圖
A85: 箱庭交響曲 | C85: D01,D02 | D85: D01 | F85: 繪師 | G85: 星穹鐵道 | H85: 一般, R18 | I85: 二創 | J85: 💠新刊 - Starry Vintage A5／12P／全彩 💠A4資料夾 - （被流螢拉出門的）周末 💠A6明信片 - 古著風 💠雙面壓克力立牌 💠滑鼠墊_星核獵手的周末 💠抱枕套_致救世主的報答 💠合拍透卡 | L85: TRUE | M85: TRUE | N85: FALSE | O85: TRUE | Q85: {=IFERROR(INDEX('印量調查區'!G:G, MATCH(A85, '印量調查區'!A:A, 0)), "")} | R85: https://www.facebook.com/hknwsymphony/ | AD85: https://www.instagram.com/hknwsymphony/ | AN85: https://www.facebook.com/share/p/1KbymGtK6K/ https://x.com/kh3ovo/status/2018706505214701594 | AO85: https://www.myacg.com.tw/goods_detail.php?gid=6774625 | AQ85: =IFERROR(__xludf.DUMMYFUNCTION("IF(IFERROR(VLOOKUP(A85, IMPORTRANGE(""https://docs.google.com/spreadsheets/d/1eazy315Oas8TkAoTsdzUl6gNf3VsnwZeSo-bRfkZzOs"", ""工作表1!A:B""), 2, FALSE), """") <> """", ""有縮圖"", ""無縮圖"")"),"無縮圖") -> 無縮圖
A86: 貓窩沒有貓 | B86: Mewo Cat | C86: I38 | F86: 繪師 | G86: 星空のメモリア | H86: R18 | I86: 二創 | J86: R18插畫集 $350 壓克力立牌花嫁款&制服款 $300/個 女僕メア抱枕套 $2000 贈品 | L86: TRUE | M86: TRUE | N86: TRUE | O86: TRUE | Q86: {=IFERROR(INDEX('印量調查區'!G:G, MATCH(A86, '印量調查區'!A:A, 0)), "")} | R86: https://www.facebook.com/mewo.cat.78413/ | V86: https://x.com/woodhxx123 | Y86: https://www.pixiv.net/users/7479841 | AN86: https://www.facebook.com/mewo.cat.78413/posts/pfbid023epj75j1vGikj58NnTChwsBt52AwcDjYASwpaW9QvZoptf9UvHUSenmVKC6TFmgfl | AQ86: =IFERROR(__xludf.DUMMYFUNCTION("IF(IFERROR(VLOOKUP(A86, IMPORTRANGE(""https://docs.google.com/spreadsheets/d/1eazy315Oas8TkAoTsdzUl6gNf3VsnwZeSo-bRfkZzOs"", ""工作表1!A:B""), 2, FALSE), """") <> """", ""有縮圖"", ""無縮圖"")"),"有縮圖") -> 有縮圖
A87: 失去明天(あしたをなくす) | B87: りとら | C87: I26 | D87: I26 | E87: C11,C12 [寄] | F87: 繪師，日本 | G87: 星塔旅人 霧語 | H87: R18 | I87: 原創, 二創 | J87: 同人誌 新刊①原創 200元 新刊②原創 200元 新刊③星塔旅人 霧語（会場限定）100元 既刊（原神/胡桃、蔚藍檔案/彌香、原創）200元 簽繪板接受請求 (全彩2500元) 簽繪板（2500元) 簽繪板競標（蔚藍檔案/1000元～) 海報競標 | L87: TRUE | M87: TRUE | N87: TRUE | O87: TRUE | Q87: {=IFERROR(INDEX('印量調查區'!G:G, MATCH(A87, '印量調查區'!A:A, 0)), "")} | R87: https://www.facebook.com/profile.php?id=61559967600600 | T87: https://bsky.app/profile/psysoda.bsky.social | V87: https://twitter.com/psy_soda | X87: https://www.plurk.com/psy_soda | Y87: https://www.pixiv.net/users/6159628 | AD87: https://www.instagram.com/li_tola_16g/?fbclid=IwY2xjawIKgPdleHRuA2FlbQIxMAABHREURvTq0uPAVYpjVGHi38PQsbP545h10cCmvi77TIBkVle5AFK9C9QZOQ_aem_4IaJSdA4DKileOJ0AQURSg | AL87: https://www.doujin.com.tw/groups/info/8613 | AM87: https://www.plurk.com/p/3i5qjvfb5v https://www.plurk.com/p/3i7lq4k471 | AN87: https://www.plurk.com/p/3i9ptrzji1 | AQ87: =IFERROR(__xludf.DUMMYFUNCTION("IF(IFERROR(VLOOKUP(A87, IMPORTRANGE(""https://docs.google.com/spreadsheets/d/1eazy315Oas8TkAoTsdzUl6gNf3VsnwZeSo-bRfkZzOs"", ""工作表1!A:B""), 2, FALSE), """") <> """", ""有縮圖"", ""無縮圖"")"),"有縮圖") -> 有縮圖
A88: 月球牡蠣 | E88: B08 [寄] | F88: 繪師 | G88: 活俠傳 | H88: 一般 | I88: 二創 | J88: 壓克力立牌 400元、壓克力吊飾 100元、既刊 200元 | L88: TRUE | M88: TRUE | N88: TRUE | O88: TRUE | R88: https://www.facebook.com/share/16Dri7ocKB/ | V88: https://x.com/moonoyster0904 | Y88: https://www.pixiv.net/en/users/69954367 | AD88: https://www.instagram.com/qikai0904/?next=%2F | AE88: https://youtube.com/channel/UC6KxBh7fSH3T3QU3640joCA?si=xSq3Nwk_xCtmS2dc | AK88: https://potofu.me/qikai | AN88: https://x.com/moonoyster0904/status/2018628131129802937 | AQ88: =IFERROR(__xludf.DUMMYFUNCTION("IF(IFERROR(VLOOKUP(A88, IMPORTRANGE(""https://docs.google.com/spreadsheets/d/1eazy315Oas8TkAoTsdzUl6gNf3VsnwZeSo-bRfkZzOs"", ""工作表1!A:B""), 2, FALSE), """") <> """", ""有縮圖"", ""無縮圖"")"),"無縮圖") -> 無縮圖
A89: 桑尤姆的部屋 | B89: 桑尤姆 | C89: C03 | D89: C04 | F89: 繪師 | G89: 活俠傳 | H89: R18 | I89: 二創 | J89: 💠同人誌【夜色鈴裳】250元 💠春聯4款 50元/款 合購價150元 💠貼紙2款 100元/款 合購價150元 💠胸章2款 100元/款 合購價150元 | L89: TRUE | M89: TRUE | N89: TRUE | O89: TRUE | Q89: {=IFERROR(INDEX('印量調查區'!G:G, MATCH(A89, '印量調查區'!A:A, 0)), "")} | R89: https://www.facebook.com/er913187750/ | V89: https://twitter.com/kino_na | X89: https://www.plurk.com/er913187750?offset=1620213582 | Y89: https://www.pixiv.net/users/92181 | Z89: https://www.twitch.tv/sum_91318 | AD89: https://www.instagram.com/youmusang/ | AH89: https://discord.gg/TRK8AsenZ2 | AI89: https://home.gamer.com.tw/homeindex.php?owner=er913187750 | AM89: https://www.facebook.com/sang.you.mu/posts/pfbid0LC7BzC55D5fF3KrzC91fkTXKir5JK9d3G54ekBU2U91bUo1PGUPTwf1mj7Fs8P5Hl | AN89: https://www.plurk.com/p/3i8z1ihhmx | AQ89: =IFERROR(__xludf.DUMMYFUNCTION("IF(IFERROR(VLOOKUP(A89, IMPORTRANGE(""https://docs.google.com/spreadsheets/d/1eazy315Oas8TkAoTsdzUl6gNf3VsnwZeSo-bRfkZzOs"", ""工作表1!A:B""), 2, FALSE), """") <> """", ""有縮圖"", ""無縮圖"")"),"無縮圖") -> 無縮圖
A90: EPO’s Art | D90: M44 [寄] | E90: B09,B10 | F90: 繪師 | G90: 活俠傳 | H90: 一般 | I90: 二創 | J90: 同人誌《我把大師兄變成狗了》170元 | L90: TRUE | M90: TRUE | N90: FALSE | O90: TRUE | P90: 高 | Q90: {=IFERROR(INDEX('印量調查區'!G:G, MATCH(A90, '印量調查區'!A:A, 0)), "")} | R90: https://www.facebook.com/0EPO0 | V90: https://twitter.com/EPO_0 | Y90: https://www.pixiv.net/users/1237464 | AD90: https://www.instagram.com/0epo0/ | AE90: https://www.youtube.com/channel/UCNZOuBt0RFkJV0kC_fqfoGw | AF90: https://www.twitch.tv/epo_live | AJ90: https://www.epoartwork.com/ | AM90: https://www.facebook.com/erythropoietin.rbc/posts/pfbid02gWFPgQwm8BSu6bRcAATLDBKqkeULmuH2RjdgbadidEVoPDKwScaRkfszuMyymdVkl?__cft__[0]=AZUUwJtnQczY7yaF9XKBATGWZWnwl5cCbnYE1h8Zcwz8bfx3mhneJTKoze8DKPcEiI2-8jJGrj4S7HfE3SM7fz1Q2H4NHH5i5BPp7KhKmLvnvGq8wW2X5NztoeQUq50NyCZrMf3uGLQMj9dEJpIT80g4ZSQTIFh6NdDEwuUTM5N3JQ&__tn__=%2CO%2CP-R | AN90: https://www.facebook.com/share/p/1Ag6ztf1wz/ | AQ90: =IFERROR(__xludf.DUMMYFUNCTION("IF(IFERROR(VLOOKUP(A90, IMPORTRANGE(""https://docs.google.com/spreadsheets/d/1eazy315Oas8TkAoTsdzUl6gNf3VsnwZeSo-bRfkZzOs"", ""工作表1!A:B""), 2, FALSE), """") <> """", ""有縮圖"", ""無縮圖"")"),"無縮圖") -> 無縮圖
A91: Shadow sensei | B91: 雪豆先生 | C91: C01,C02 | F91: 繪師 | G91: 活俠傳、蔚藍檔案 | H91: R18 | I91: 二創 | J91: 簽繪板 | L91: TRUE | M91: TRUE | N91: TRUE | O91: TRUE | Q91: {=IFERROR(INDEX('印量調查區'!G:G, MATCH(A91, '印量調查區'!A:A, 0)), "")} | V91: https://x.com/the29657036 | Y91: https://www.pixiv.net/users/3423339 | AM91: https://x.com/the29657036/status/2017295788817453394?s=20 | AN91: https://x.com/the29657036/status/2017295788817453394?s=20 | AO91: https://www.myacg.com.tw/goods_detail.php?gid=6777956 | AQ91: =IFERROR(__xludf.DUMMYFUNCTION("IF(IFERROR(VLOOKUP(A91, IMPORTRANGE(""https://docs.google.com/spreadsheets/d/1eazy315Oas8TkAoTsdzUl6gNf3VsnwZeSo-bRfkZzOs"", ""工作表1!A:B""), 2, FALSE), """") <> """", ""有縮圖"", ""無縮圖"")"),"無縮圖") -> 無縮圖
A92: 企鵝w | B92: 企鵝w | E92: B08 | F92: 繪師 | G92: 活俠傳、戀與深空 | H92: 一般 | I92: 二創 | J92: 💠 活俠傳 唐門斗方春聯組100元 唐門紅包袋組100元 小師妹令牌吊飾150元 唐門卡套100元 雙閃壓克力色紙150元 小師妹/雲裳甜品勺80元 💠 戀與深空-黎深 黎神票根吊飾100元 薄荷巧克力棒80元 雪花/梨子甜品勺80元 紓壓按鍵吊飾80元 雙閃壓克力色紙150元 小雪人卡套+小卡120元 馬口鐵盒100元 橢圓徽章組60元 | L92: TRUE | M92: TRUE | N92: TRUE | O92: TRUE | P92: 高 | Q92: {=IFERROR(INDEX('印量調查區'!G:G, MATCH(A92, '印量調查區'!A:A, 0)), "")} | R92: https://www.facebook.com/Penguin.w.1205 | V92: https://x.com/Penguin_w1205 | X92: https://www.plurk.com/penguin_w1205 | Y92: https://www.pixiv.net/users/24182395 | AK92: https://portaly.cc/Penguin_w | AL92: https://portaly.cc/jasminum.sambac_0905 | AM92: https://www.facebook.com/share/r/1Fvm4wVBwC/ | AN92: https://www.facebook.com/share/p/1F6Ld1i3uf/?mibextid=wwXIfr | AQ92: =IFERROR(__xludf.DUMMYFUNCTION("IF(IFERROR(VLOOKUP(A92, IMPORTRANGE(""https://docs.google.com/spreadsheets/d/1eazy315Oas8TkAoTsdzUl6gNf3VsnwZeSo-bRfkZzOs"", ""工作表1!A:B""), 2, FALSE), """") <> """", ""有縮圖"", ""無縮圖"")"),"有縮圖") -> 有縮圖
A93: 倫語project | B93: ASLE | D93: V23,V24 | E93: V21,V22 | F93: 繪師 | G93: 約會大作戰 | H93: R18, R15 | I93: 二創 | J93: 同人誌 150元、桌曆 200元、光柵卡、明信片、桌墊 600元、大紙袋 150元、掛軸 500元、吊飾、新年小套組 400元、經典中套組 1300元、超狂大套組 1900元、會場限定大套組 2400元 | L93: TRUE | M93: TRUE | N93: FALSE | O93: TRUE | Q93: {=IFERROR(INDEX('印量調查區'!G:G, MATCH(A93, '印量調查區'!A:A, 0)), "")} | R93: https://www.facebook.com/asleisureto | V93: https://twitter.com/asleisureto | X93: https://www.plurk.com/asleisureto | Y93: https://www.pixiv.net/users/654041 | AN93: https://www.facebook.com/asleisureto/posts/pfbid032M93vB9wHbMG8mR3aPcF57TYL67ceZPuqA426Nj3jxdFihQsPq9ZZaV5jABzL3hel | AQ93: =IFERROR(__xludf.DUMMYFUNCTION("IF(IFERROR(VLOOKUP(A93, IMPORTRANGE(""https://docs.google.com/spreadsheets/d/1eazy315Oas8TkAoTsdzUl6gNf3VsnwZeSo-bRfkZzOs"", ""工作表1!A:B""), 2, FALSE), """") <> """", ""有縮圖"", ""無縮圖"")"),"有縮圖") -> 有縮圖
A94: 鬼瞳在這欸 | B94: 鬼瞳 | C94: R17,R18 | F94: Coser | G94: 約會大作戰 | H94: R15 | I94: 二創 | J94: 單買電子檔 480$ 單書 600$ 小套組 880$(單書+隨機一張撕拉生寫真小卡+書中照片檔(載點)) 中套組 1200$(單書+隨機四張撕拉生寫真小卡+書中照片檔(含USB)) 大套組 2100$(單書+特點寫真書+七張撕拉生寫真小卡+所有精修檔(含USB)+透明A3膠片海報) 經典套組 3000$(大套組全部額外+所有手機自拍+短影片+12月狂三電子檔造型膠片海報) | L94: TRUE | M94: TRUE | N94: TRUE | O94: TRUE | P94: 高 | Q94: {=IFERROR(INDEX('印量調查區'!G:G, MATCH(A94, '印量調查區'!A:A, 0)), "")} | R94: http://www.facebook.com/OniHitomi.fanpage | V94: https://x.com/abc12692 | AD94: https://www.instagram.com/abc12692/ | AE94: https://www.youtube.com/oHitomi777 | AJ94: https://oni-hitomi.weebly.com/ | AM94: https://www.facebook.com/OniHitomi.fanpage/posts/pfbid03pD8XyJBkqpKZDGjM2FwXQgPi97EV43gnjW248YWJqUKF6ArV9wMw33eJ6nTCrPCl | AN94: https://www.facebook.com/share/p/1DJANHG2Hn/ | AO94: https://docs.google.com/forms/d/e/1FAIpQLSeM31tSuyZneTEUDOGf2nkk_AZW68MKp8quVRXZ9VKh955IBQ/viewform | AQ94: =IFERROR(__xludf.DUMMYFUNCTION("IF(IFERROR(VLOOKUP(A94, IMPORTRANGE(""https://docs.google.com/spreadsheets/d/1eazy315Oas8TkAoTsdzUl6gNf3VsnwZeSo-bRfkZzOs"", ""工作表1!A:B""), 2, FALSE), """") <> """", ""有縮圖"", ""無縮圖"")"),"無縮圖") -> 無縮圖
A95: JILI♡ | B95: 池尻愛梨 | C95: S05,S06 | E95: R26,R27 | F95: Coser | G95: 美少女戰士 | H95: R15 | I95: 二創 | J95: 寫真集 700元、寫真卡組 200元、徽章組 300元、壓克力立牌 550元、拍立得 / 自拍 300元 | L95: TRUE | M95: TRUE | N95: TRUE | O95: TRUE | Q95: {=IFERROR(INDEX('印量調查區'!G:G, MATCH(A95, '印量調查區'!A:A, 0)), "")} | R95: https://www.facebook.com/ikejiriairi | V95: https://x.com/ilovely1007_?fbclid=IwY2xjawPYW-VleHRuA2FlbQIxMABicmlkETFCQVJxMUtNWHlMcG5RMnhnc3J0YwZhcHBfaWQQMjIyMDM5MTc4ODIwMDg5MgABHjtcCqoyO7BLWrrV3jVYD0RlKNjIULYY4MhKIh8FXre6yKVLbTPK4KggijNk_aem_iaDhkFdX5MgmMabddyEKCg | AD95: https://www.instagram.com/ilovely1007_?fbclid=IwY2xjawPYW-xleHRuA2FlbQIxMABicmlkETFCQVJxMUtNWHlMcG5RMnhnc3J0YwZhcHBfaWQQMjIyMDM5MTc4ODIwMDg5MgABHnaUlvdnzlQ29z_ZZMtW9NVkRrmH5eTy8cklwPehNUBaY7Ykt5d4oUMmrd4E_aem_mcSZa9xvQI_TG1afoLvtow | AM95: https://www.facebook.com/ikejiriairi/posts/pfbid0kvotbLpMzY3c1roGxdeJ1jmGTgGRoyepNYzQuUzvXeBY8iDuLz1uZGYQgqmeZud3l?__cft__[0]=AZaDkI-g9Uf4k2JRV8RWwBz3SWpUGRnSiqzppPTQgTh4yh-q0tMtlQYU_ghB4qJgi7sz2e5Fbm9G-FPNF4jPHfkfpFDAetNms5oJ_6P5aOwCs-PN86Jj8pXZ_OJ9s4gskZpOtaujjoVAp9eSAwnJ9JW49UyuKzlW-0TrElwD-6OK1oWrHYOKHnMUtLnzzBw9iAw&__tn__=%2CO%2CP-R | AN95: https://www.facebook.com/photo/?fbid=1704105784244789&set=pcb.1704105817578119 | AQ95: =IFERROR(__xludf.DUMMYFUNCTION("IF(IFERROR(VLOOKUP(A95, IMPORTRANGE(""https://docs.google.com/spreadsheets/d/1eazy315Oas8TkAoTsdzUl6gNf3VsnwZeSo-bRfkZzOs"", ""工作表1!A:B""), 2, FALSE), """") <> """", ""有縮圖"", ""無縮圖"")"),"無縮圖") -> 無縮圖
A96: 這個名字有毒 | B96: 阿助,鞋帶,九尾貓 | D96: B14 | E96: N27,N28 | F96: 繪師 | G96: 重返未來1999，明日方舟，魔法少女的魔女裁判，鏈鋸人，超時空輝夜姬，MyGO!!!!!，Ave Mujica，崩壞星穹鐵道 / Honkai: Star Rail / 崩壊:スターレイル、箱箱、Vtuber | H96: 一般 | I96: 二創 | J96: 💠透明化妝包 120元 💠霧面消光鉛筆盒 130元 💠厚壓克力 80元 💠33毫米徽章 30元 💠44毫米徽章 40元 💠25毫米胸章藥片 120元 💠32毫米徽章 30元 💠吊卡吊飾 150元 💠厚壓克力 70元 💠沙包團子 180元/個 500元/3個 重返未來1999 💠沙包團子 180元 💠32毫米霧面徽章 30元 💠44毫米霧面徽章 40元 💠厚壓克力 60元 💠飲料杯套 100元 明日方舟 💠飲料手提袋 180元 💠44毫米徽章 40元 💠燙藍明信片&票根 50元 💠龍泡泡串吊飾 80元 💠龍泡泡徽章 30元/個 150元/6個 💠飲料杯套 10元 💠壓克力吊飾 80元 💠44毫米徽章 40元 💠壓克力立牌 350元 魔法少女的魔女裁判 💠44毫米徽章 40元 💠大帆布袋 250元 💠飲料杯套 100元 鏈鋸人 💠壓克力吊飾 60元 💠吊卡吊飾 135元 💠32毫米徽章 30元 💠壓克力吊飾 80元 超時空輝夜姬 💠32毫米徽章 30元 💠44毫米徽章 40元 箱箱 💠霧面徽章 40元 💠厚壓克力 80元 惡之系列 💠小立牌 300元 MyGO!!!!! Ave Mujica 💠沙包團子 180元/個 500元/3個 崩壞星穹鐵道 💠校園PARO拍立得 30元/張 50元/組 💠樹庭組全段貼紙 60元 | L96: TRUE | M96: TRUE | N96: TRUE | O96: TRUE | Q96: {=IFERROR(INDEX('印量調查區'!G:G, MATCH(A96, '印量調查區'!A:A, 0)), "")} | R96: https://www.facebook.com/ke.su.7524 | X96: https://www.plurk.com/pudding28033757 | AD96: IG | AE96: YOUTUBE | AF96: TWITCH | AH96: DISCORD | AI96: 巴哈姆特 | AJ96: https://www.doujin.com.tw/groups/info/7613/goods | AN96: https://www.facebook.com/ke.su.7524/posts/pfbid0M1dTApQfGmfBEuSQjp3XnVFDXYDxbpthzETwgkbshZjJVUPn6YeFcqMTmwPZHWGal | AQ96: =IFERROR(__xludf.DUMMYFUNCTION("IF(IFERROR(VLOOKUP(A96, IMPORTRANGE(""https://docs.google.com/spreadsheets/d/1eazy315Oas8TkAoTsdzUl6gNf3VsnwZeSo-bRfkZzOs"", ""工作表1!A:B""), 2, FALSE), """") <> """", ""有縮圖"", ""無縮圖"")"),"無縮圖") -> 無縮圖
A97: あるかみかど | C97: I24 | D97: I24 | F97: 繪師 | G97: 原神 | H97: R18 | J97: 抱枕：絲柯克師匠.雅珂達.檔案的教授跟場刊圖的SUZUMI | L97: TRUE | M97: TRUE | N97: FALSE | O97: TRUE | P97: 高 | Q97: {=IFERROR(INDEX('印量調查區'!G:G, MATCH(A97, '印量調查區'!A:A, 0)), "")} | R97: https://www.facebook.com/Arukamikad | V97: https://x.com/Arukamikad | X97: https://www.plurk.com/Kazuki_Sakurai | Z97: https://arukamikad.fanbox.cc/ | AM97: https://www.facebook.com/Arukamikad/posts/pfbid02UQpy3CNgthDGVsziuzqD79NSLEXPEhQJYJHYtzrW7a1V6rZfF6aRbbB7LhQSvJbZl | AN97: https://x.com/Arukamikad/status/2018631721336602688 | AQ97: =IFERROR(__xludf.DUMMYFUNCTION("IF(IFERROR(VLOOKUP(A97, IMPORTRANGE(""https://docs.google.com/spreadsheets/d/1eazy315Oas8TkAoTsdzUl6gNf3VsnwZeSo-bRfkZzOs"", ""工作表1!A:B""), 2, FALSE), """") <> """", ""有縮圖"", ""無縮圖"")"),"無縮圖") -> 無縮圖
A98: 愛肉通販 | C98: J11,J12 | E98: J13,J14 | F98: 代理社團 | G98: 原神 / Genshin Impact | H98: R18 | I98: 原創, 二創 | J98: 💠同人誌【祕密的戀情與學園祭】350元 💠同人誌既刊 200元-750元 💠同人誌【芙寧娜胡桃妊活紀錄】200元 | L98: TRUE | M98: TRUE | N98: FALSE | O98: TRUE | Q98: {=IFERROR(INDEX('印量調查區'!G:G, MATCH(A98, '印量調查區'!A:A, 0)), "")} | R98: https://www.facebook.com/erohonuriko/posts/pfbid0MFARNUqoSPvutgpBEfvHa3X42tjymk9aoXLm6CyudQhUpphHvyE5CowQzCEWTTAzl | V98: https://x.com/pox4231 | X98: https://www.plurk.com/erohon | Y98: PIXIV | AM98: https://www.plurk.com/p/3i4fkc8xr6 https://www.facebook.com/erohonuriko/posts/pfbid0MFARNUqoSPvutgpBEfvHa3X42tjymk9aoXLm6CyudQhUpphHvyE5CowQzCEWTTAzl | AN98: https://drive.google.com/file/d/1TJ-ks2jIdsROQp1gRIU6gOkAGsXEXw74/view?usp=sharing | AQ98: =IFERROR(__xludf.DUMMYFUNCTION("IF(IFERROR(VLOOKUP(A98, IMPORTRANGE(""https://docs.google.com/spreadsheets/d/1eazy315Oas8TkAoTsdzUl6gNf3VsnwZeSo-bRfkZzOs"", ""工作表1!A:B""), 2, FALSE), """") <> """", ""有縮圖"", ""無縮圖"")"),"有縮圖") -> 有縮圖
A99: Varlyn琳 | B99: Varlyn | C99: D37,D38 | D99: D04 [寄] | E99: D33,D34 | F99: 繪師 | G99: 原神 / Genshin Impact | H99: 一般 | I99: 二創 | J99: 哥倫比婭系列 💠 哥倫比婭三層大立牌 500 元 💠 哥倫比婭金屬鑰匙扣 350 元 💠 哥倫比婭飯友 200 元 💠 FF46 新品套組 (哥倫比婭系列) 1000 元 1️⃣ 哥倫比婭三層大立牌 2️⃣ 哥倫比婭金屬鑰匙扣 3️⃣ 哥倫比婭飯友 贈送：壓克力透卡 + 明信片 芙寧娜系列 💠 同人誌新刊《Lumine Echoes》 300 元 💠 芙寧娜金屬鑰匙扣 350 元 💠 芙寧娜飯友 200 元 💠 2025冬季新品套組800 元 1️⃣ 同人誌新刊《Lumine Echoes》 2️⃣ 芙寧娜金屬鑰匙扣 3️⃣ 芙寧娜飯友 贈送：壓克力透卡 | L99: TRUE | M99: TRUE | N99: TRUE | O99: TRUE | Q99: {=IFERROR(INDEX('印量調查區'!G:G, MATCH(A99, '印量調查區'!A:A, 0)), "")} | R99: https://www.facebook.com/chen.varlyn/ | V99: https://x.com/varlyn_art | Y99: https://www.pixiv.net/users/7270024 | Z99: https://varlyn.fanbox.cc/ | AK99: https://linktr.ee/Varlyn.art | AM99: https://www.facebook.com/chen.varlyn/posts/pfbid02Wmz36Q3uFk1euVt5pbwvNBGSeXq1CoJX2g4iGYTkNHLQGJfNDjeM1Fnu9QmsNwxvl | AN99: https://www.facebook.com/chen.varlyn/posts/pfbid02NDQbDoq5KByVJqwT4UmDwDVdgsGKaUxQTqBya8EuqhftS9LZ5DdemBQqk3VR7rVYl | AO99: https://myship.7-11.com.tw/general/detail/GM2412028188583 | AQ99: =IFERROR(__xludf.DUMMYFUNCTION("IF(IFERROR(VLOOKUP(A99, IMPORTRANGE(""https://docs.google.com/spreadsheets/d/1eazy315Oas8TkAoTsdzUl6gNf3VsnwZeSo-bRfkZzOs"", ""工作表1!A:B""), 2, FALSE), """") <> """", ""有縮圖"", ""無縮圖"")"),"有縮圖") -> 有縮圖
A100: まふゆ | C100: D39 | E100: C29,C30 | F100: 繪師 | G100: 原神 / Genshin Impact、崩壞星穹鐵道 / Honkai: Star Rail / 崩壊:スターレイル | H100: 一般 | I100: 二創 | J100: 💠新品全都要組A+B 600元 ▫️A：新品明信片1+2+3+4+5+6 150元，30元/張 ▫️B：新品吊飾 1+2+3+4 550元，150元/個 💠吊飾7CM(胡桃/知更鳥) 150元 💠立牌7CM(藿藿) 180元 💠飯友7CM(芙寧娜) 200元 💠芙寧娜立牌 350元 💠明信片 30元/張 💠競標掛軸 500起標 💠認親卡 | L100: TRUE | M100: TRUE | N100: FALSE | O100: TRUE | Q100: {=IFERROR(INDEX('印量調查區'!G:G, MATCH(A100, '印量調查區'!A:A, 0)), "")} | R100: https://www.facebook.com/neko.winter.9 | T100: https://bsky.app/profile/mafuyu2.bsky.social | V100: https://x.com/mistletoeouo | X100: https://www.plurk.com/mistletoeouo | Y100: https://www.pixiv.net/users/24106238 | AD100: https://www.instagram.com/_mafuyuuuuu_ | AE100: https://www.youtube.com/@_mafuyuuuuu_ | AF100: https://www.twitch.tv/mistletoeouo | AH100: https://discord.gg/3BSCj49jsM | AI100: https://home.gamer.com.tw/d0108i0080 | AK100: https://lit.link/mafuyuuu | AN100: https://www.facebook.com/share/p/1CQV9sNETE/ | AQ100: =IFERROR(__xludf.DUMMYFUNCTION("IF(IFERROR(VLOOKUP(A100, IMPORTRANGE(""https://docs.google.com/spreadsheets/d/1eazy315Oas8TkAoTsdzUl6gNf3VsnwZeSo-bRfkZzOs"", ""工作表1!A:B""), 2, FALSE), """") <> """", ""有縮圖"", ""無縮圖"")"),"無縮圖") -> 無縮圖
...

Sheet DAY2
A1: 攤位編號 | B1: 攤位名稱
A2: A01,A02 | B2: OriginZero
A3: A03 | B3: MAI
A4: A04 | B4: 心重力動漫工作室
A5: A05,A06 | B5: 蒼銀之星
A6: A07 | B6: 殺必死天國
A7: A08,A09 | B7: 闇夢館
A8: A10,A11 | B8: 三色坊
A9: A12 | B9: 有害蕈類集會所
A10: A13,A14 | B10: 箱庭交響曲
A11: A15 | B11: BsWs黑星白星
A12: A16 | B12: 黑蛛白蛛
... A309: J07,J08 | B309: 手創館
A310: J09,J10 | B310: =+喵耳園魔法道具屋+ -> #ERROR!
A311: J11 | B311: 三分糖手作中
A312: J12 | B312: 光影之下
A313: J13,J14 | B313: 艾宅團
A314: J15,J16 | B314: 薛頭的塞
A315: J17,J18 | B315: 狸奴小築
A316: J19,J20 | B316: ZAP製造所
A317: J21,J22 | B317: 克特小舖
A318: J23,J24 | B318: 好惠圖屋
A319: J25 | B319: 波比好朋友
A320: J26 | B320: 全麥醬子
A321: J27 | B321: 模型優創
A322: J28 | B322: ブルーブルルー
... A657: T07 | B657: 芙米是一隻小米蟲
A658: T08 | B658: 825
A659: T09 | B659: Nao Cosplay
A660: T10 | B660: 阿璇Xuan
A661: T11 | B661: 豬視會攝Studio
A662: T12 | B662: 雙糖＊糖霜
A663: T13 | B663: 狐川_kitsunekawa
A664: T14 | B664: みゆき·Miyuki
A665: T15,T16 | B665: Shey雪依
A666: T17 | B666: 小熊貓工作室
A667: T18 | B667: 天使堡佑
A668: T19 | B668: 容子
A669: T20 | B669: Meikoです
A670: T21,T22 | B670: Helene海琳
... A783: W41,W42 | B783: 雨波HaneAme

Sheet DAY3
B1: 攤位名稱
A2: A01,A02 | B2: OriginZero
A3: A03,A04 | B3: 蒼銀之星
A4: A05,A06 | B4: 御狐亭
A5: A07,A08 | B5: 箱庭交響曲
A6: A09,A10 | B6: DSP國際
A7: A11 | B7: Cabbage_ex 白菜滷
A8: A12 | B8: Xamu ArtWorks
A9: A13 | B9: 楓糖藍莓塔
A10: A14 | B10: 7B鉛筆
A11: A15 | B11: AIZAWA 藍沢津
A12: A16 | B12: NC731
A13: A17 | B13: curry and rice(咖哩飯)
... A674: U42 | B674: 自由黑貓的紙箱
A675: U43 | B675: 2.5
A676: U44 | B676: 小菊小花園
A677: V01,V02 | B677: 大幼蟲
A678: V03,V04 | B678: MIBRY
A679: V05,V06 | B679: 千煂+BS
A680: V07 | B680: 瑠璃瑠璃企画
A681: V08 | B681: 蘿蔔農學院
A682: V09,V10 | B682: 貓專用牛乳
A683: V11 | B683: 卯時日和
A684: V12 | B684: 小白鹿 WHITE DEER
A685: V13 | B685: 陪騎的快樂小舖
A686: V14 | B686: 黑嚕嚕的六華貓
A687: V15,V16 | B687: 貓咪窩
... A732: W41,W42 | B732: 雨波HaneAme
